Workbook

Sheet Dashboard
A1: Inventory & Supplier Dashboard: Corrib Medical Devices
A2: Snapshot 30-Sep-2026. All figures are live formulas; change the Assumptions sheet to run scenarios.
A4: Inventory value | D4: Excess stock value | G4: SKUs below safety stock | J4: SKUs to reorder now
A5: =SUM(Inventory_Policy!$AB$5:$AB$120) | D5: =SUM(Inventory_Policy!$AC$5:$AC$120) | G5: =COUNTIF(Inventory_Policy!$AA$5:$AA$120,"Below safety stock") | J5: =COUNTIF(Inventory_Policy!$AA$5:$AA$120,"Reorder now")
A7: Supplier OTIF (weighted) | D7: FY purchase variance | G7: of which price variance
A8: =Supplier_Scorecard!J17 | D8: =Budget_vs_Actual!D57 | G8: =Budget_vs_Actual!F57
A10: ABC classification | F10: Stock status | K10: ABC-XYZ matrix (SKU count)
A11: Class | B11: SKUs | C11: % of SKUs | D11: % of spend | F11: Status | G11: SKUs | H11: Stock value (€) | I11: Excess (€) | K11: ABC \ XYZ | L11: X stable | M11: Y variable | N11: Z erratic
A12: A | B12: =COUNTIF(Inventory_Policy!$L$5:$L$120,A12) | C12: =B12/SUM($B$12:$B$14) | D12: =SUMIF(Inventory_Policy!$L$5:$L$120,A12,Inventory_Policy!$J$5:$J$120)/SUM(Inventory_Policy!$J$5:$J$120) | F12: Below safety stock | G12: =COUNTIF(Inventory_Policy!$AA$5:$AA$120,F12) | H12: =SUMIF(Inventory_Policy!$AA$5:$AA$120,F12,Inventory_Policy!$AB$5:$AB$120) | I12: =SUMIF(Inventory_Policy!$AA$5:$AA$120,F12,Inventory_Policy!$AC$5:$AC$120) | K12: A | L12: =COUNTIF(Inventory_Policy!$N$5:$N$120,"AX") | M12: =COUNTIF(Inventory_Policy!$N$5:$N$120,"AY") | N12: =COUNTIF(Inventory_Policy!$N$5:$N$120,"AZ")
A13: B | B13: =COUNTIF(Inventory_Policy!$L$5:$L$120,A13) | C13: =B13/SUM($B$12:$B$14) | D13: =SUMIF(Inventory_Policy!$L$5:$L$120,A13,Inventory_Policy!$J$5:$J$120)/SUM(Inventory_Policy!$J$5:$J$120) | F13: Reorder now | G13: =COUNTIF(Inventory_Policy!$AA$5:$AA$120,F13) | H13: =SUMIF(Inventory_Policy!$AA$5:$AA$120,F13,Inventory_Policy!$AB$5:$AB$120) | I13: =SUMIF(Inventory_Policy!$AA$5:$AA$120,F13,Inventory_Policy!$AC$5:$AC$120) | K13: B | L13: =COUNTIF(Inventory_Policy!$N$5:$N$120,"BX") | M13: =COUNTIF(Inventory_Policy!$N$5:$N$120,"BY") | N13: =COUNTIF(Inventory_Policy!$N$5:$N$120,"BZ")
A14: C | B14: =COUNTIF(Inventory_Policy!$L$5:$L$120,A14) | C14: =B14/SUM($B$12:$B$14) | D14: =SUMIF(Inventory_Policy!$L$5:$L$120,A14,Inventory_Policy!$J$5:$J$120)/SUM(Inventory_Policy!$J$5:$J$120) | F14: Healthy | G14: =COUNTIF(Inventory_Policy!$AA$5:$AA$120,F14) | H14: =SUMIF(Inventory_Policy!$AA$5:$AA$120,F14,Inventory_Policy!$AB$5:$AB$120) | I14: =SUMIF(Inventory_Policy!$AA$5:$AA$120,F14,Inventory_Policy!$AC$5:$AC$120) | K14: C | L14: =COUNTIF(Inventory_Policy!$N$5:$N$120,"CX") | M14: =COUNTIF(Inventory_Policy!$N$5:$N$120,"CY") | N14: =COUNTIF(Inventory_Policy!$N$5:$N$120,"CZ")
F15: Excess | G15: =COUNTIF(Inventory_Policy!$AA$5:$AA$120,F15) | H15: =SUMIF(Inventory_Policy!$AA$5:$AA$120,F15,Inventory_Policy!$AB$5:$AB$120) | I15: =SUMIF(Inventory_Policy!$AA$5:$AA$120,F15,Inventory_Policy!$AC$5:$AC$120)
A17: Top 10 excess stock (€) | F17: Top 10 shortfall vs reorder point (€) | K17: SKU lookup: pick a SKU
A18: SKU | B18: Description | C18: Supplier | D18: Value (€) | F18: SKU | G18: Description | H18: Supplier | I18: Value (€) | K18: Selected SKU | L18: CMD-0001
A19: =IF(D19=0,"",INDEX(Inventory_Policy!$A$5:$A$120,MATCH(D19,Inventory_Policy!$AC$5:$AC$120,0))) | B19: =IF(D19=0,"",INDEX(Inventory_Policy!$B$5:$B$120,MATCH(D19,Inventory_Policy!$AC$5:$AC$120,0))) | C19: =IF(D19=0,"",INDEX(Inventory_Policy!$D$5:$D$120,MATCH(D19,Inventory_Policy!$AC$5:$AC$120,0))) | D19: =LARGE(Inventory_Policy!$AC$5:$AC$120,1) | F19: =IF(I19=0,"",INDEX(Inventory_Policy!$A$5:$A$120,MATCH(I19,Inventory_Policy!$AE$5:$AE$120,0))) | G19: =IF(I19=0,"",INDEX(Inventory_Policy!$B$5:$B$120,MATCH(I19,Inventory_Policy!$AE$5:$AE$120,0))) | H19: =IF(I19=0,"",INDEX(Inventory_Policy!$D$5:$D$120,MATCH(I19,Inventory_Policy!$AE$5:$AE$120,0))) | I19: =LARGE(Inventory_Policy!$AE$5:$AE$120,1) | K19: Description | L19: =INDEX(Inventory_Policy!$B$5:$B$120,MATCH($L$18,Inventory_Policy!$A$5:$A$120,0))
A20: =IF(D20=0,"",INDEX(Inventory_Policy!$A$5:$A$120,MATCH(D20,Inventory_Policy!$AC$5:$AC$120,0))) | B20: =IF(D20=0,"",INDEX(Inventory_Policy!$B$5:$B$120,MATCH(D20,Inventory_Policy!$AC$5:$AC$120,0))) | C20: =IF(D20=0,"",INDEX(Inventory_Policy!$D$5:$D$120,MATCH(D20,Inventory_Policy!$AC$5:$AC$120,0))) | D20: =LARGE(Inventory_Policy!$AC$5:$AC$120,2) | F20: =IF(I20=0,"",INDEX(Inventory_Policy!$A$5:$A$120,MATCH(I20,Inventory_Policy!$AE$5:$AE$120,0))) | G20: =IF(I20=0,"",INDEX(Inventory_Policy!$B$5:$B$120,MATCH(I20,Inventory_Policy!$AE$5:$AE$120,0))) | H20: =IF(I20=0,"",INDEX(Inventory_Policy!$D$5:$D$120,MATCH(I20,Inventory_Policy!$AE$5:$AE$120,0))) | I20: =LARGE(Inventory_Policy!$AE$5:$AE$120,2) | K20: Category | L20: =INDEX(Inventory_Policy!$C$5:$C$120,MATCH($L$18,Inventory_Policy!$A$5:$A$120,0))
A21: =IF(D21=0,"",INDEX(Inventory_Policy!$A$5:$A$120,MATCH(D21,Inventory_Policy!$AC$5:$AC$120,0))) | B21: =IF(D21=0,"",INDEX(Inventory_Policy!$B$5:$B$120,MATCH(D21,Inventory_Policy!$AC$5:$AC$120,0))) | C21: =IF(D21=0,"",INDEX(Inventory_Policy!$D$5:$D$120,MATCH(D21,Inventory_Policy!$AC$5:$AC$120,0))) | D21: =LARGE(Inventory_Policy!$AC$5:$AC$120,3) | F21: =IF(I21=0,"",INDEX(Inventory_Policy!$A$5:$A$120,MATCH(I21,Inventory_Policy!$AE$5:$AE$120,0))) | G21: =IF(I21=0,"",INDEX(Inventory_Policy!$B$5:$B$120,MATCH(I21,Inventory_Policy!$AE$5:$AE$120,0))) | H21: =IF(I21=0,"",INDEX(Inventory_Policy!$D$5:$D$120,MATCH(I21,Inventory_Policy!$AE$5:$AE$120,0))) | I21: =LARGE(Inventory_Policy!$AE$5:$AE$120,3) | K21: Supplier | L21: =INDEX(Inventory_Policy!$D$5:$D$120,MATCH($L$18,Inventory_Policy!$A$5:$A$120,0))
A22: =IF(D22=0,"",INDEX(Inventory_Policy!$A$5:$A$120,MATCH(D22,Inventory_Policy!$AC$5:$AC$120,0))) | B22: =IF(D22=0,"",INDEX(Inventory_Policy!$B$5:$B$120,MATCH(D22,Inventory_Policy!$AC$5:$AC$120,0))) | C22: =IF(D22=0,"",INDEX(Inventory_Policy!$D$5:$D$120,MATCH(D22,Inventory_Policy!$AC$5:$AC$120,0))) | D22: =LARGE(Inventory_Policy!$AC$5:$AC$120,4) | F22: =IF(I22=0,"",INDEX(Inventory_Policy!$A$5:$A$120,MATCH(I22,Inventory_Policy!$AE$5:$AE$120,0))) | G22: =IF(I22=0,"",INDEX(Inventory_Policy!$B$5:$B$120,MATCH(I22,Inventory_Policy!$AE$5:$AE$120,0))) | H22: =IF(I22=0,"",INDEX(Inventory_Policy!$D$5:$D$120,MATCH(I22,Inventory_Policy!$AE$5:$AE$120,0))) | I22: =LARGE(Inventory_Policy!$AE$5:$AE$120,4) | K22: ABC-XYZ | L22: =INDEX(Inventory_Policy!$N$5:$N$120,MATCH($L$18,Inventory_Policy!$A$5:$A$120,0))
A23: =IF(D23=0,"",INDEX(Inventory_Policy!$A$5:$A$120,MATCH(D23,Inventory_Policy!$AC$5:$AC$120,0))) | B23: =IF(D23=0,"",INDEX(Inventory_Policy!$B$5:$B$120,MATCH(D23,Inventory_Policy!$AC$5:$AC$120,0))) | C23: =IF(D23=0,"",INDEX(Inventory_Policy!$D$5:$D$120,MATCH(D23,Inventory_Policy!$AC$5:$AC$120,0))) | D23: =LARGE(Inventory_Policy!$AC$5:$AC$120,5) | F23: =IF(I23=0,"",INDEX(Inventory_Policy!$A$5:$A$120,MATCH(I23,Inventory_Policy!$AE$5:$AE$120,0))) | G23: =IF(I23=0,"",INDEX(Inventory_Policy!$B$5:$B$120,MATCH(I23,Inventory_Policy!$AE$5:$AE$120,0))) | H23: =IF(I23=0,"",INDEX(Inventory_Policy!$D$5:$D$120,MATCH(I23,Inventory_Policy!$AE$5:$AE$120,0))) | I23: =LARGE(Inventory_Policy!$AE$5:$AE$120,5) | K23: Avg monthly demand | L23: =INDEX(Inventory_Policy!$G$5:$G$120,MATCH($L$18,Inventory_Policy!$A$5:$A$120,0))
A24: =IF(D24=0,"",INDEX(Inventory_Policy!$A$5:$A$120,MATCH(D24,Inventory_Policy!$AC$5:$AC$120,0))) | B24: =IF(D24=0,"",INDEX(Inventory_Policy!$B$5:$B$120,MATCH(D24,Inventory_Policy!$AC$5:$AC$120,0))) | C24: =IF(D24=0,"",INDEX(Inventory_Policy!$D$5:$D$120,MATCH(D24,Inventory_Policy!$AC$5:$AC$120,0))) | D24: =LARGE(Inventory_Policy!$AC$5:$AC$120,6) | F24: =IF(I24=0,"",INDEX(Inventory_Policy!$A$5:$A$120,MATCH(I24,Inventory_Policy!$AE$5:$AE$120,0))) | G24: =IF(I24=0,"",INDEX(Inventory_Policy!$B$5:$B$120,MATCH(I24,Inventory_Policy!$AE$5:$AE$120,0))) | H24: =IF(I24=0,"",INDEX(Inventory_Policy!$D$5:$D$120,MATCH(I24,Inventory_Policy!$AE$5:$AE$120,0))) | I24: =LARGE(Inventory_Policy!$AE$5:$AE$120,6) | K24: Actual lead time (days) | L24: =INDEX(Inventory_Policy!$Q$5:$Q$120,MATCH($L$18,Inventory_Policy!$A$5:$A$120,0))
A25: =IF(D25=0,"",INDEX(Inventory_Policy!$A$5:$A$120,MATCH(D25,Inventory_Policy!$AC$5:$AC$120,0))) | B25: =IF(D25=0,"",INDEX(Inventory_Policy!$B$5:$B$120,MATCH(D25,Inventory_Policy!$AC$5:$AC$120,0))) | C25: =IF(D25=0,"",INDEX(Inventory_Policy!$D$5:$D$120,MATCH(D25,Inventory_Policy!$AC$5:$AC$120,0))) | D25: =LARGE(Inventory_Policy!$AC$5:$AC$120,7) | F25: =IF(I25=0,"",INDEX(Inventory_Policy!$A$5:$A$120,MATCH(I25,Inventory_Policy!$AE$5:$AE$120,0))) | G25: =IF(I25=0,"",INDEX(Inventory_Policy!$B$5:$B$120,MATCH(I25,Inventory_Policy!$AE$5:$AE$120,0))) | H25: =IF(I25=0,"",INDEX(Inventory_Policy!$D$5:$D$120,MATCH(I25,Inventory_Policy!$AE$5:$AE$120,0))) | I25: =LARGE(Inventory_Policy!$AE$5:$AE$120,7) | K25: Safety stock | L25: =INDEX(Inventory_Policy!$S$5:$S$120,MATCH($L$18,Inventory_Policy!$A$5:$A$120,0))
A26: =IF(D26=0,"",INDEX(Inventory_Policy!$A$5:$A$120,MATCH(D26,Inventory_Policy!$AC$5:$AC$120,0))) | B26: =IF(D26=0,"",INDEX(Inventory_Policy!$B$5:$B$120,MATCH(D26,Inventory_Policy!$AC$5:$AC$120,0))) | C26: =IF(D26=0,"",INDEX(Inventory_Policy!$D$5:$D$120,MATCH(D26,Inventory_Policy!$AC$5:$AC$120,0))) | D26: =LARGE(Inventory_Policy!$AC$5:$AC$120,8) | F26: =IF(I26=0,"",INDEX(Inventory_Policy!$A$5:$A$120,MATCH(I26,Inventory_Policy!$AE$5:$AE$120,0))) | G26: =IF(I26=0,"",INDEX(Inventory_Policy!$B$5:$B$120,MATCH(I26,Inventory_Policy!$AE$5:$AE$120,0))) | H26: =IF(I26=0,"",INDEX(Inventory_Policy!$D$5:$D$120,MATCH(I26,Inventory_Policy!$AE$5:$AE$120,0))) | I26: =LARGE(Inventory_Policy!$AE$5:$AE$120,8) | K26: Reorder point | L26: =INDEX(Inventory_Policy!$T$5:$T$120,MATCH($L$18,Inventory_Policy!$A$5:$A$120,0))
A27: =IF(D27=0,"",INDEX(Inventory_Policy!$A$5:$A$120,MATCH(D27,Inventory_Policy!$AC$5:$AC$120,0))) | B27: =IF(D27=0,"",INDEX(Inventory_Policy!$B$5:$B$120,MATCH(D27,Inventory_Policy!$AC$5:$AC$120,0))) | C27: =IF(D27=0,"",INDEX(Inventory_Policy!$D$5:$D$120,MATCH(D27,Inventory_Policy!$AC$5:$AC$120,0))) | D27: =LARGE(Inventory_Policy!$AC$5:$AC$120,9) | F27: =IF(I27=0,"",INDEX(Inventory_Policy!$A$5:$A$120,MATCH(I27,Inventory_Policy!$AE$5:$AE$120,0))) | G27: =IF(I27=0,"",INDEX(Inventory_Policy!$B$5:$B$120,MATCH(I27,Inventory_Policy!$AE$5:$AE$120,0))) | H27: =IF(I27=0,"",INDEX(Inventory_Policy!$D$5:$D$120,MATCH(I27,Inventory_Policy!$AE$5:$AE$120,0))) | I27: =LARGE(Inventory_Policy!$AE$5:$AE$120,9) | K27: Order quantity | L27: =INDEX(Inventory_Policy!$U$5:$U$120,MATCH($L$18,Inventory_Policy!$A$5:$A$120,0))
A28: =IF(D28=0,"",INDEX(Inventory_Policy!$A$5:$A$120,MATCH(D28,Inventory_Policy!$AC$5:$AC$120,0))) | B28: =IF(D28=0,"",INDEX(Inventory_Policy!$B$5:$B$120,MATCH(D28,Inventory_Policy!$AC$5:$AC$120,0))) | C28: =IF(D28=0,"",INDEX(Inventory_Policy!$D$5:$D$120,MATCH(D28,Inventory_Policy!$AC$5:$AC$120,0))) | D28: =LARGE(Inventory_Policy!$AC$5:$AC$120,10) | F28: =IF(I28=0,"",INDEX(Inventory_Policy!$A$5:$A$120,MATCH(I28,Inventory_Policy!$AE$5:$AE$120,0))) | G28: =IF(I28=0,"",INDEX(Inventory_Policy!$B$5:$B$120,MATCH(I28,Inventory_Policy!$AE$5:$AE$120,0))) | H28: =IF(I28=0,"",INDEX(Inventory_Policy!$D$5:$D$120,MATCH(I28,Inventory_Policy!$AE$5:$AE$120,0))) | I28: =LARGE(Inventory_Policy!$AE$5:$AE$120,10) | K28: On hand | L28: =INDEX(Inventory_Policy!$V$5:$V$120,MATCH($L$18,Inventory_Policy!$A$5:$A$120,0))
K29: On order | L29: =INDEX(Inventory_Policy!$W$5:$W$120,MATCH($L$18,Inventory_Policy!$A$5:$A$120,0))
K30: Days of cover | L30: =INDEX(Inventory_Policy!$Y$5:$Y$120,MATCH($L$18,Inventory_Policy!$A$5:$A$120,0))
K31: Status | L31: =INDEX(Inventory_Policy!$AA$5:$AA$120,MATCH($L$18,Inventory_Policy!$A$5:$A$120,0))
K32: Suggested order qty | L32: =INDEX(Inventory_Policy!$AD$5:$AD$120,MATCH($L$18,Inventory_Policy!$A$5:$A$120,0))
A55: Chart data (feeds the charts above)
A56: Supplier | B56: OTIF % | F56: Month | G56: Budget (€) | H56: Actual (€)
A57: =Supplier_Scorecard!B5 | B57: =Supplier_Scorecard!J5 | F57: 2025-10 | G57: =Budget_vs_Actual!B15 | H57: =Budget_vs_Actual!B29
A58: =Supplier_Scorecard!B6 | B58: =Supplier_Scorecard!J6 | F58: 2025-11 | G58: =Budget_vs_Actual!C15 | H58: =Budget_vs_Actual!C29
A59: =Supplier_Scorecard!B7 | B59: =Supplier_Scorecard!J7 | F59: 2025-12 | G59: =Budget_vs_Actual!D15 | H59: =Budget_vs_Actual!D29
A60: =Supplier_Scorecard!B8 | B60: =Supplier_Scorecard!J8 | F60: 2026-01 | G60: =Budget_vs_Actual!E15 | H60: =Budget_vs_Actual!E29
A61: =Supplier_Scorecard!B9 | B61: =Supplier_Scorecard!J9 | F61: 2026-02 | G61: =Budget_vs_Actual!F15 | H61: =Budget_vs_Actual!F29
A62: =Supplier_Scorecard!B10 | B62: =Supplier_Scorecard!J10 | F62: 2026-03 | G62: =Budget_vs_Actual!G15 | H62: =Budget_vs_Actual!G29
A63: =Supplier_Scorecard!B11 | B63: =Supplier_Scorecard!J11 | F63: 2026-04 | G63: =Budget_vs_Actual!H15 | H63: =Budget_vs_Actual!H29
A64: =Supplier_Scorecard!B12 | B64: =Supplier_Scorecard!J12 | F64: 2026-05 | G64: =Budget_vs_Actual!I15 | H64: =Budget_vs_Actual!I29
A65: =Supplier_Scorecard!B13 | B65: =Supplier_Scorecard!J13 | F65: 2026-06 | G65: =Budget_vs_Actual!J15 | H65: =Budget_vs_Actual!J29
A66: =Supplier_Scorecard!B14 | B66: =Supplier_Scorecard!J14 | F66: 2026-07 | G66: =Budget_vs_Actual!K15 | H66: =Budget_vs_Actual!K29
A67: =Supplier_Scorecard!B15 | B67: =Supplier_Scorecard!J15 | F67: 2026-08 | G67: =Budget_vs_Actual!L15 | H67: =Budget_vs_Actual!L29
A68: =Supplier_Scorecard!B16 | B68: =Supplier_Scorecard!J16 | F68: 2026-09 | G68: =Budget_vs_Actual!M15 | H68: =Budget_vs_Actual!M29

Sheet README
A1: Corrib Medical Devices: Component Inventory & Supplier Model
A2: Simulated data for a fictional Galway medtech manufacturer (patient monitors, wearable ECG patches, infusion pumps)
A4: Purpose | B4: Set inventory policy (safety stock, reorder point, order quantity) for 116 electronic and packaging components, find excess and shortage risk, score suppliers, and explain budget variance.
A5: How to use | B5: Change any yellow cell on the 'Assumptions' sheet (service levels, holding cost, thresholds). Every analysis sheet recalculates. Use the SKU selector on the 'Dashboard' to inspect any part.
A6: Sheets | B6: Dashboard: KPIs, charts, SKU lookup | Inventory_Policy: ABC/XYZ, safety stock, ROP, EOQ, status | Supplier_Scorecard: OTIF, rejects, lead times | Budget_vs_Actual: monthly variance with price/volume split | Assumptions | Data sheets: Items, Demand, PO_Lines, Stock_Snapshot, Suppliers
A7: Colour legend | B7: Blue text = hard-coded input | Black text = formula | Yellow fill = key assumption you can change
A8: Method | B8: ABC by 12-month spend (Pareto). XYZ by coefficient of variation of monthly demand. Safety stock = z x sqrt(LT x sd_demand^2 + demand^2 x sd_LT^2) using actual supplier lead times. ROP = demand during lead time + safety stock. Order qty = largest of EOQ (sqrt(2 x annual demand x order cost / holding cost per unit)), supplier MOQ and minimum order cover. Excess = stock above safety stock + one order quantity.
A9: Data | B9: All data is simulated (see src/generate_data.py) and the company is fictional. Snapshot date 30-Sep-2026; 24 months of consumption; 2,026 purchase order lines.

Sheet Inventory_Policy
A1: Inventory Policy by SKU
A2: ABC/XYZ classification, safety stock, reorder point, EOQ and stock status. All cells are formulas driven by the Assumptions sheet.
A4: SKU | B4: Description | C4: Category | D4: Supplier | E4: Unit cost (€) | F4: Annual usage (units) | G4: Avg monthly demand | H4: Std dev monthly | I4: CV | J4: Annual spend (€) | K4: Cumulative spend % | L4: ABC | M4: XYZ | N4: ABC-XYZ | O4: Service level | P4: z | Q4: Avg actual lead time (days) | R4: Lead time std dev (days) | S4: Safety stock (units) | T4: Reorder point (units) | U4: Order qty (EOQ, MOQ, min cover) | V4: On hand (units) | W4: On order (units) | X4: Inventory position | Y4: Days of cover | Z4: Max stock (SS + order qty) | AA4: Stock status | AB4: Stock value (€) | AC4: Excess value (€) | AD4: Suggested order qty | AE4: Shortfall vs ROP (€) | AF4: Oldest lot expiry | AG4: Expiry flag
A5: CMD-0001 | B5: =INDEX(Items!$B$2:$B$117,MATCH($A5,Items!$A$2:$A$117,0)) | C5: =INDEX(Items!$C$2:$C$117,MATCH($A5,Items!$A$2:$A$117,0)) | D5: =INDEX(Items!$D$2:$D$117,MATCH($A5,Items!$A$2:$A$117,0)) | E5: =INDEX(Items!$E$2:$E$117,MATCH($A5,Items!$A$2:$A$117,0)) | F5: =SUM(INDEX(Demand!$N$2:$Y$117,MATCH($A5,Demand!$A$2:$A$117,0),0)) | G5: =F5/12 | H5: =STDEV(INDEX(Demand!$N$2:$Y$117,MATCH($A5,Demand!$A$2:$A$117,0),0)) | I5: =IF(G5>0,H5/G5,0) | J5: =F5*E5 | K5: =SUMIF($J$5:$J$120,">="&J5)/SUM($J$5:$J$120) | L5: =IF(K5<=Assumptions!$B$7,"A",IF(K5<=Assumptions!$B$8,"B","C")) | M5: =IF(I5<=Assumptions!$B$9,"X",IF(I5<=Assumptions!$B$10,"Y","Z")) | N5: =L5&M5 | O5: =INDEX(Assumptions!$F$4:$F$6,MATCH(L5,Assumptions!$E$4:$E$6,0)) | P5: =NORMSINV(O5) | Q5: =IFERROR(AVERAGEIFS(PO_Lines!$R$2:$R$2025,PO_Lines!$B$2:$B$2025,$A5,PO_Lines!$Q$2:$Q$2025,1),INDEX(Items!$F$2:$F$117,MATCH($A5,Items!$A$2:$A$117,0))) | R5: =IFERROR(SQRT(SUMPRODUCT((PO_Lines!$B$2:$B$2025=$A5)*PO_Lines!$Q$2:$Q$2025*(PO_Lines!$R$2:$R$2025-Q5)^2)/(COUNTIFS(PO_Lines!$B$2:$B$2025,$A5,PO_Lines!$Q$2:$Q$2025,1)-1)),0) | S5: =ROUNDUP(P5*SQRT((Q5/Assumptions!$B$11)*H5^2+G5^2*(R5/Assumptions!$B$11)^2),0) | T5: =ROUNDUP(G5*Q5/Assumptions!$B$11+S5,0) | U5: =ROUNDUP(MAX(INDEX(Items!$G$2:$G$117,MATCH($A5,Items!$A$2:$A$117,0)),SQRT(2*F5*Assumptions!$B$5/(Assumptions!$B$6*E5)),G5*Assumptions!$B$16),0) | V5: =INDEX(Stock_Snapshot!$B$2:$B$117,MATCH($A5,Stock_Snapshot!$A$2:$A$117,0)) | W5: =INDEX(Stock_Snapshot!$C$2:$C$117,MATCH($A5,Stock_Snapshot!$A$2:$A$117,0)) | X5: =V5+W5 | Y5: =IF(G5>0,V5/(G5/Assumptions!$B$11),999) | Z5: =S5+U5 | AA5: =IF(V5<S5,"Below safety stock",IF(X5<=T5,"Reorder now",IF(V5>Z5,"Excess","Healthy"))) | AB5: =V5*E5 | AC5: =MAX(0,V5-Z5)*E5 | AD5: =IF(X5<=T5,ROUNDUP(T5+U5-X5,0),0) | AE5: =MAX(0,T5-X5)*E5 | AF5: =IF(INDEX(Stock_Snapshot!$D$2:$D$117,MATCH($A5,Stock_Snapshot!$A$2:$A$117,0))="","",INDEX(Stock_Snapshot!$D$2:$D$117,MATCH($A5,Stock_Snapshot!$A$2:$A$117,0))) | AG5: =IF(AF5="","",IF(AF5<=EDATE(Assumptions!$B$4,Assumptions!$B$12),"Expires < "&Assumptions!$B$12&" m","OK"))
A6: CMD-0002 | B6: =INDEX(Items!$B$2:$B$117,MATCH($A6,Items!$A$2:$A$117,0)) | C6: =INDEX(Items!$C$2:$C$117,MATCH($A6,Items!$A$2:$A$117,0)) | D6: =INDEX(Items!$D$2:$D$117,MATCH($A6,Items!$A$2:$A$117,0)) | E6: =INDEX(Items!$E$2:$E$117,MATCH($A6,Items!$A$2:$A$117,0)) | F6: =SUM(INDEX(Demand!$N$2:$Y$117,MATCH($A6,Demand!$A$2:$A$117,0),0)) | G6: =F6/12 | H6: =STDEV(INDEX(Demand!$N$2:$Y$117,MATCH($A6,Demand!$A$2:$A$117,0),0)) | I6: =IF(G6>0,H6/G6,0) | J6: =F6*E6 | K6: =SUMIF($J$5:$J$120,">="&J6)/SUM($J$5:$J$120) | L6: =IF(K6<=Assumptions!$B$7,"A",IF(K6<=Assumptions!$B$8,"B","C")) | M6: =IF(I6<=Assumptions!$B$9,"X",IF(I6<=Assumptions!$B$10,"Y","Z")) | N6: =L6&M6 | O6: =INDEX(Assumptions!$F$4:$F$6,MATCH(L6,Assumptions!$E$4:$E$6,0)) | P6: =NORMSINV(O6) | Q6: =IFERROR(AVERAGEIFS(PO_Lines!$R$2:$R$2025,PO_Lines!$B$2:$B$2025,$A6,PO_Lines!$Q$2:$Q$2025,1),INDEX(Items!$F$2:$F$117,MATCH($A6,Items!$A$2:$A$117,0))) | R6: =IFERROR(SQRT(SUMPRODUCT((PO_Lines!$B$2:$B$2025=$A6)*PO_Lines!$Q$2:$Q$2025*(PO_Lines!$R$2:$R$2025-Q6)^2)/(COUNTIFS(PO_Lines!$B$2:$B$2025,$A6,PO_Lines!$Q$2:$Q$2025,1)-1)),0) | S6: =ROUNDUP(P6*SQRT((Q6/Assumptions!$B$11)*H6^2+G6^2*(R6/Assumptions!$B$11)^2),0) | T6: =ROUNDUP(G6*Q6/Assumptions!$B$11+S6,0) | U6: =ROUNDUP(MAX(INDEX(Items!$G$2:$G$117,MATCH($A6,Items!$A$2:$A$117,0)),SQRT(2*F6*Assumptions!$B$5/(Assumptions!$B$6*E6)),G6*Assumptions!$B$16),0) | V6: =INDEX(Stock_Snapshot!$B$2:$B$117,MATCH($A6,Stock_Snapshot!$A$2:$A$117,0)) | W6: =INDEX(Stock_Snapshot!$C$2:$C$117,MATCH($A6,Stock_Snapshot!$A$2:$A$117,0)) | X6: =V6+W6 | Y6: =IF(G6>0,V6/(G6/Assumptions!$B$11),999) | Z6: =S6+U6 | AA6: =IF(V6<S6,"Below safety stock",IF(X6<=T6,"Reorder now",IF(V6>Z6,"Excess","Healthy"))) | AB6: =V6*E6 | AC6: =MAX(0,V6-Z6)*E6 | AD6: =IF(X6<=T6,ROUNDUP(T6+U6-X6,0),0) | AE6: =MAX(0,T6-X6)*E6 | AF6: =IF(INDEX(Stock_Snapshot!$D$2:$D$117,MATCH($A6,Stock_Snapshot!$A$2:$A$117,0))="","",INDEX(Stock_Snapshot!$D$2:$D$117,MATCH($A6,Stock_Snapshot!$A$2:$A$117,0))) | AG6: =IF(AF6="","",IF(AF6<=EDATE(Assumptions!$B$4,Assumptions!$B$12),"Expires < "&Assumptions!$B$12&" m","OK"))
A7: CMD-0003 | B7: =INDEX(Items!$B$2:$B$117,MATCH($A7,Items!$A$2:$A$117,0)) | C7: =INDEX(Items!$C$2:$C$117,MATCH($A7,Items!$A$2:$A$117,0)) | D7: =INDEX(Items!$D$2:$D$117,MATCH($A7,Items!$A$2:$A$117,0)) | E7: =INDEX(Items!$E$2:$E$117,MATCH($A7,Items!$A$2:$A$117,0)) | F7: =SUM(INDEX(Demand!$N$2:$Y$117,MATCH($A7,Demand!$A$2:$A$117,0),0)) | G7: =F7/12 | H7: =STDEV(INDEX(Demand!$N$2:$Y$117,MATCH($A7,Demand!$A$2:$A$117,0),0)) | I7: =IF(G7>0,H7/G7,0) | J7: =F7*E7 | K7: =SUMIF($J$5:$J$120,">="&J7)/SUM($J$5:$J$120) | L7: =IF(K7<=Assumptions!$B$7,"A",IF(K7<=Assumptions!$B$8,"B","C")) | M7: =IF(I7<=Assumptions!$B$9,"X",IF(I7<=Assumptions!$B$10,"Y","Z")) | N7: =L7&M7 | O7: =INDEX(Assumptions!$F$4:$F$6,MATCH(L7,Assumptions!$E$4:$E$6,0)) | P7: =NORMSINV(O7) | Q7: =IFERROR(AVERAGEIFS(PO_Lines!$R$2:$R$2025,PO_Lines!$B$2:$B$2025,$A7,PO_Lines!$Q$2:$Q$2025,1),INDEX(Items!$F$2:$F$117,MATCH($A7,Items!$A$2:$A$117,0))) | R7: =IFERROR(SQRT(SUMPRODUCT((PO_Lines!$B$2:$B$2025=$A7)*PO_Lines!$Q$2:$Q$2025*(PO_Lines!$R$2:$R$2025-Q7)^2)/(COUNTIFS(PO_Lines!$B$2:$B$2025,$A7,PO_Lines!$Q$2:$Q$2025,1)-1)),0) | S7: =ROUNDUP(P7*SQRT((Q7/Assumptions!$B$11)*H7^2+G7^2*(R7/Assumptions!$B$11)^2),0) | T7: =ROUNDUP(G7*Q7/Assumptions!$B$11+S7,0) | U7: =ROUNDUP(MAX(INDEX(Items!$G$2:$G$117,MATCH($A7,Items!$A$2:$A$117,0)),SQRT(2*F7*Assumptions!$B$5/(Assumptions!$B$6*E7)),G7*Assumptions!$B$16),0) | V7: =INDEX(Stock_Snapshot!$B$2:$B$117,MATCH($A7,Stock_Snapshot!$A$2:$A$117,0)) | W7: =INDEX(Stock_Snapshot!$C$2:$C$117,MATCH($A7,Stock_Snapshot!$A$2:$A$117,0)) | X7: =V7+W7 | Y7: =IF(G7>0,V7/(G7/Assumptions!$B$11),999) | Z7: =S7+U7 | AA7: =IF(V7<S7,"Below safety stock",IF(X7<=T7,"Reorder now",IF(V7>Z7,"Excess","Healthy"))) | AB7: =V7*E7 | AC7: =MAX(0,V7-Z7)*E7 | AD7: =IF(X7<=T7,ROUNDUP(T7+U7-X7,0),0) | AE7: =MAX(0,T7-X7)*E7 | AF7: =IF(INDEX(Stock_Snapshot!$D$2:$D$117,MATCH($A7,Stock_Snapshot!$A$2:$A$117,0))="","",INDEX(Stock_Snapshot!$D$2:$D$117,MATCH($A7,Stock_Snapshot!$A$2:$A$117,0))) | AG7: =IF(AF7="","",IF(AF7<=EDATE(Assumptions!$B$4,Assumptions!$B$12),"Expires < "&Assumptions!$B$12&" m","OK"))
A8: CMD-0004 | B8: =INDEX(Items!$B$2:$B$117,MATCH($A8,Items!$A$2:$A$117,0)) | C8: =INDEX(Items!$C$2:$C$117,MATCH($A8,Items!$A$2:$A$117,0)) | D8: =INDEX(Items!$D$2:$D$117,MATCH($A8,Items!$A$2:$A$117,0)) | E8: =INDEX(Items!$E$2:$E$117,MATCH($A8,Items!$A$2:$A$117,0)) | F8: =SUM(INDEX(Demand!$N$2:$Y$117,MATCH($A8,Demand!$A$2:$A$117,0),0)) | G8: =F8/12 | H8: =STDEV(INDEX(Demand!$N$2:$Y$117,MATCH($A8,Demand!$A$2:$A$117,0),0)) | I8: =IF(G8>0,H8/G8,0) | J8: =F8*E8 | K8: =SUMIF($J$5:$J$120,">="&J8)/SUM($J$5:$J$120) | L8: =IF(K8<=Assumptions!$B$7,"A",IF(K8<=Assumptions!$B$8,"B","C")) | M8: =IF(I8<=Assumptions!$B$9,"X",IF(I8<=Assumptions!$B$10,"Y","Z")) | N8: =L8&M8 | O8: =INDEX(Assumptions!$F$4:$F$6,MATCH(L8,Assumptions!$E$4:$E$6,0)) | P8: =NORMSINV(O8) | Q8: =IFERROR(AVERAGEIFS(PO_Lines!$R$2:$R$2025,PO_Lines!$B$2:$B$2025,$A8,PO_Lines!$Q$2:$Q$2025,1),INDEX(Items!$F$2:$F$117,MATCH($A8,Items!$A$2:$A$117,0))) | R8: =IFERROR(SQRT(SUMPRODUCT((PO_Lines!$B$2:$B$2025=$A8)*PO_Lines!$Q$2:$Q$2025*(PO_Lines!$R$2:$R$2025-Q8)^2)/(COUNTIFS(PO_Lines!$B$2:$B$2025,$A8,PO_Lines!$Q$2:$Q$2025,1)-1)),0) | S8: =ROUNDUP(P8*SQRT((Q8/Assumptions!$B$11)*H8^2+G8^2*(R8/Assumptions!$B$11)^2),0) | T8: =ROUNDUP(G8*Q8/Assumptions!$B$11+S8,0) | U8: =ROUNDUP(MAX(INDEX(Items!$G$2:$G$117,MATCH($A8,Items!$A$2:$A$117,0)),SQRT(2*F8*Assumptions!$B$5/(Assumptions!$B$6*E8)),G8*Assumptions!$B$16),0) | V8: =INDEX(Stock_Snapshot!$B$2:$B$117,MATCH($A8,Stock_Snapshot!$A$2:$A$117,0)) | W8: =INDEX(Stock_Snapshot!$C$2:$C$117,MATCH($A8,Stock_Snapshot!$A$2:$A$117,0)) | X8: =V8+W8 | Y8: =IF(G8>0,V8/(G8/Assumptions!$B$11),999) | Z8: =S8+U8 | AA8: =IF(V8<S8,"Below safety stock",IF(X8<=T8,"Reorder now",IF(V8>Z8,"Excess","Healthy"))) | AB8: =V8*E8 | AC8: =MAX(0,V8-Z8)*E8 | AD8: =IF(X8<=T8,ROUNDUP(T8+U8-X8,0),0) | AE8: =MAX(0,T8-X8)*E8 | AF8: =IF(INDEX(Stock_Snapshot!$D$2:$D$117,MATCH($A8,Stock_Snapshot!$A$2:$A$117,0))="","",INDEX(Stock_Snapshot!$D$2:$D$117,MATCH($A8,Stock_Snapshot!$A$2:$A$117,0))) | AG8: =IF(AF8="","",IF(AF8<=EDATE(Assumptions!$B$4,Assumptions!$B$12),"Expires < "&Assumptions!$B$12&" m","OK"))
A9: CMD-0005 | B9: =INDEX(Items!$B$2:$B$117,MATCH($A9,Items!$A$2:$A$117,0)) | C9: =INDEX(Items!$C$2:$C$117,MATCH($A9,Items!$A$2:$A$117,0)) | D9: =INDEX(Items!$D$2:$D$117,MATCH($A9,Items!$A$2:$A$117,0)) | E9: =INDEX(Items!$E$2:$E$117,MATCH($A9,Items!$A$2:$A$117,0)) | F9: =SUM(INDEX(Demand!$N$2:$Y$117,MATCH($A9,Demand!$A$2:$A$117,0),0)) | G9: =F9/12 | H9: =STDEV(INDEX(Demand!$N$2:$Y$117,MATCH($A9,Demand!$A$2:$A$117,0),0)) | I9: =IF(G9>0,H9/G9,0) | J9: =F9*E9 | K9: =SUMIF($J$5:$J$120,">="&J9)/SUM($J$5:$J$120) | L9: =IF(K9<=Assumptions!$B$7,"A",IF(K9<=Assumptions!$B$8,"B","C")) | M9: =IF(I9<=Assumptions!$B$9,"X",IF(I9<=Assumptions!$B$10,"Y","Z")) | N9: =L9&M9 | O9: =INDEX(Assumptions!$F$4:$F$6,MATCH(L9,Assumptions!$E$4:$E$6,0)) | P9: =NORMSINV(O9) | Q9: =IFERROR(AVERAGEIFS(PO_Lines!$R$2:$R$2025,PO_Lines!$B$2:$B$2025,$A9,PO_Lines!$Q$2:$Q$2025,1),INDEX(Items!$F$2:$F$117,MATCH($A9,Items!$A$2:$A$117,0))) | R9: =IFERROR(SQRT(SUMPRODUCT((PO_Lines!$B$2:$B$2025=$A9)*PO_Lines!$Q$2:$Q$2025*(PO_Lines!$R$2:$R$2025-Q9)^2)/(COUNTIFS(PO_Lines!$B$2:$B$2025,$A9,PO_Lines!$Q$2:$Q$2025,1)-1)),0) | S9: =ROUNDUP(P9*SQRT((Q9/Assumptions!$B$11)*H9^2+G9^2*(R9/Assumptions!$B$11)^2),0) | T9: =ROUNDUP(G9*Q9/Assumptions!$B$11+S9,0) | U9: =ROUNDUP(MAX(INDEX(Items!$G$2:$G$117,MATCH($A9,Items!$A$2:$A$117,0)),SQRT(2*F9*Assumptions!$B$5/(Assumptions!$B$6*E9)),G9*Assumptions!$B$16),0) | V9: =INDEX(Stock_Snapshot!$B$2:$B$117,MATCH($A9,Stock_Snapshot!$A$2:$A$117,0)) | W9: =INDEX(Stock_Snapshot!$C$2:$C$117,MATCH($A9,Stock_Snapshot!$A$2:$A$117,0)) | X9: =V9+W9 | Y9: =IF(G9>0,V9/(G9/Assumptions!$B$11),999) | Z9: =S9+U9 | AA9: =IF(V9<S9,"Below safety stock",IF(X9<=T9,"Reorder now",IF(V9>Z9,"Excess","Healthy"))) | AB9: =V9*E9 | AC9: =MAX(0,V9-Z9)*E9 | AD9: =IF(X9<=T9,ROUNDUP(T9+U9-X9,0),0) | AE9: =MAX(0,T9-X9)*E9 | AF9: =IF(INDEX(Stock_Snapshot!$D$2:$D$117,MATCH($A9,Stock_Snapshot!$A$2:$A$117,0))="","",INDEX(Stock_Snapshot!$D$2:$D$117,MATCH($A9,Stock_Snapshot!$A$2:$A$117,0))) | AG9: =IF(AF9="","",IF(AF9<=EDATE(Assumptions!$B$4,Assumptions!$B$12),"Expires < "&Assumptions!$B$12&" m","OK"))
A10: CMD-0006 | B10: =INDEX(Items!$B$2:$B$117,MATCH($A10,Items!$A$2:$A$117,0)) | C10: =INDEX(Items!$C$2:$C$117,MATCH($A10,Items!$A$2:$A$117,0)) | D10: =INDEX(Items!$D$2:$D$117,MATCH($A10,Items!$A$2:$A$117,0)) | E10: =INDEX(Items!$E$2:$E$117,MATCH($A10,Items!$A$2:$A$117,0)) | F10: =SUM(INDEX(Demand!$N$2:$Y$117,MATCH($A10,Demand!$A$2:$A$117,0),0)) | G10: =F10/12 | H10: =STDEV(INDEX(Demand!$N$2:$Y$117,MATCH($A10,Demand!$A$2:$A$117,0),0)) | I10: =IF(G10>0,H10/G10,0) | J10: =F10*E10 | K10: =SUMIF($J$5:$J$120,">="&J10)/SUM($J$5:$J$120) | L10: =IF(K10<=Assumptions!$B$7,"A",IF(K10<=Assumptions!$B$8,"B","C")) | M10: =IF(I10<=Assumptions!$B$9,"X",IF(I10<=Assumptions!$B$10,"Y","Z")) | N10: =L10&M10 | O10: =INDEX(Assumptions!$F$4:$F$6,MATCH(L10,Assumptions!$E$4:$E$6,0)) | P10: =NORMSINV(O10) | Q10: =IFERROR(AVERAGEIFS(PO_Lines!$R$2:$R$2025,PO_Lines!$B$2:$B$2025,$A10,PO_Lines!$Q$2:$Q$2025,1),INDEX(Items!$F$2:$F$117,MATCH($A10,Items!$A$2:$A$117,0))) | R10: =IFERROR(SQRT(SUMPRODUCT((PO_Lines!$B$2:$B$2025=$A10)*PO_Lines!$Q$2:$Q$2025*(PO_Lines!$R$2:$R$2025-Q10)^2)/(COUNTIFS(PO_Lines!$B$2:$B$2025,$A10,PO_Lines!$Q$2:$Q$2025,1)-1)),0) | S10: =ROUNDUP(P10*SQRT((Q10/Assumptions!$B$11)*H10^2+G10^2*(R10/Assumptions!$B$11)^2),0) | T10: =ROUNDUP(G10*Q10/Assumptions!$B$11+S10,0) | U10: =ROUNDUP(MAX(INDEX(Items!$G$2:$G$117,MATCH($A10,Items!$A$2:$A$117,0)),SQRT(2*F10*Assumptions!$B$5/(Assumptions!$B$6*E10)),G10*Assumptions!$B$16),0) | V10: =INDEX(Stock_Snapshot!$B$2:$B$117,MATCH($A10,Stock_Snapshot!$A$2:$A$117,0)) | W10: =INDEX(Stock_Snapshot!$C$2:$C$117,MATCH($A10,Stock_Snapshot!$A$2:$A$117,0)) | X10: =V10+W10 | Y10: =IF(G10>0,V10/(G10/Assumptions!$B$11),999) | Z10: =S10+U10 | AA10: =IF(V10<S10,"Below safety stock",IF(X10<=T10,"Reorder now",IF(V10>Z10,"Excess","Healthy"))) | AB10: =V10*E10 | AC10: =MAX(0,V10-Z10)*E10 | AD10: =IF(X10<=T10,ROUNDUP(T10+U10-X10,0),0) | AE10: =MAX(0,T10-X10)*E10 | AF10: =IF(INDEX(Stock_Snapshot!$D$2:$D$117,MATCH($A10,Stock_Snapshot!$A$2:$A$117,0))="","",INDEX(Stock_Snapshot!$D$2:$D$117,MATCH($A10,Stock_Snapshot!$A$2:$A$117,0))) | AG10: =IF(AF10="","",IF(AF10<=EDATE(Assumptions!$B$4,Assumptions!$B$12),"Expires < "&Assumptions!$B$12&" m","OK"))
A11: CMD-0007 | B11: =INDEX(Items!$B$2:$B$117,MATCH($A11,Items!$A$2:$A$117,0)) | C11: =INDEX(Items!$C$2:$C$117,MATCH($A11,Items!$A$2:$A$117,0)) | D11: =INDEX(Items!$D$2:$D$117,MATCH($A11,Items!$A$2:$A$117,0)) | E11: =INDEX(Items!$E$2:$E$117,MATCH($A11,Items!$A$2:$A$117,0)) | F11: =SUM(INDEX(Demand!$N$2:$Y$117,MATCH($A11,Demand!$A$2:$A$117,0),0)) | G11: =F11/12 | H11: =STDEV(INDEX(Demand!$N$2:$Y$117,MATCH($A11,Demand!$A$2:$A$117,0),0)) | I11: =IF(G11>0,H11/G11,0) | J11: =F11*E11 | K11: =SUMIF($J$5:$J$120,">="&J11)/SUM($J$5:$J$120) | L11: =IF(K11<=Assumptions!$B$7,"A",IF(K11<=Assumptions!$B$8,"B","C")) | M11: =IF(I11<=Assumptions!$B$9,"X",IF(I11<=Assumptions!$B$10,"Y","Z")) | N11: =L11&M11 | O11: =INDEX(Assumptions!$F$4:$F$6,MATCH(L11,Assumptions!$E$4:$E$6,0)) | P11: =NORMSINV(O11) | Q11: =IFERROR(AVERAGEIFS(PO_Lines!$R$2:$R$2025,PO_Lines!$B$2:$B$2025,$A11,PO_Lines!$Q$2:$Q$2025,1),INDEX(Items!$F$2:$F$117,MATCH($A11,Items!$A$2:$A$117,0))) | R11: =IFERROR(SQRT(SUMPRODUCT((PO_Lines!$B$2:$B$2025=$A11)*PO_Lines!$Q$2:$Q$2025*(PO_Lines!$R$2:$R$2025-Q11)^2)/(COUNTIFS(PO_Lines!$B$2:$B$2025,$A11,PO_Lines!$Q$2:$Q$2025,1)-1)),0) | S11: =ROUNDUP(P11*SQRT((Q11/Assumptions!$B$11)*H11^2+G11^2*(R11/Assumptions!$B$11)^2),0) | T11: =ROUNDUP(G11*Q11/Assumptions!$B$11+S11,0) | U11: =ROUNDUP(MAX(INDEX(Items!$G$2:$G$117,MATCH($A11,Items!$A$2:$A$117,0)),SQRT(2*F11*Assumptions!$B$5/(Assumptions!$B$6*E11)),G11*Assumptions!$B$16),0) | V11: =INDEX(Stock_Snapshot!$B$2:$B$117,MATCH($A11,Stock_Snapshot!$A$2:$A$117,0)) | W11: =INDEX(Stock_Snapshot!$C$2:$C$117,MATCH($A11,Stock_Snapshot!$A$2:$A$117,0)) | X11: =V11+W11 | Y11: =IF(G11>0,V11/(G11/Assumptions!$B$11),999) | Z11: =S11+U11 | AA11: =IF(V11<S11,"Below safety stock",IF(X11<=T11,"Reorder now",IF(V11>Z11,"Excess","Healthy"))) | AB11: =V11*E11 | AC11: =MAX(0,V11-Z11)*E11 | AD11: =IF(X11<=T11,ROUNDUP(T11+U11-X11,0),0) | AE11: =MAX(0,T11-X11)*E11 | AF11: =IF(INDEX(Stock_Snapshot!$D$2:$D$117,MATCH($A11,Stock_Snapshot!$A$2:$A$117,0))="","",INDEX(Stock_Snapshot!$D$2:$D$117,MATCH($A11,Stock_Snapshot!$A$2:$A$117,0))) | AG11: =IF(AF11="","",IF(AF11<=EDATE(Assumptions!$B$4,Assumptions!$B$12),"Expires < "&Assumptions!$B$12&" m","OK"))
A12: CMD-0008 | B12: =INDEX(Items!$B$2:$B$117,MATCH($A12,Items!$A$2:$A$117,0)) | C12: =INDEX(Items!$C$2:$C$117,MATCH($A12,Items!$A$2:$A$117,0)) | D12: =INDEX(Items!$D$2:$D$117,MATCH($A12,Items!$A$2:$A$117,0)) | E12: =INDEX(Items!$E$2:$E$117,MATCH($A12,Items!$A$2:$A$117,0)) | F12: =SUM(INDEX(Demand!$N$2:$Y$117,MATCH($A12,Demand!$A$2:$A$117,0),0)) | G12: =F12/12 | H12: =STDEV(INDEX(Demand!$N$2:$Y$117,MATCH($A12,Demand!$A$2:$A$117,0),0)) | I12: =IF(G12>0,H12/G12,0) | J12: =F12*E12 | K12: =SUMIF($J$5:$J$120,">="&J12)/SUM($J$5:$J$120) | L12: =IF(K12<=Assumptions!$B$7,"A",IF(K12<=Assumptions!$B$8,"B","C")) | M12: =IF(I12<=Assumptions!$B$9,"X",IF(I12<=Assumptions!$B$10,"Y","Z")) | N12: =L12&M12 | O12: =INDEX(Assumptions!$F$4:$F$6,MATCH(L12,Assumptions!$E$4:$E$6,0)) | P12: =NORMSINV(O12) | Q12: =IFERROR(AVERAGEIFS(PO_Lines!$R$2:$R$2025,PO_Lines!$B$2:$B$2025,$A12,PO_Lines!$Q$2:$Q$2025,1),INDEX(Items!$F$2:$F$117,MATCH($A12,Items!$A$2:$A$117,0))) | R12: =IFERROR(SQRT(SUMPRODUCT((PO_Lines!$B$2:$B$2025=$A12)*PO_Lines!$Q$2:$Q$2025*(PO_Lines!$R$2:$R$2025-Q12)^2)/(COUNTIFS(PO_Lines!$B$2:$B$2025,$A12,PO_Lines!$Q$2:$Q$2025,1)-1)),0) | S12: =ROUNDUP(P12*SQRT((Q12/Assumptions!$B$11)*H12^2+G12^2*(R12/Assumptions!$B$11)^2),0) | T12: =ROUNDUP(G12*Q12/Assumptions!$B$11+S12,0) | U12: =ROUNDUP(MAX(INDEX(Items!$G$2:$G$117,MATCH($A12,Items!$A$2:$A$117,0)),SQRT(2*F12*Assumptions!$B$5/(Assumptions!$B$6*E12)),G12*Assumptions!$B$16),0) | V12: =INDEX(Stock_Snapshot!$B$2:$B$117,MATCH($A12,Stock_Snapshot!$A$2:$A$117,0)) | W12: =INDEX(Stock_Snapshot!$C$2:$C$117,MATCH($A12,Stock_Snapshot!$A$2:$A$117,0)) | X12: =V12+W12 | Y12: =IF(G12>0,V12/(G12/Assumptions!$B$11),999) | Z12: =S12+U12 | AA12: =IF(V12<S12,"Below safety stock",IF(X12<=T12,"Reorder now",IF(V12>Z12,"Excess","Healthy"))) | AB12: =V12*E12 | AC12: =MAX(0,V12-Z12)*E12 | AD12: =IF(X12<=T12,ROUNDUP(T12+U12-X12,0),0) | AE12: =MAX(0,T12-X12)*E12 | AF12: =IF(INDEX(Stock_Snapshot!$D$2:$D$117,MATCH($A12,Stock_Snapshot!$A$2:$A$117,0))="","",INDEX(Stock_Snapshot!$D$2:$D$117,MATCH($A12,Stock_Snapshot!$A$2:$A$117,0))) | AG12: =IF(AF12="","",IF(AF12<=EDATE(Assumptions!$B$4,Assumptions!$B$12),"Expires < "&Assumptions!$B$12&" m","OK"))
A13: CMD-0009 | B13: =INDEX(Items!$B$2:$B$117,MATCH($A13,Items!$A$2:$A$117,0)) | C13: =INDEX(Items!$C$2:$C$117,MATCH($A13,Items!$A$2:$A$117,0)) | D13: =INDEX(Items!$D$2:$D$117,MATCH($A13,Items!$A$2:$A$117,0)) | E13: =INDEX(Items!$E$2:$E$117,MATCH($A13,Items!$A$2:$A$117,0)) | F13: =SUM(INDEX(Demand!$N$2:$Y$117,MATCH($A13,Demand!$A$2:$A$117,0),0)) | G13: =F13/12 | H13: =STDEV(INDEX(Demand!$N$2:$Y$117,MATCH($A13,Demand!$A$2:$A$117,0),0)) | I13: =IF(G13>0,H13/G13,0) | J13: =F13*E13 | K13: =SUMIF($J$5:$J$120,">="&J13)/SUM($J$5:$J$120) | L13: =IF(K13<=Assumptions!$B$7,"A",IF(K13<=Assumptions!$B$8,"B","C")) | M13: =IF(I13<=Assumptions!$B$9,"X",IF(I13<=Assumptions!$B$10,"Y","Z")) | N13: =L13&M13 | O13: =INDEX(Assumptions!$F$4:$F$6,MATCH(L13,Assumptions!$E$4:$E$6,0)) | P13: =NORMSINV(O13) | Q13: =IFERROR(AVERAGEIFS(PO_Lines!$R$2:$R$2025,PO_Lines!$B$2:$B$2025,$A13,PO_Lines!$Q$2:$Q$2025,1),INDEX(Items!$F$2:$F$117,MATCH($A13,Items!$A$2:$A$117,0))) | R13: =IFERROR(SQRT(SUMPRODUCT((PO_Lines!$B$2:$B$2025=$A13)*PO_Lines!$Q$2:$Q$2025*(PO_Lines!$R$2:$R$2025-Q13)^2)/(COUNTIFS(PO_Lines!$B$2:$B$2025,$A13,PO_Lines!$Q$2:$Q$2025,1)-1)),0) | S13: =ROUNDUP(P13*SQRT((Q13/Assumptions!$B$11)*H13^2+G13^2*(R13/Assumptions!$B$11)^2),0) | T13: =ROUNDUP(G13*Q13/Assumptions!$B$11+S13,0) | U13: =ROUNDUP(MAX(INDEX(Items!$G$2:$G$117,MATCH($A13,Items!$A$2:$A$117,0)),SQRT(2*F13*Assumptions!$B$5/(Assumptions!$B$6*E13)),G13*Assumptions!$B$16),0) | V13: =INDEX(Stock_Snapshot!$B$2:$B$117,MATCH($A13,Stock_Snapshot!$A$2:$A$117,0)) | W13: =INDEX(Stock_Snapshot!$C$2:$C$117,MATCH($A13,Stock_Snapshot!$A$2:$A$117,0)) | X13: =V13+W13 | Y13: =IF(G13>0,V13/(G13/Assumptions!$B$11),999) | Z13: =S13+U13 | AA13: =IF(V13<S13,"Below safety stock",IF(X13<=T13,"Reorder now",IF(V13>Z13,"Excess","Healthy"))) | AB13: =V13*E13 | AC13: =MAX(0,V13-Z13)*E13 | AD13: =IF(X13<=T13,ROUNDUP(T13+U13-X13,0),0) | AE13: =MAX(0,T13-X13)*E13 | AF13: =IF(INDEX(Stock_Snapshot!$D$2:$D$117,MATCH($A13,Stock_Snapshot!$A$2:$A$117,0))="","",INDEX(Stock_Snapshot!$D$2:$D$117,MATCH($A13,Stock_Snapshot!$A$2:$A$117,0))) | AG13: =IF(AF13="","",IF(AF13<=EDATE(Assumptions!$B$4,Assumptions!$B$12),"Expires < "&Assumptions!$B$12&" m","OK"))
A14: CMD-0010 | B14: =INDEX(Items!$B$2:$B$117,MATCH($A14,Items!$A$2:$A$117,0)) | C14: =INDEX(Items!$C$2:$C$117,MATCH($A14,Items!$A$2:$A$117,0)) | D14: =INDEX(Items!$D$2:$D$117,MATCH($A14,Items!$A$2:$A$117,0)) | E14: =INDEX(Items!$E$2:$E$117,MATCH($A14,Items!$A$2:$A$117,0)) | F14: =SUM(INDEX(Demand!$N$2:$Y$117,MATCH($A14,Demand!$A$2:$A$117,0),0)) | G14: =F14/12 | H14: =STDEV(INDEX(Demand!$N$2:$Y$117,MATCH($A14,Demand!$A$2:$A$117,0),0)) | I14: =IF(G14>0,H14/G14,0) | J14: =F14*E14 | K14: =SUMIF($J$5:$J$120,">="&J14)/SUM($J$5:$J$120) | L14: =IF(K14<=Assumptions!$B$7,"A",IF(K14<=Assumptions!$B$8,"B","C")) | M14: =IF(I14<=Assumptions!$B$9,"X",IF(I14<=Assumptions!$B$10,"Y","Z")) | N14: =L14&M14 | O14: =INDEX(Assumptions!$F$4:$F$6,MATCH(L14,Assumptions!$E$4:$E$6,0)) | P14: =NORMSINV(O14) | Q14: =IFERROR(AVERAGEIFS(PO_Lines!$R$2:$R$2025,PO_Lines!$B$2:$B$2025,$A14,PO_Lines!$Q$2:$Q$2025,1),INDEX(Items!$F$2:$F$117,MATCH($A14,Items!$A$2:$A$117,0))) | R14: =IFERROR(SQRT(SUMPRODUCT((PO_Lines!$B$2:$B$2025=$A14)*PO_Lines!$Q$2:$Q$2025*(PO_Lines!$R$2:$R$2025-Q14)^2)/(COUNTIFS(PO_Lines!$B$2:$B$2025,$A14,PO_Lines!$Q$2:$Q$2025,1)-1)),0) | S14: =ROUNDUP(P14*SQRT((Q14/Assumptions!$B$11)*H14^2+G14^2*(R14/Assumptions!$B$11)^2),0) | T14: =ROUNDUP(G14*Q14/Assumptions!$B$11+S14,0) | U14: =ROUNDUP(MAX(INDEX(Items!$G$2:$G$117,MATCH($A14,Items!$A$2:$A$117,0)),SQRT(2*F14*Assumptions!$B$5/(Assumptions!$B$6*E14)),G14*Assumptions!$B$16),0) | V14: =INDEX(Stock_Snapshot!$B$2:$B$117,MATCH($A14,Stock_Snapshot!$A$2:$A$117,0)) | W14: =INDEX(Stock_Snapshot!$C$2:$C$117,MATCH($A14,Stock_Snapshot!$A$2:$A$117,0)) | X14: =V14+W14 | Y14: =IF(G14>0,V14/(G14/Assumptions!$B$11),999) | Z14: =S14+U14 | AA14: =IF(V14<S14,"Below safety stock",IF(X14<=T14,"Reorder now",IF(V14>Z14,"Excess","Healthy"))) | AB14: =V14*E14 | AC14: =MAX(0,V14-Z14)*E14 | AD14: =IF(X14<=T14,ROUNDUP(T14+U14-X14,0),0) | AE14: =MAX(0,T14-X14)*E14 | AF14: =IF(INDEX(Stock_Snapshot!$D$2:$D$117,MATCH($A14,Stock_Snapshot!$A$2:$A$117,0))="","",INDEX(Stock_Snapshot!$D$2:$D$117,MATCH($A14,Stock_Snapshot!$A$2:$A$117,0))) | AG14: =IF(AF14="","",IF(AF14<=EDATE(Assumptions!$B$4,Assumptions!$B$12),"Expires < "&Assumptions!$B$12&" m","OK"))
A15: CMD-0011 | B15: =INDEX(Items!$B$2:$B$117,MATCH($A15,Items!$A$2:$A$117,0)) | C15: =INDEX(Items!$C$2:$C$117,MATCH($A15,Items!$A$2:$A$117,0)) | D15: =INDEX(Items!$D$2:$D$117,MATCH($A15,Items!$A$2:$A$117,0)) | E15: =INDEX(Items!$E$2:$E$117,MATCH($A15,Items!$A$2:$A$117,0)) | F15: =SUM(INDEX(Demand!$N$2:$Y$117,MATCH($A15,Demand!$A$2:$A$117,0),0)) | G15: =F15/12 | H15: =STDEV(INDEX(Demand!$N$2:$Y$117,MATCH($A15,Demand!$A$2:$A$117,0),0)) | I15: =IF(G15>0,H15/G15,0) | J15: =F15*E15 | K15: =SUMIF($J$5:$J$120,">="&J15)/SUM($J$5:$J$120) | L15: =IF(K15<=Assumptions!$B$7,"A",IF(K15<=Assumptions!$B$8,"B","C")) | M15: =IF(I15<=Assumptions!$B$9,"X",IF(I15<=Assumptions!$B$10,"Y","Z")) | N15: =L15&M15 | O15: =INDEX(Assumptions!$F$4:$F$6,MATCH(L15,Assumptions!$E$4:$E$6,0)) | P15: =NORMSINV(O15) | Q15: =IFERROR(AVERAGEIFS(PO_Lines!$R$2:$R$2025,PO_Lines!$B$2:$B$2025,$A15,PO_Lines!$Q$2:$Q$2025,1),INDEX(Items!$F$2:$F$117,MATCH($A15,Items!$A$2:$A$117,0))) | R15: =IFERROR(SQRT(SUMPRODUCT((PO_Lines!$B$2:$B$2025=$A15)*PO_Lines!$Q$2:$Q$2025*(PO_Lines!$R$2:$R$2025-Q15)^2)/(COUNTIFS(PO_Lines!$B$2:$B$2025,$A15,PO_Lines!$Q$2:$Q$2025,1)-1)),0) | S15: =ROUNDUP(P15*SQRT((Q15/Assumptions!$B$11)*H15^2+G15^2*(R15/Assumptions!$B$11)^2),0) | T15: =ROUNDUP(G15*Q15/Assumptions!$B$11+S15,0) | U15: =ROUNDUP(MAX(INDEX(Items!$G$2:$G$117,MATCH($A15,Items!$A$2:$A$117,0)),SQRT(2*F15*Assumptions!$B$5/(Assumptions!$B$6*E15)),G15*Assumptions!$B$16),0) | V15: =INDEX(Stock_Snapshot!$B$2:$B$117,MATCH($A15,Stock_Snapshot!$A$2:$A$117,0)) | W15: =INDEX(Stock_Snapshot!$C$2:$C$117,MATCH($A15,Stock_Snapshot!$A$2:$A$117,0)) | X15: =V15+W15 | Y15: =IF(G15>0,V15/(G15/Assumptions!$B$11),999) | Z15: =S15+U15 | AA15: =IF(V15<S15,"Below safety stock",IF(X15<=T15,"Reorder now",IF(V15>Z15,"Excess","Healthy"))) | AB15: =V15*E15 | AC15: =MAX(0,V15-Z15)*E15 | AD15: =IF(X15<=T15,ROUNDUP(T15+U15-X15,0),0) | AE15: =MAX(0,T15-X15)*E15 | AF15: =IF(INDEX(Stock_Snapshot!$D$2:$D$117,MATCH($A15,Stock_Snapshot!$A$2:$A$117,0))="","",INDEX(Stock_Snapshot!$D$2:$D$117,MATCH($A15,Stock_Snapshot!$A$2:$A$117,0))) | AG15: =IF(AF15="","",IF(AF15<=EDATE(Assumptions!$B$4,Assumptions!$B$12),"Expires < "&Assumptions!$B$12&" m","OK"))
A16: CMD-0012 | B16: =INDEX(Items!$B$2:$B$117,MATCH($A16,Items!$A$2:$A$117,0)) | C16: =INDEX(Items!$C$2:$C$117,MATCH($A16,Items!$A$2:$A$117,0)) | D16: =INDEX(Items!$D$2:$D$117,MATCH($A16,Items!$A$2:$A$117,0)) | E16: =INDEX(Items!$E$2:$E$117,MATCH($A16,Items!$A$2:$A$117,0)) | F16: =SUM(INDEX(Demand!$N$2:$Y$117,MATCH($A16,Demand!$A$2:$A$117,0),0)) | G16: =F16/12 | H16: =STDEV(INDEX(Demand!$N$2:$Y$117,MATCH($A16,Demand!$A$2:$A$117,0),0)) | I16: =IF(G16>0,H16/G16,0) | J16: =F16*E16 | K16: =SUMIF($J$5:$J$120,">="&J16)/SUM($J$5:$J$120) | L16: =IF(K16<=Assumptions!$B$7,"A",IF(K16<=Assumptions!$B$8,"B","C")) | M16: =IF(I16<=Assumptions!$B$9,"X",IF(I16<=Assumptions!$B$10,"Y","Z")) | N16: =L16&M16 | O16: =INDEX(Assumptions!$F$4:$F$6,MATCH(L16,Assumptions!$E$4:$E$6,0)) | P16: =NORMSINV(O16) | Q16: =IFERROR(AVERAGEIFS(PO_Lines!$R$2:$R$2025,PO_Lines!$B$2:$B$2025,$A16,PO_Lines!$Q$2:$Q$2025,1),INDEX(Items!$F$2:$F$117,MATCH($A16,Items!$A$2:$A$117,0))) | R16: =IFERROR(SQRT(SUMPRODUCT((PO_Lines!$B$2:$B$2025=$A16)*PO_Lines!$Q$2:$Q$2025*(PO_Lines!$R$2:$R$2025-Q16)^2)/(COUNTIFS(PO_Lines!$B$2:$B$2025,$A16,PO_Lines!$Q$2:$Q$2025,1)-1)),0) | S16: =ROUNDUP(P16*SQRT((Q16/Assumptions!$B$11)*H16^2+G16^2*(R16/Assumptions!$B$11)^2),0) | T16: =ROUNDUP(G16*Q16/Assumptions!$B$11+S16,0) | U16: =ROUNDUP(MAX(INDEX(Items!$G$2:$G$117,MATCH($A16,Items!$A$2:$A$117,0)),SQRT(2*F16*Assumptions!$B$5/(Assumptions!$B$6*E16)),G16*Assumptions!$B$16),0) | V16: =INDEX(Stock_Snapshot!$B$2:$B$117,MATCH($A16,Stock_Snapshot!$A$2:$A$117,0)) | W16: =INDEX(Stock_Snapshot!$C$2:$C$117,MATCH($A16,Stock_Snapshot!$A$2:$A$117,0)) | X16: =V16+W16 | Y16: =IF(G16>0,V16/(G16/Assumptions!$B$11),999) | Z16: =S16+U16 | AA16: =IF(V16<S16,"Below safety stock",IF(X16<=T16,"Reorder now",IF(V16>Z16,"Excess","Healthy"))) | AB16: =V16*E16 | AC16: =MAX(0,V16-Z16)*E16 | AD16: =IF(X16<=T16,ROUNDUP(T16+U16-X16,0),0) | AE16: =MAX(0,T16-X16)*E16 | AF16: =IF(INDEX(Stock_Snapshot!$D$2:$D$117,MATCH($A16,Stock_Snapshot!$A$2:$A$117,0))="","",INDEX(Stock_Snapshot!$D$2:$D$117,MATCH($A16,Stock_Snapshot!$A$2:$A$117,0))) | AG16: =IF(AF16="","",IF(AF16<=EDATE(Assumptions!$B$4,Assumptions!$B$12),"Expires < "&Assumptions!$B$12&" m","OK"))
... A120: CMD-0116 | B120: =INDEX(Items!$B$2:$B$117,MATCH($A120,Items!$A$2:$A$117,0)) | C120: =INDEX(Items!$C$2:$C$117,MATCH($A120,Items!$A$2:$A$117,0)) | D120: =INDEX(Items!$D$2:$D$117,MATCH($A120,Items!$A$2:$A$117,0)) | E120: =INDEX(Items!$E$2:$E$117,MATCH($A120,Items!$A$2:$A$117,0)) | F120: =SUM(INDEX(Demand!$N$2:$Y$117,MATCH($A120,Demand!$A$2:$A$117,0),0)) | G120: =F120/12 | H120: =STDEV(INDEX(Demand!$N$2:$Y$117,MATCH($A120,Demand!$A$2:$A$117,0),0)) | I120: =IF(G120>0,H120/G120,0) | J120: =F120*E120 | K120: =SUMIF($J$5:$J$120,">="&J120)/SUM($J$5:$J$120) | L120: =IF(K120<=Assumptions!$B$7,"A",IF(K120<=Assumptions!$B$8,"B","C")) | M120: =IF(I120<=Assumptions!$B$9,"X",IF(I120<=Assumptions!$B$10,"Y","Z")) | N120: =L120&M120 | O120: =INDEX(Assumptions!$F$4:$F$6,MATCH(L120,Assumptions!$E$4:$E$6,0)) | P120: =NORMSINV(O120) | Q120: =IFERROR(AVERAGEIFS(PO_Lines!$R$2:$R$2025,PO_Lines!$B$2:$B$2025,$A120,PO_Lines!$Q$2:$Q$2025,1),INDEX(Items!$F$2:$F$117,MATCH($A120,Items!$A$2:$A$117,0))) | R120: =IFERROR(SQRT(SUMPRODUCT((PO_Lines!$B$2:$B$2025=$A120)*PO_Lines!$Q$2:$Q$2025*(PO_Lines!$R$2:$R$2025-Q120)^2)/(COUNTIFS(PO_Lines!$B$2:$B$2025,$A120,PO_Lines!$Q$2:$Q$2025,1)-1)),0) | S120: =ROUNDUP(P120*SQRT((Q120/Assumptions!$B$11)*H120^2+G120^2*(R120/Assumptions!$B$11)^2),0) | T120: =ROUNDUP(G120*Q120/Assumptions!$B$11+S120,0) | U120: =ROUNDUP(MAX(INDEX(Items!$G$2:$G$117,MATCH($A120,Items!$A$2:$A$117,0)),SQRT(2*F120*Assumptions!$B$5/(Assumptions!$B$6*E120)),G120*Assumptions!$B$16),0) | V120: =INDEX(Stock_Snapshot!$B$2:$B$117,MATCH($A120,Stock_Snapshot!$A$2:$A$117,0)) | W120: =INDEX(Stock_Snapshot!$C$2:$C$117,MATCH($A120,Stock_Snapshot!$A$2:$A$117,0)) | X120: =V120+W120 | Y120: =IF(G120>0,V120/(G120/Assumptions!$B$11),999) | Z120: =S120+U120 | AA120: =IF(V120<S120,"Below safety stock",IF(X120<=T120,"Reorder now",IF(V120>Z120,"Excess","Healthy"))) | AB120: =V120*E120 | AC120: =MAX(0,V120-Z120)*E120 | AD120: =IF(X120<=T120,ROUNDUP(T120+U120-X120,0),0) | AE120: =MAX(0,T120-X120)*E120 | AF120: =IF(INDEX(Stock_Snapshot!$D$2:$D$117,MATCH($A120,Stock_Snapshot!$A$2:$A$117,0))="","",INDEX(Stock_Snapshot!$D$2:$D$117,MATCH($A120,Stock_Snapshot!$A$2:$A$117,0))) | AG120: =IF(AF120="","",IF(AF120<=EDATE(Assumptions!$B$4,Assumptions!$B$12),"Expires < "&Assumptions!$B$12&" m","OK"))

Sheet Supplier_Scorecard
A1: Supplier Scorecard
A2: On-time, in-full (OTIF), quality and lead-time performance per supplier, all POs received Oct-2024 to Sep-2026.
A4: Supplier ID | B4: Supplier | C4: Country | D4: SKUs supplied | E4: Single-source SKUs | F4: POs received | G4: FY spend (€) | H4: On-time % | I4: In-full % | J4: OTIF % | K4: Avg days late (late POs) | L4: Reject rate | M4: Avg actual lead time (days) | N4: Rating
A5: S01 | B5: Shannon Electronics Ltd | C5: Ireland | D5: =COUNTIF(Items!$D$2:$D$117,A5) | E5: =COUNTIFS(Items!$D$2:$D$117,A5,Items!$I$2:$I$117,TRUE) | F5: =COUNTIFS(PO_Lines!$C$2:$C$2025,A5,PO_Lines!$Q$2:$Q$2025,1) | G5: =SUMIFS(PO_Lines!$O$2:$O$2025,PO_Lines!$C$2:$C$2025,A5,PO_Lines!$D$2:$D$2025,">="&Assumptions!$B$13) | H5: =IFERROR(SUMIFS(PO_Lines!$S$2:$S$2025,PO_Lines!$C$2:$C$2025,A5)/F5,0) | I5: =IFERROR(SUMIFS(PO_Lines!$T$2:$T$2025,PO_Lines!$C$2:$C$2025,A5)/F5,0) | J5: =IFERROR(SUMIFS(PO_Lines!$U$2:$U$2025,PO_Lines!$C$2:$C$2025,A5)/F5,0) | K5: =IFERROR(AVERAGEIFS(PO_Lines!$V$2:$V$2025,PO_Lines!$C$2:$C$2025,A5,PO_Lines!$V$2:$V$2025,">0"),0) | L5: =IFERROR(SUMIFS(PO_Lines!$I$2:$I$2025,PO_Lines!$C$2:$C$2025,A5)/SUMIFS(PO_Lines!$H$2:$H$2025,PO_Lines!$C$2:$C$2025,A5),0) | M5: =IFERROR(AVERAGEIFS(PO_Lines!$R$2:$R$2025,PO_Lines!$C$2:$C$2025,A5,PO_Lines!$Q$2:$Q$2025,1),0) | N5: =IF(J5>=Assumptions!$B$14,"Preferred",IF(J5>=Assumptions!$B$15,"Approved","Improvement plan"))
A6: S02 | B6: Rhein Sensorik GmbH | C6: Germany | D6: =COUNTIF(Items!$D$2:$D$117,A6) | E6: =COUNTIFS(Items!$D$2:$D$117,A6,Items!$I$2:$I$117,TRUE) | F6: =COUNTIFS(PO_Lines!$C$2:$C$2025,A6,PO_Lines!$Q$2:$Q$2025,1) | G6: =SUMIFS(PO_Lines!$O$2:$O$2025,PO_Lines!$C$2:$C$2025,A6,PO_Lines!$D$2:$D$2025,">="&Assumptions!$B$13) | H6: =IFERROR(SUMIFS(PO_Lines!$S$2:$S$2025,PO_Lines!$C$2:$C$2025,A6)/F6,0) | I6: =IFERROR(SUMIFS(PO_Lines!$T$2:$T$2025,PO_Lines!$C$2:$C$2025,A6)/F6,0) | J6: =IFERROR(SUMIFS(PO_Lines!$U$2:$U$2025,PO_Lines!$C$2:$C$2025,A6)/F6,0) | K6: =IFERROR(AVERAGEIFS(PO_Lines!$V$2:$V$2025,PO_Lines!$C$2:$C$2025,A6,PO_Lines!$V$2:$V$2025,">0"),0) | L6: =IFERROR(SUMIFS(PO_Lines!$I$2:$I$2025,PO_Lines!$C$2:$C$2025,A6)/SUMIFS(PO_Lines!$H$2:$H$2025,PO_Lines!$C$2:$C$2025,A6),0) | M6: =IFERROR(AVERAGEIFS(PO_Lines!$R$2:$R$2025,PO_Lines!$C$2:$C$2025,A6,PO_Lines!$Q$2:$Q$2025,1),0) | N6: =IF(J6>=Assumptions!$B$14,"Preferred",IF(J6>=Assumptions!$B$15,"Approved","Improvement plan"))
A7: S03 | B7: Formosa Microtech Co. | C7: Taiwan | D7: =COUNTIF(Items!$D$2:$D$117,A7) | E7: =COUNTIFS(Items!$D$2:$D$117,A7,Items!$I$2:$I$117,TRUE) | F7: =COUNTIFS(PO_Lines!$C$2:$C$2025,A7,PO_Lines!$Q$2:$Q$2025,1) | G7: =SUMIFS(PO_Lines!$O$2:$O$2025,PO_Lines!$C$2:$C$2025,A7,PO_Lines!$D$2:$D$2025,">="&Assumptions!$B$13) | H7: =IFERROR(SUMIFS(PO_Lines!$S$2:$S$2025,PO_Lines!$C$2:$C$2025,A7)/F7,0) | I7: =IFERROR(SUMIFS(PO_Lines!$T$2:$T$2025,PO_Lines!$C$2:$C$2025,A7)/F7,0) | J7: =IFERROR(SUMIFS(PO_Lines!$U$2:$U$2025,PO_Lines!$C$2:$C$2025,A7)/F7,0) | K7: =IFERROR(AVERAGEIFS(PO_Lines!$V$2:$V$2025,PO_Lines!$C$2:$C$2025,A7,PO_Lines!$V$2:$V$2025,">0"),0) | L7: =IFERROR(SUMIFS(PO_Lines!$I$2:$I$2025,PO_Lines!$C$2:$C$2025,A7)/SUMIFS(PO_Lines!$H$2:$H$2025,PO_Lines!$C$2:$C$2025,A7),0) | M7: =IFERROR(AVERAGEIFS(PO_Lines!$R$2:$R$2025,PO_Lines!$C$2:$C$2025,A7,PO_Lines!$Q$2:$Q$2025,1),0) | N7: =IF(J7>=Assumptions!$B$14,"Preferred",IF(J7>=Assumptions!$B$15,"Approved","Improvement plan"))
A8: S04 | B8: Penang Precision Sdn Bhd | C8: Malaysia | D8: =COUNTIF(Items!$D$2:$D$117,A8) | E8: =COUNTIFS(Items!$D$2:$D$117,A8,Items!$I$2:$I$117,TRUE) | F8: =COUNTIFS(PO_Lines!$C$2:$C$2025,A8,PO_Lines!$Q$2:$Q$2025,1) | G8: =SUMIFS(PO_Lines!$O$2:$O$2025,PO_Lines!$C$2:$C$2025,A8,PO_Lines!$D$2:$D$2025,">="&Assumptions!$B$13) | H8: =IFERROR(SUMIFS(PO_Lines!$S$2:$S$2025,PO_Lines!$C$2:$C$2025,A8)/F8,0) | I8: =IFERROR(SUMIFS(PO_Lines!$T$2:$T$2025,PO_Lines!$C$2:$C$2025,A8)/F8,0) | J8: =IFERROR(SUMIFS(PO_Lines!$U$2:$U$2025,PO_Lines!$C$2:$C$2025,A8)/F8,0) | K8: =IFERROR(AVERAGEIFS(PO_Lines!$V$2:$V$2025,PO_Lines!$C$2:$C$2025,A8,PO_Lines!$V$2:$V$2025,">0"),0) | L8: =IFERROR(SUMIFS(PO_Lines!$I$2:$I$2025,PO_Lines!$C$2:$C$2025,A8)/SUMIFS(PO_Lines!$H$2:$H$2025,PO_Lines!$C$2:$C$2025,A8),0) | M8: =IFERROR(AVERAGEIFS(PO_Lines!$R$2:$R$2025,PO_Lines!$C$2:$C$2025,A8,PO_Lines!$Q$2:$Q$2025,1),0) | N8: =IF(J8>=Assumptions!$B$14,"Preferred",IF(J8>=Assumptions!$B$15,"Approved","Improvement plan"))
A9: S05 | B9: Shenzhen Brightcell Power | C9: China | D9: =COUNTIF(Items!$D$2:$D$117,A9) | E9: =COUNTIFS(Items!$D$2:$D$117,A9,Items!$I$2:$I$117,TRUE) | F9: =COUNTIFS(PO_Lines!$C$2:$C$2025,A9,PO_Lines!$Q$2:$Q$2025,1) | G9: =SUMIFS(PO_Lines!$O$2:$O$2025,PO_Lines!$C$2:$C$2025,A9,PO_Lines!$D$2:$D$2025,">="&Assumptions!$B$13) | H9: =IFERROR(SUMIFS(PO_Lines!$S$2:$S$2025,PO_Lines!$C$2:$C$2025,A9)/F9,0) | I9: =IFERROR(SUMIFS(PO_Lines!$T$2:$T$2025,PO_Lines!$C$2:$C$2025,A9)/F9,0) | J9: =IFERROR(SUMIFS(PO_Lines!$U$2:$U$2025,PO_Lines!$C$2:$C$2025,A9)/F9,0) | K9: =IFERROR(AVERAGEIFS(PO_Lines!$V$2:$V$2025,PO_Lines!$C$2:$C$2025,A9,PO_Lines!$V$2:$V$2025,">0"),0) | L9: =IFERROR(SUMIFS(PO_Lines!$I$2:$I$2025,PO_Lines!$C$2:$C$2025,A9)/SUMIFS(PO_Lines!$H$2:$H$2025,PO_Lines!$C$2:$C$2025,A9),0) | M9: =IFERROR(AVERAGEIFS(PO_Lines!$R$2:$R$2025,PO_Lines!$C$2:$C$2025,A9,PO_Lines!$Q$2:$Q$2025,1),0) | N9: =IF(J9>=Assumptions!$B$14,"Preferred",IF(J9>=Assumptions!$B$15,"Approved","Improvement plan"))
A10: S06 | B10: Midlands Connect UK | C10: United Kingdom | D10: =COUNTIF(Items!$D$2:$D$117,A10) | E10: =COUNTIFS(Items!$D$2:$D$117,A10,Items!$I$2:$I$117,TRUE) | F10: =COUNTIFS(PO_Lines!$C$2:$C$2025,A10,PO_Lines!$Q$2:$Q$2025,1) | G10: =SUMIFS(PO_Lines!$O$2:$O$2025,PO_Lines!$C$2:$C$2025,A10,PO_Lines!$D$2:$D$2025,">="&Assumptions!$B$13) | H10: =IFERROR(SUMIFS(PO_Lines!$S$2:$S$2025,PO_Lines!$C$2:$C$2025,A10)/F10,0) | I10: =IFERROR(SUMIFS(PO_Lines!$T$2:$T$2025,PO_Lines!$C$2:$C$2025,A10)/F10,0) | J10: =IFERROR(SUMIFS(PO_Lines!$U$2:$U$2025,PO_Lines!$C$2:$C$2025,A10)/F10,0) | K10: =IFERROR(AVERAGEIFS(PO_Lines!$V$2:$V$2025,PO_Lines!$C$2:$C$2025,A10,PO_Lines!$V$2:$V$2025,">0"),0) | L10: =IFERROR(SUMIFS(PO_Lines!$I$2:$I$2025,PO_Lines!$C$2:$C$2025,A10)/SUMIFS(PO_Lines!$H$2:$H$2025,PO_Lines!$C$2:$C$2025,A10),0) | M10: =IFERROR(AVERAGEIFS(PO_Lines!$R$2:$R$2025,PO_Lines!$C$2:$C$2025,A10,PO_Lines!$Q$2:$Q$2025,1),0) | N10: =IF(J10>=Assumptions!$B$14,"Preferred",IF(J10>=Assumptions!$B$15,"Approved","Improvement plan"))
A11: S07 | B11: Lakeview Circuits Inc. | C11: USA | D11: =COUNTIF(Items!$D$2:$D$117,A11) | E11: =COUNTIFS(Items!$D$2:$D$117,A11,Items!$I$2:$I$117,TRUE) | F11: =COUNTIFS(PO_Lines!$C$2:$C$2025,A11,PO_Lines!$Q$2:$Q$2025,1) | G11: =SUMIFS(PO_Lines!$O$2:$O$2025,PO_Lines!$C$2:$C$2025,A11,PO_Lines!$D$2:$D$2025,">="&Assumptions!$B$13) | H11: =IFERROR(SUMIFS(PO_Lines!$S$2:$S$2025,PO_Lines!$C$2:$C$2025,A11)/F11,0) | I11: =IFERROR(SUMIFS(PO_Lines!$T$2:$T$2025,PO_Lines!$C$2:$C$2025,A11)/F11,0) | J11: =IFERROR(SUMIFS(PO_Lines!$U$2:$U$2025,PO_Lines!$C$2:$C$2025,A11)/F11,0) | K11: =IFERROR(AVERAGEIFS(PO_Lines!$V$2:$V$2025,PO_Lines!$C$2:$C$2025,A11,PO_Lines!$V$2:$V$2025,">0"),0) | L11: =IFERROR(SUMIFS(PO_Lines!$I$2:$I$2025,PO_Lines!$C$2:$C$2025,A11)/SUMIFS(PO_Lines!$H$2:$H$2025,PO_Lines!$C$2:$C$2025,A11),0) | M11: =IFERROR(AVERAGEIFS(PO_Lines!$R$2:$R$2025,PO_Lines!$C$2:$C$2025,A11,PO_Lines!$Q$2:$Q$2025,1),0) | N11: =IF(J11>=Assumptions!$B$14,"Preferred",IF(J11>=Assumptions!$B$15,"Approved","Improvement plan"))
A12: S08 | B12: Bavaria Display AG | C12: Germany | D12: =COUNTIF(Items!$D$2:$D$117,A12) | E12: =COUNTIFS(Items!$D$2:$D$117,A12,Items!$I$2:$I$117,TRUE) | F12: =COUNTIFS(PO_Lines!$C$2:$C$2025,A12,PO_Lines!$Q$2:$Q$2025,1) | G12: =SUMIFS(PO_Lines!$O$2:$O$2025,PO_Lines!$C$2:$C$2025,A12,PO_Lines!$D$2:$D$2025,">="&Assumptions!$B$13) | H12: =IFERROR(SUMIFS(PO_Lines!$S$2:$S$2025,PO_Lines!$C$2:$C$2025,A12)/F12,0) | I12: =IFERROR(SUMIFS(PO_Lines!$T$2:$T$2025,PO_Lines!$C$2:$C$2025,A12)/F12,0) | J12: =IFERROR(SUMIFS(PO_Lines!$U$2:$U$2025,PO_Lines!$C$2:$C$2025,A12)/F12,0) | K12: =IFERROR(AVERAGEIFS(PO_Lines!$V$2:$V$2025,PO_Lines!$C$2:$C$2025,A12,PO_Lines!$V$2:$V$2025,">0"),0) | L12: =IFERROR(SUMIFS(PO_Lines!$I$2:$I$2025,PO_Lines!$C$2:$C$2025,A12)/SUMIFS(PO_Lines!$H$2:$H$2025,PO_Lines!$C$2:$C$2025,A12),0) | M12: =IFERROR(AVERAGEIFS(PO_Lines!$R$2:$R$2025,PO_Lines!$C$2:$C$2025,A12,PO_Lines!$Q$2:$Q$2025,1),0) | N12: =IF(J12>=Assumptions!$B$14,"Preferred",IF(J12>=Assumptions!$B$15,"Approved","Improvement plan"))
A13: S09 | B13: Atlantic Polymers Ltd | C13: Ireland | D13: =COUNTIF(Items!$D$2:$D$117,A13) | E13: =COUNTIFS(Items!$D$2:$D$117,A13,Items!$I$2:$I$117,TRUE) | F13: =COUNTIFS(PO_Lines!$C$2:$C$2025,A13,PO_Lines!$Q$2:$Q$2025,1) | G13: =SUMIFS(PO_Lines!$O$2:$O$2025,PO_Lines!$C$2:$C$2025,A13,PO_Lines!$D$2:$D$2025,">="&Assumptions!$B$13) | H13: =IFERROR(SUMIFS(PO_Lines!$S$2:$S$2025,PO_Lines!$C$2:$C$2025,A13)/F13,0) | I13: =IFERROR(SUMIFS(PO_Lines!$T$2:$T$2025,PO_Lines!$C$2:$C$2025,A13)/F13,0) | J13: =IFERROR(SUMIFS(PO_Lines!$U$2:$U$2025,PO_Lines!$C$2:$C$2025,A13)/F13,0) | K13: =IFERROR(AVERAGEIFS(PO_Lines!$V$2:$V$2025,PO_Lines!$C$2:$C$2025,A13,PO_Lines!$V$2:$V$2025,">0"),0) | L13: =IFERROR(SUMIFS(PO_Lines!$I$2:$I$2025,PO_Lines!$C$2:$C$2025,A13)/SUMIFS(PO_Lines!$H$2:$H$2025,PO_Lines!$C$2:$C$2025,A13),0) | M13: =IFERROR(AVERAGEIFS(PO_Lines!$R$2:$R$2025,PO_Lines!$C$2:$C$2025,A13,PO_Lines!$Q$2:$Q$2025,1),0) | N13: =IF(J13>=Assumptions!$B$14,"Preferred",IF(J13>=Assumptions!$B$15,"Approved","Improvement plan"))
A14: S10 | B14: Nordic Passive Components | C14: Sweden | D14: =COUNTIF(Items!$D$2:$D$117,A14) | E14: =COUNTIFS(Items!$D$2:$D$117,A14,Items!$I$2:$I$117,TRUE) | F14: =COUNTIFS(PO_Lines!$C$2:$C$2025,A14,PO_Lines!$Q$2:$Q$2025,1) | G14: =SUMIFS(PO_Lines!$O$2:$O$2025,PO_Lines!$C$2:$C$2025,A14,PO_Lines!$D$2:$D$2025,">="&Assumptions!$B$13) | H14: =IFERROR(SUMIFS(PO_Lines!$S$2:$S$2025,PO_Lines!$C$2:$C$2025,A14)/F14,0) | I14: =IFERROR(SUMIFS(PO_Lines!$T$2:$T$2025,PO_Lines!$C$2:$C$2025,A14)/F14,0) | J14: =IFERROR(SUMIFS(PO_Lines!$U$2:$U$2025,PO_Lines!$C$2:$C$2025,A14)/F14,0) | K14: =IFERROR(AVERAGEIFS(PO_Lines!$V$2:$V$2025,PO_Lines!$C$2:$C$2025,A14,PO_Lines!$V$2:$V$2025,">0"),0) | L14: =IFERROR(SUMIFS(PO_Lines!$I$2:$I$2025,PO_Lines!$C$2:$C$2025,A14)/SUMIFS(PO_Lines!$H$2:$H$2025,PO_Lines!$C$2:$C$2025,A14),0) | M14: =IFERROR(AVERAGEIFS(PO_Lines!$R$2:$R$2025,PO_Lines!$C$2:$C$2025,A14,PO_Lines!$Q$2:$Q$2025,1),0) | N14: =IF(J14>=Assumptions!$B$14,"Preferred",IF(J14>=Assumptions!$B$15,"Approved","Improvement plan"))
A15: S11 | B15: Kyushu Semiconductor KK | C15: Japan | D15: =COUNTIF(Items!$D$2:$D$117,A15) | E15: =COUNTIFS(Items!$D$2:$D$117,A15,Items!$I$2:$I$117,TRUE) | F15: =COUNTIFS(PO_Lines!$C$2:$C$2025,A15,PO_Lines!$Q$2:$Q$2025,1) | G15: =SUMIFS(PO_Lines!$O$2:$O$2025,PO_Lines!$C$2:$C$2025,A15,PO_Lines!$D$2:$D$2025,">="&Assumptions!$B$13) | H15: =IFERROR(SUMIFS(PO_Lines!$S$2:$S$2025,PO_Lines!$C$2:$C$2025,A15)/F15,0) | I15: =IFERROR(SUMIFS(PO_Lines!$T$2:$T$2025,PO_Lines!$C$2:$C$2025,A15)/F15,0) | J15: =IFERROR(SUMIFS(PO_Lines!$U$2:$U$2025,PO_Lines!$C$2:$C$2025,A15)/F15,0) | K15: =IFERROR(AVERAGEIFS(PO_Lines!$V$2:$V$2025,PO_Lines!$C$2:$C$2025,A15,PO_Lines!$V$2:$V$2025,">0"),0) | L15: =IFERROR(SUMIFS(PO_Lines!$I$2:$I$2025,PO_Lines!$C$2:$C$2025,A15)/SUMIFS(PO_Lines!$H$2:$H$2025,PO_Lines!$C$2:$C$2025,A15),0) | M15: =IFERROR(AVERAGEIFS(PO_Lines!$R$2:$R$2025,PO_Lines!$C$2:$C$2025,A15,PO_Lines!$Q$2:$Q$2025,1),0) | N15: =IF(J15>=Assumptions!$B$14,"Preferred",IF(J15>=Assumptions!$B$15,"Approved","Improvement plan"))
A16: S12 | B16: Dublin Sterile Packaging | C16: Ireland | D16: =COUNTIF(Items!$D$2:$D$117,A16) | E16: =COUNTIFS(Items!$D$2:$D$117,A16,Items!$I$2:$I$117,TRUE) | F16: =COUNTIFS(PO_Lines!$C$2:$C$2025,A16,PO_Lines!$Q$2:$Q$2025,1) | G16: =SUMIFS(PO_Lines!$O$2:$O$2025,PO_Lines!$C$2:$C$2025,A16,PO_Lines!$D$2:$D$2025,">="&Assumptions!$B$13) | H16: =IFERROR(SUMIFS(PO_Lines!$S$2:$S$2025,PO_Lines!$C$2:$C$2025,A16)/F16,0) | I16: =IFERROR(SUMIFS(PO_Lines!$T$2:$T$2025,PO_Lines!$C$2:$C$2025,A16)/F16,0) | J16: =IFERROR(SUMIFS(PO_Lines!$U$2:$U$2025,PO_Lines!$C$2:$C$2025,A16)/F16,0) | K16: =IFERROR(AVERAGEIFS(PO_Lines!$V$2:$V$2025,PO_Lines!$C$2:$C$2025,A16,PO_Lines!$V$2:$V$2025,">0"),0) | L16: =IFERROR(SUMIFS(PO_Lines!$I$2:$I$2025,PO_Lines!$C$2:$C$2025,A16)/SUMIFS(PO_Lines!$H$2:$H$2025,PO_Lines!$C$2:$C$2025,A16),0) | M16: =IFERROR(AVERAGEIFS(PO_Lines!$R$2:$R$2025,PO_Lines!$C$2:$C$2025,A16,PO_Lines!$Q$2:$Q$2025,1),0) | N16: =IF(J16>=Assumptions!$B$14,"Preferred",IF(J16>=Assumptions!$B$15,"Approved","Improvement plan"))
A17: Total / weighted | D17: =SUM(D5:D16) | E17: =SUM(E5:E16) | F17: =SUM(F5:F16) | G17: =SUM(G5:G16) | H17: =SUMPRODUCT(H5:H16,$F$5:$F$16)/$F$17 | I17: =SUMPRODUCT(I5:I16,$F$5:$F$16)/$F$17 | J17: =SUMPRODUCT(J5:J16,$F$5:$F$16)/$F$17
A19: OTIF = share of received POs delivered on or before the promised date AND in full. Rating thresholds are on the Assumptions sheet.

Sheet Budget_vs_Actual
A1: Purchasing Budget vs Actual: FY Oct-2025 to Sep-2026
A2: Budget = planned purchases at standard cost. Actual = PO value at actual price (formulas on PO_Lines).
A4: Budget (€)
A5: Category | B5: 2025-10 | C5: 2025-11 | D5: 2025-12 | E5: 2026-01 | F5: 2026-02 | G5: 2026-03 | H5: 2026-04 | I5: 2026-05 | J5: 2026-06 | K5: 2026-07 | L5: 2026-08 | M5: 2026-09 | N5: FY total
A6: Microcontrollers & ICs | B6: 753100 | C6: 701200 | D6: 701700 | E6: 654900 | F6: 843400 | G6: 907100 | H6: 875900 | I6: 886700 | J6: 1036100 | K6: 1021100 | L6: 721700 | M6: 987800 | N6: =SUM(B6:M6)
A7: Sensors | B7: 791200 | C7: 736600 | D7: 737200 | E7: 687900 | F7: 886000 | G7: 952900 | H7: 920200 | I7: 931500 | J7: 1088400 | K7: 1072700 | L7: 758100 | M7: 1037700 | N7: =SUM(B7:M7)
A8: Printed circuit boards | B8: 275600 | C8: 256600 | D8: 256800 | E8: 239600 | F8: 308600 | G8: 331900 | H8: 320500 | I8: 324500 | J8: 379100 | K8: 373600 | L8: 264100 | M8: 361400 | N8: =SUM(B8:M8)
A9: Batteries | B9: 222600 | C9: 207200 | D9: 207400 | E9: 193500 | F9: 249200 | G9: 268100 | H9: 258900 | I9: 262100 | J9: 306200 | K9: 301800 | L9: 213300 | M9: 291900 | N9: =SUM(B9:M9)
A10: Passive components | B10: 129200 | C10: 120300 | D10: 120400 | E10: 112400 | F10: 144700 | G10: 155700 | H10: 150300 | I10: 152200 | J10: 177800 | K10: 175200 | L10: 123800 | M10: 169500 | N10: =SUM(B10:M10)
A11: Connectors & cables | B11: 135900 | C11: 126500 | D11: 126600 | E11: 118200 | F11: 152200 | G11: 163700 | H11: 158100 | I11: 160000 | J11: 187000 | K11: 184300 | L11: 130200 | M11: 178300 | N11: =SUM(B11:M11)
A12: Displays | B12: 116400 | C12: 108400 | D12: 108500 | E12: 101200 | F12: 130400 | G12: 140200 | H12: 135400 | I12: 137100 | J12: 160200 | K12: 157900 | L12: 111600 | M12: 152700 | N12: =SUM(B12:M12)
A13: Enclosures & plastics | B13: 84100 | C13: 78300 | D13: 78300 | E13: 73100 | F13: 94100 | G13: 101200 | H13: 97800 | I13: 99000 | J13: 115700 | K13: 114000 | L13: 80600 | M13: 110300 | N13: =SUM(B13:M13)
A14: Sterile packaging | B14: 17400 | C14: 16200 | D14: 16200 | E14: 15100 | F14: 19500 | G14: 21000 | H14: 20200 | I14: 20500 | J14: 23900 | K14: 23600 | L14: 16700 | M14: 22800 | N14: =SUM(B14:M14)
A15: Total | B15: =SUM(B6:B14) | C15: =SUM(C6:C14) | D15: =SUM(D6:D14) | E15: =SUM(E6:E14) | F15: =SUM(F6:F14) | G15: =SUM(G6:G14) | H15: =SUM(H6:H14) | I15: =SUM(I6:I14) | ... N15: =SUM(N6:N14)
A18: Actual (€)
A19: Category | B19: 2025-10 | C19: 2025-11 | D19: 2025-12 | E19: 2026-01 | F19: 2026-02 | G19: 2026-03 | H19: 2026-04 | I19: 2026-05 | J19: 2026-06 | K19: 2026-07 | L19: 2026-08 | M19: 2026-09 | N19: FY total
A20: Microcontrollers & ICs | B20: =SUMIFS(PO_Lines!$O$2:$O$2025,PO_Lines!$L$2:$L$2025,$A20,PO_Lines!$N$2:$N$2025,B$19) | C20: =SUMIFS(PO_Lines!$O$2:$O$2025,PO_Lines!$L$2:$L$2025,$A20,PO_Lines!$N$2:$N$2025,C$19) | D20: =SUMIFS(PO_Lines!$O$2:$O$2025,PO_Lines!$L$2:$L$2025,$A20,PO_Lines!$N$2:$N$2025,D$19) | E20: =SUMIFS(PO_Lines!$O$2:$O$2025,PO_Lines!$L$2:$L$2025,$A20,PO_Lines!$N$2:$N$2025,E$19) | F20: =SUMIFS(PO_Lines!$O$2:$O$2025,PO_Lines!$L$2:$L$2025,$A20,PO_Lines!$N$2:$N$2025,F$19) | G20: =SUMIFS(PO_Lines!$O$2:$O$2025,PO_Lines!$L$2:$L$2025,$A20,PO_Lines!$N$2:$N$2025,G$19) | H20: =SUMIFS(PO_Lines!$O$2:$O$2025,PO_Lines!$L$2:$L$2025,$A20,PO_Lines!$N$2:$N$2025,H$19) | I20: =SUMIFS(PO_Lines!$O$2:$O$2025,PO_Lines!$L$2:$L$2025,$A20,PO_Lines!$N$2:$N$2025,I$19) | ... M20: =SUMIFS(PO_Lines!$O$2:$O$2025,PO_Lines!$L$2:$L$2025,$A20,PO_Lines!$N$2:$N$2025,M$19) | N20: =SUM(B20:M20)
A21: Sensors | B21: =SUMIFS(PO_Lines!$O$2:$O$2025,PO_Lines!$L$2:$L$2025,$A21,PO_Lines!$N$2:$N$2025,B$19) | C21: =SUMIFS(PO_Lines!$O$2:$O$2025,PO_Lines!$L$2:$L$2025,$A21,PO_Lines!$N$2:$N$2025,C$19) | D21: =SUMIFS(PO_Lines!$O$2:$O$2025,PO_Lines!$L$2:$L$2025,$A21,PO_Lines!$N$2:$N$2025,D$19) | E21: =SUMIFS(PO_Lines!$O$2:$O$2025,PO_Lines!$L$2:$L$2025,$A21,PO_Lines!$N$2:$N$2025,E$19) | F21: =SUMIFS(PO_Lines!$O$2:$O$2025,PO_Lines!$L$2:$L$2025,$A21,PO_Lines!$N$2:$N$2025,F$19) | G21: =SUMIFS(PO_Lines!$O$2:$O$2025,PO_Lines!$L$2:$L$2025,$A21,PO_Lines!$N$2:$N$2025,G$19) | H21: =SUMIFS(PO_Lines!$O$2:$O$2025,PO_Lines!$L$2:$L$2025,$A21,PO_Lines!$N$2:$N$2025,H$19) | I21: =SUMIFS(PO_Lines!$O$2:$O$2025,PO_Lines!$L$2:$L$2025,$A21,PO_Lines!$N$2:$N$2025,I$19) | ... M21: =SUMIFS(PO_Lines!$O$2:$O$2025,PO_Lines!$L$2:$L$2025,$A21,PO_Lines!$N$2:$N$2025,M$19) | N21: =SUM(B21:M21)
A22: Printed circuit boards | B22: =SUMIFS(PO_Lines!$O$2:$O$2025,PO_Lines!$L$2:$L$2025,$A22,PO_Lines!$N$2:$N$2025,B$19) | C22: =SUMIFS(PO_Lines!$O$2:$O$2025,PO_Lines!$L$2:$L$2025,$A22,PO_Lines!$N$2:$N$2025,C$19) | D22: =SUMIFS(PO_Lines!$O$2:$O$2025,PO_Lines!$L$2:$L$2025,$A22,PO_Lines!$N$2:$N$2025,D$19) | E22: =SUMIFS(PO_Lines!$O$2:$O$2025,PO_Lines!$L$2:$L$2025,$A22,PO_Lines!$N$2:$N$2025,E$19) | F22: =SUMIFS(PO_Lines!$O$2:$O$2025,PO_Lines!$L$2:$L$2025,$A22,PO_Lines!$N$2:$N$2025,F$19) | G22: =SUMIFS(PO_Lines!$O$2:$O$2025,PO_Lines!$L$2:$L$2025,$A22,PO_Lines!$N$2:$N$2025,G$19) | H22: =SUMIFS(PO_Lines!$O$2:$O$2025,PO_Lines!$L$2:$L$2025,$A22,PO_Lines!$N$2:$N$2025,H$19) | I22: =SUMIFS(PO_Lines!$O$2:$O$2025,PO_Lines!$L$2:$L$2025,$A22,PO_Lines!$N$2:$N$2025,I$19) | ... M22: =SUMIFS(PO_Lines!$O$2:$O$2025,PO_Lines!$L$2:$L$2025,$A22,PO_Lines!$N$2:$N$2025,M$19) | N22: =SUM(B22:M22)
A23: Batteries | B23: =SUMIFS(PO_Lines!$O$2:$O$2025,PO_Lines!$L$2:$L$2025,$A23,PO_Lines!$N$2:$N$2025,B$19) | C23: =SUMIFS(PO_Lines!$O$2:$O$2025,PO_Lines!$L$2:$L$2025,$A23,PO_Lines!$N$2:$N$2025,C$19) | D23: =SUMIFS(PO_Lines!$O$2:$O$2025,PO_Lines!$L$2:$L$2025,$A23,PO_Lines!$N$2:$N$2025,D$19) | E23: =SUMIFS(PO_Lines!$O$2:$O$2025,PO_Lines!$L$2:$L$2025,$A23,PO_Lines!$N$2:$N$2025,E$19) | F23: =SUMIFS(PO_Lines!$O$2:$O$2025,PO_Lines!$L$2:$L$2025,$A23,PO_Lines!$N$2:$N$2025,F$19) | G23: =SUMIFS(PO_Lines!$O$2:$O$2025,PO_Lines!$L$2:$L$2025,$A23,PO_Lines!$N$2:$N$2025,G$19) | H23: =SUMIFS(PO_Lines!$O$2:$O$2025,PO_Lines!$L$2:$L$2025,$A23,PO_Lines!$N$2:$N$2025,H$19) | I23: =SUMIFS(PO_Lines!$O$2:$O$2025,PO_Lines!$L$2:$L$2025,$A23,PO_Lines!$N$2:$N$2025,I$19) | ... M23: =SUMIFS(PO_Lines!$O$2:$O$2025,PO_Lines!$L$2:$L$2025,$A23,PO_Lines!$N$2:$N$2025,M$19) | N23: =SUM(B23:M23)
A24: Passive components | B24: =SUMIFS(PO_Lines!$O$2:$O$2025,PO_Lines!$L$2:$L$2025,$A24,PO_Lines!$N$2:$N$2025,B$19) | C24: =SUMIFS(PO_Lines!$O$2:$O$2025,PO_Lines!$L$2:$L$2025,$A24,PO_Lines!$N$2:$N$2025,C$19) | D24: =SUMIFS(PO_Lines!$O$2:$O$2025,PO_Lines!$L$2:$L$2025,$A24,PO_Lines!$N$2:$N$2025,D$19) | E24: =SUMIFS(PO_Lines!$O$2:$O$2025,PO_Lines!$L$2:$L$2025,$A24,PO_Lines!$N$2:$N$2025,E$19) | F24: =SUMIFS(PO_Lines!$O$2:$O$2025,PO_Lines!$L$2:$L$2025,$A24,PO_Lines!$N$2:$N$2025,F$19) | G24: =SUMIFS(PO_Lines!$O$2:$O$2025,PO_Lines!$L$2:$L$2025,$A24,PO_Lines!$N$2:$N$2025,G$19) | H24: =SUMIFS(PO_Lines!$O$2:$O$2025,PO_Lines!$L$2:$L$2025,$A24,PO_Lines!$N$2:$N$2025,H$19) | I24: =SUMIFS(PO_Lines!$O$2:$O$2025,PO_Lines!$L$2:$L$2025,$A24,PO_Lines!$N$2:$N$2025,I$19) | ... M24: =SUMIFS(PO_Lines!$O$2:$O$2025,PO_Lines!$L$2:$L$2025,$A24,PO_Lines!$N$2:$N$2025,M$19) | N24: =SUM(B24:M24)
A25: Connectors & cables | B25: =SUMIFS(PO_Lines!$O$2:$O$2025,PO_Lines!$L$2:$L$2025,$A25,PO_Lines!$N$2:$N$2025,B$19) | C25: =SUMIFS(PO_Lines!$O$2:$O$2025,PO_Lines!$L$2:$L$2025,$A25,PO_Lines!$N$2:$N$2025,C$19) | D25: =SUMIFS(PO_Lines!$O$2:$O$2025,PO_Lines!$L$2:$L$2025,$A25,PO_Lines!$N$2:$N$2025,D$19) | E25: =SUMIFS(PO_Lines!$O$2:$O$2025,PO_Lines!$L$2:$L$2025,$A25,PO_Lines!$N$2:$N$2025,E$19) | F25: =SUMIFS(PO_Lines!$O$2:$O$2025,PO_Lines!$L$2:$L$2025,$A25,PO_Lines!$N$2:$N$2025,F$19) | G25: =SUMIFS(PO_Lines!$O$2:$O$2025,PO_Lines!$L$2:$L$2025,$A25,PO_Lines!$N$2:$N$2025,G$19) | H25: =SUMIFS(PO_Lines!$O$2:$O$2025,PO_Lines!$L$2:$L$2025,$A25,PO_Lines!$N$2:$N$2025,H$19) | I25: =SUMIFS(PO_Lines!$O$2:$O$2025,PO_Lines!$L$2:$L$2025,$A25,PO_Lines!$N$2:$N$2025,I$19) | ... M25: =SUMIFS(PO_Lines!$O$2:$O$2025,PO_Lines!$L$2:$L$2025,$A25,PO_Lines!$N$2:$N$2025,M$19) | N25: =SUM(B25:M25)
A26: Displays | B26: =SUMIFS(PO_Lines!$O$2:$O$2025,PO_Lines!$L$2:$L$2025,$A26,PO_Lines!$N$2:$N$2025,B$19) | C26: =SUMIFS(PO_Lines!$O$2:$O$2025,PO_Lines!$L$2:$L$2025,$A26,PO_Lines!$N$2:$N$2025,C$19) | D26: =SUMIFS(PO_Lines!$O$2:$O$2025,PO_Lines!$L$2:$L$2025,$A26,PO_Lines!$N$2:$N$2025,D$19) | E26: =SUMIFS(PO_Lines!$O$2:$O$2025,PO_Lines!$L$2:$L$2025,$A26,PO_Lines!$N$2:$N$2025,E$19) | F26: =SUMIFS(PO_Lines!$O$2:$O$2025,PO_Lines!$L$2:$L$2025,$A26,PO_Lines!$N$2:$N$2025,F$19) | G26: =SUMIFS(PO_Lines!$O$2:$O$2025,PO_Lines!$L$2:$L$2025,$A26,PO_Lines!$N$2:$N$2025,G$19) | H26: =SUMIFS(PO_Lines!$O$2:$O$2025,PO_Lines!$L$2:$L$2025,$A26,PO_Lines!$N$2:$N$2025,H$19) | I26: =SUMIFS(PO_Lines!$O$2:$O$2025,PO_Lines!$L$2:$L$2025,$A26,PO_Lines!$N$2:$N$2025,I$19) | ... M26: =SUMIFS(PO_Lines!$O$2:$O$2025,PO_Lines!$L$2:$L$2025,$A26,PO_Lines!$N$2:$N$2025,M$19) | N26: =SUM(B26:M26)
A27: Enclosures & plastics | B27: =SUMIFS(PO_Lines!$O$2:$O$2025,PO_Lines!$L$2:$L$2025,$A27,PO_Lines!$N$2:$N$2025,B$19) | C27: =SUMIFS(PO_Lines!$O$2:$O$2025,PO_Lines!$L$2:$L$2025,$A27,PO_Lines!$N$2:$N$2025,C$19) | D27: =SUMIFS(PO_Lines!$O$2:$O$2025,PO_Lines!$L$2:$L$2025,$A27,PO_Lines!$N$2:$N$2025,D$19) | E27: =SUMIFS(PO_Lines!$O$2:$O$2025,PO_Lines!$L$2:$L$2025,$A27,PO_Lines!$N$2:$N$2025,E$19) | F27: =SUMIFS(PO_Lines!$O$2:$O$2025,PO_Lines!$L$2:$L$2025,$A27,PO_Lines!$N$2:$N$2025,F$19) | G27: =SUMIFS(PO_Lines!$O$2:$O$2025,PO_Lines!$L$2:$L$2025,$A27,PO_Lines!$N$2:$N$2025,G$19) | H27: =SUMIFS(PO_Lines!$O$2:$O$2025,PO_Lines!$L$2:$L$2025,$A27,PO_Lines!$N$2:$N$2025,H$19) | I27: =SUMIFS(PO_Lines!$O$2:$O$2025,PO_Lines!$L$2:$L$2025,$A27,PO_Lines!$N$2:$N$2025,I$19) | ... M27: =SUMIFS(PO_Lines!$O$2:$O$2025,PO_Lines!$L$2:$L$2025,$A27,PO_Lines!$N$2:$N$2025,M$19) | N27: =SUM(B27:M27)
A28: Sterile packaging | B28: =SUMIFS(PO_Lines!$O$2:$O$2025,PO_Lines!$L$2:$L$2025,$A28,PO_Lines!$N$2:$N$2025,B$19) | C28: =SUMIFS(PO_Lines!$O$2:$O$2025,PO_Lines!$L$2:$L$2025,$A28,PO_Lines!$N$2:$N$2025,C$19) | D28: =SUMIFS(PO_Lines!$O$2:$O$2025,PO_Lines!$L$2:$L$2025,$A28,PO_Lines!$N$2:$N$2025,D$19) | E28: =SUMIFS(PO_Lines!$O$2:$O$2025,PO_Lines!$L$2:$L$2025,$A28,PO_Lines!$N$2:$N$2025,E$19) | F28: =SUMIFS(PO_Lines!$O$2:$O$2025,PO_Lines!$L$2:$L$2025,$A28,PO_Lines!$N$2:$N$2025,F$19) | G28: =SUMIFS(PO_Lines!$O$2:$O$2025,PO_Lines!$L$2:$L$2025,$A28,PO_Lines!$N$2:$N$2025,G$19) | H28: =SUMIFS(PO_Lines!$O$2:$O$2025,PO_Lines!$L$2:$L$2025,$A28,PO_Lines!$N$2:$N$2025,H$19) | I28: =SUMIFS(PO_Lines!$O$2:$O$2025,PO_Lines!$L$2:$L$2025,$A28,PO_Lines!$N$2:$N$2025,I$19) | ... M28: =SUMIFS(PO_Lines!$O$2:$O$2025,PO_Lines!$L$2:$L$2025,$A28,PO_Lines!$N$2:$N$2025,M$19) | N28: =SUM(B28:M28)
A29: Total | B29: =SUM(B20:B28) | C29: =SUM(C20:C28) | D29: =SUM(D20:D28) | E29: =SUM(E20:E28) | F29: =SUM(F20:F28) | G29: =SUM(G20:G28) | H29: =SUM(H20:H28) | I29: =SUM(I20:I28) | ... N29: =SUM(N20:N28)
A32: Variance: actual minus budget (€)
A33: Category | B33: 2025-10 | C33: 2025-11 | D33: 2025-12 | E33: 2026-01 | F33: 2026-02 | G33: 2026-03 | H33: 2026-04 | I33: 2026-05 | J33: 2026-06 | K33: 2026-07 | L33: 2026-08 | M33: 2026-09 | N33: FY total
A34: Microcontrollers & ICs | B34: =B20-B6 | C34: =C20-C6 | D34: =D20-D6 | E34: =E20-E6 | F34: =F20-F6 | G34: =G20-G6 | H34: =H20-H6 | I34: =I20-I6 | ... M34: =M20-M6 | N34: =SUM(B34:M34)
A35: Sensors | B35: =B21-B7 | C35: =C21-C7 | D35: =D21-D7 | E35: =E21-E7 | F35: =F21-F7 | G35: =G21-G7 | H35: =H21-H7 | I35: =I21-I7 | ... M35: =M21-M7 | N35: =SUM(B35:M35)
A36: Printed circuit boards | B36: =B22-B8 | C36: =C22-C8 | D36: =D22-D8 | E36: =E22-E8 | F36: =F22-F8 | G36: =G22-G8 | H36: =H22-H8 | I36: =I22-I8 | ... M36: =M22-M8 | N36: =SUM(B36:M36)
A37: Batteries | B37: =B23-B9 | C37: =C23-C9 | D37: =D23-D9 | E37: =E23-E9 | F37: =F23-F9 | G37: =G23-G9 | H37: =H23-H9 | I37: =I23-I9 | ... M37: =M23-M9 | N37: =SUM(B37:M37)
A38: Passive components | B38: =B24-B10 | C38: =C24-C10 | D38: =D24-D10 | E38: =E24-E10 | F38: =F24-F10 | G38: =G24-G10 | H38: =H24-H10 | I38: =I24-I10 | ... M38: =M24-M10 | N38: =SUM(B38:M38)
A39: Connectors & cables | B39: =B25-B11 | C39: =C25-C11 | D39: =D25-D11 | E39: =E25-E11 | F39: =F25-F11 | G39: =G25-G11 | H39: =H25-H11 | I39: =I25-I11 | ... M39: =M25-M11 | N39: =SUM(B39:M39)
A40: Displays | B40: =B26-B12 | C40: =C26-C12 | D40: =D26-D12 | E40: =E26-E12 | F40: =F26-F12 | G40: =G26-G12 | H40: =H26-H12 | I40: =I26-I12 | ... M40: =M26-M12 | N40: =SUM(B40:M40)
A41: Enclosures & plastics | B41: =B27-B13 | C41: =C27-C13 | D41: =D27-D13 | E41: =E27-E13 | F41: =F27-F13 | G41: =G27-G13 | H41: =H27-H13 | I41: =I27-I13 | ... M41: =M27-M13 | N41: =SUM(B41:M41)
A42: Sterile packaging | B42: =B28-B14 | C42: =C28-C14 | D42: =D28-D14 | E42: =E28-E14 | F42: =F28-F14 | G42: =G28-G14 | H42: =H28-H14 | I42: =I28-I14 | ... M42: =M28-M14 | N42: =SUM(B42:M42)
A43: Total | B43: =SUM(B34:B42) | C43: =SUM(C34:C42) | D43: =SUM(D34:D42) | E43: =SUM(E34:E42) | F43: =SUM(F34:F42) | G43: =SUM(G34:G42) | H43: =SUM(H34:H42) | I43: =SUM(I34:I42) | ... N43: =SUM(N34:N42)
A46: FY variance analysis: price vs volume/timing
A47: Category | B47: FY budget (€) | C47: FY actual (€) | D47: Variance (€) | E47: Variance % | F47: Price variance (€) | G47: Volume / timing (€) | H47: Main driver
A48: Microcontrollers & ICs | B48: =N6 | C48: =N20 | D48: =C48-B48 | E48: =IFERROR(D48/B48,0) | F48: =SUMIFS(PO_Lines!$P$2:$P$2025,PO_Lines!$L$2:$L$2025,A48,PO_Lines!$D$2:$D$2025,">="&Assumptions!$B$13) | G48: =D48-F48 | H48: =IF(ABS(D48)<0.02*B48,"On budget",IF(ABS(F48)>ABS(G48),"Price","Volume / timing"))
A49: Sensors | B49: =N7 | C49: =N21 | D49: =C49-B49 | E49: =IFERROR(D49/B49,0) | F49: =SUMIFS(PO_Lines!$P$2:$P$2025,PO_Lines!$L$2:$L$2025,A49,PO_Lines!$D$2:$D$2025,">="&Assumptions!$B$13) | G49: =D49-F49 | H49: =IF(ABS(D49)<0.02*B49,"On budget",IF(ABS(F49)>ABS(G49),"Price","Volume / timing"))
A50: Printed circuit boards | B50: =N8 | C50: =N22 | D50: =C50-B50 | E50: =IFERROR(D50/B50,0) | F50: =SUMIFS(PO_Lines!$P$2:$P$2025,PO_Lines!$L$2:$L$2025,A50,PO_Lines!$D$2:$D$2025,">="&Assumptions!$B$13) | G50: =D50-F50 | H50: =IF(ABS(D50)<0.02*B50,"On budget",IF(ABS(F50)>ABS(G50),"Price","Volume / timing"))
A51: Batteries | B51: =N9 | C51: =N23 | D51: =C51-B51 | E51: =IFERROR(D51/B51,0) | F51: =SUMIFS(PO_Lines!$P$2:$P$2025,PO_Lines!$L$2:$L$2025,A51,PO_Lines!$D$2:$D$2025,">="&Assumptions!$B$13) | G51: =D51-F51 | H51: =IF(ABS(D51)<0.02*B51,"On budget",IF(ABS(F51)>ABS(G51),"Price","Volume / timing"))
A52: Passive components | B52: =N10 | C52: =N24 | D52: =C52-B52 | E52: =IFERROR(D52/B52,0) | F52: =SUMIFS(PO_Lines!$P$2:$P$2025,PO_Lines!$L$2:$L$2025,A52,PO_Lines!$D$2:$D$2025,">="&Assumptions!$B$13) | G52: =D52-F52 | H52: =IF(ABS(D52)<0.02*B52,"On budget",IF(ABS(F52)>ABS(G52),"Price","Volume / timing"))
A53: Connectors & cables | B53: =N11 | C53: =N25 | D53: =C53-B53 | E53: =IFERROR(D53/B53,0) | F53: =SUMIFS(PO_Lines!$P$2:$P$2025,PO_Lines!$L$2:$L$2025,A53,PO_Lines!$D$2:$D$2025,">="&Assumptions!$B$13) | G53: =D53-F53 | H53: =IF(ABS(D53)<0.02*B53,"On budget",IF(ABS(F53)>ABS(G53),"Price","Volume / timing"))
A54: Displays | B54: =N12 | C54: =N26 | D54: =C54-B54 | E54: =IFERROR(D54/B54,0) | F54: =SUMIFS(PO_Lines!$P$2:$P$2025,PO_Lines!$L$2:$L$2025,A54,PO_Lines!$D$2:$D$2025,">="&Assumptions!$B$13) | G54: =D54-F54 | H54: =IF(ABS(D54)<0.02*B54,"On budget",IF(ABS(F54)>ABS(G54),"Price","Volume / timing"))
A55: Enclosures & plastics | B55: =N13 | C55: =N27 | D55: =C55-B55 | E55: =IFERROR(D55/B55,0) | F55: =SUMIFS(PO_Lines!$P$2:$P$2025,PO_Lines!$L$2:$L$2025,A55,PO_Lines!$D$2:$D$2025,">="&Assumptions!$B$13) | G55: =D55-F55 | H55: =IF(ABS(D55)<0.02*B55,"On budget",IF(ABS(F55)>ABS(G55),"Price","Volume / timing"))
A56: Sterile packaging | B56: =N14 | C56: =N28 | D56: =C56-B56 | E56: =IFERROR(D56/B56,0) | F56: =SUMIFS(PO_Lines!$P$2:$P$2025,PO_Lines!$L$2:$L$2025,A56,PO_Lines!$D$2:$D$2025,">="&Assumptions!$B$13) | G56: =D56-F56 | H56: =IF(ABS(D56)<0.02*B56,"On budget",IF(ABS(F56)>ABS(G56),"Price","Volume / timing"))
A57: Total | B57: =N15 | C57: =N29 | D57: =C57-B57 | E57: =IFERROR(D57/B57,0) | F57: =SUM(F48:F56) | G57: =D57-F57 | H57: =IF(ABS(D57)<0.02*B57,"On budget",IF(ABS(F57)>ABS(G57),"Price","Volume / timing"))

Sheet Assumptions
A1: Assumptions
A2: Yellow cells are inputs. Every analysis formula references these cells.
A3: Assumption | B3: Value | C3: Notes | E3: ABC class | F3: Target service level | G3: z-score
A4: Snapshot date | B4: 46295 | C4: Date of the stock count. | E4: A | F4: 0.98 | G4: =NORMSINV(F4)
A5: Ordering cost per PO (€) | B5: 85 | C5: Buyer time, receiving, inspection and invoice processing per order. | E5: B | F5: 0.95 | G5: =NORMSINV(F5)
A6: Annual holding cost rate | B6: 0.22 | C6: Cost of capital + storage + insurance + obsolescence, % of unit cost per year. | E6: C | F6: 0.9 | G6: =NORMSINV(F6)
A7: ABC: A-class up to cumulative spend | B7: 0.8 | C7: Items making up the first 80% of spend are A.
A8: ABC: B-class up to cumulative spend | B8: 0.95 | C8: Next 15% are B, remainder C. | E8: Higher service for A items: they are critical to production and expensive to run out of.
A9: XYZ: X-class max coefficient of variation | B9: 0.25 | C9: Stable demand.
A10: XYZ: Y-class max coefficient of variation | B10: 0.5 | C10: Variable demand; above this is Z (erratic).
A11: Days per month | B11: 30.4 | C11: Converts lead time in days to months of demand.
A12: Expiry warning window (months) | B12: 6 | C12: Flag lots expiring within this window.
A13: Budget year start | B13: 45931 | C13: FY runs Oct to Sep.
A14: Supplier OTIF: Preferred at or above | B14: 0.95 | C14: Rating thresholds for the scorecard.
A15: Supplier OTIF: Approved at or above | B15: 0.85 | C15: Below this = improvement plan.
A16: Minimum order cover (months) | B16: 1 | C16: Suppliers ship monthly at most, so order quantity is never below 1 month of demand.

Sheet Items
A1: sku | B1: description | C1: category | D1: supplier_id | E1: unit_cost_eur | F1: quoted_lead_time_days | G1: moq | H1: shelf_life_months | I1: single_source
A2: CMD-0001 | B2: ARM Cortex-M4 MCU | C2: Microcontrollers & ICs | D2: S07 | E2: 14.26 | F2: 91 | G2: 1 | H2: 0 | I2: FALSE
A3: CMD-0002 | B3: ARM Cortex-M0+ MCU | C3: Microcontrollers & ICs | D3: S11 | E3: 6.85 | F3: 119 | G3: 25 | H3: 0 | I3: FALSE
A4: CMD-0003 | B4: Bluetooth LE SoC | C4: Microcontrollers & ICs | D4: S11 | E4: 21.49 | F4: 119 | G4: 10 | H4: 0 | I4: FALSE
A5: CMD-0004 | B5: ECG analog front end | C5: Microcontrollers & ICs | D5: S07 | E5: 4.05 | F5: 91 | G5: 100 | H5: 0 | I5: FALSE
A6: CMD-0005 | B6: Power management IC | C6: Microcontrollers & ICs | D6: S07 | E6: 5.63 | F6: 91 | G6: 50 | H6: 0 | I6: FALSE
A7: CMD-0006 | B7: Motor driver IC | C7: Microcontrollers & ICs | D7: S03 | E7: 30.55 | F7: 133 | G7: 100 | H7: 0 | I7: FALSE
A8: CMD-0007 | B8: 16-bit ADC | C8: Microcontrollers & ICs | D8: S03 | E8: 19.39 | F8: 133 | G8: 50 | H8: 0 | I8: FALSE
A9: CMD-0008 | B9: Op-amp quad | C9: Microcontrollers & ICs | D9: S03 | E9: 23.66 | F9: 133 | G9: 25 | H9: 0 | I9: FALSE
A10: CMD-0009 | B10: Flash memory 64Mb | C10: Microcontrollers & ICs | D10: S11 | E10: 6.29 | F10: 119 | G10: 25 | H10: 0 | I10: FALSE
A11: CMD-0010 | B11: Isolated gate driver | C11: Microcontrollers & ICs | D11: S03 | E11: 4.63 | F11: 133 | G11: 10 | H11: 0 | I11: FALSE
A12: CMD-0011 | B12: LDO regulator 3.3V | C12: Microcontrollers & ICs | D12: S07 | E12: 8.08 | F12: 91 | G12: 25 | H12: 0 | I12: FALSE
A13: CMD-0012 | B13: Buck converter IC | C13: Microcontrollers & ICs | D13: S03 | E13: 2.59 | F13: 133 | G13: 50 | H13: 0 | I13: FALSE
... A117: CMD-0116 | B117: Hydrogel electrode pad | C117: Sterile packaging | D117: S12 | E117: 0.3644 | F117: 7 | G117: 1 | H117: 36 | I117: TRUE

Sheet Suppliers
A1: supplier_id | B1: supplier_name | C1: country
A2: S01 | B2: Shannon Electronics Ltd | C2: Ireland
A3: S02 | B3: Rhein Sensorik GmbH | C3: Germany
A4: S03 | B4: Formosa Microtech Co. | C4: Taiwan
A5: S04 | B5: Penang Precision Sdn Bhd | C5: Malaysia
A6: S05 | B6: Shenzhen Brightcell Power | C6: China
A7: S06 | B7: Midlands Connect UK | C7: United Kingdom
A8: S07 | B8: Lakeview Circuits Inc. | C8: USA
A9: S08 | B9: Bavaria Display AG | C9: Germany
A10: S09 | B10: Atlantic Polymers Ltd | C10: Ireland
A11: S10 | B11: Nordic Passive Components | C11: Sweden
A12: S11 | B12: Kyushu Semiconductor KK | C12: Japan
A13: S12 | B13: Dublin Sterile Packaging | C13: Ireland

Sheet Demand
A1: sku | B1: 2024-10 | C1: 2024-11 | D1: 2024-12 | E1: 2025-01 | F1: 2025-02 | G1: 2025-03 | H1: 2025-04 | I1: 2025-05 | J1: 2025-06 | K1: 2025-07 | L1: 2025-08 | M1: 2025-09 | N1: 2025-10 | O1: 2025-11 | P1: 2025-12 | Q1: 2026-01 | R1: 2026-02 | S1: 2026-03 | T1: 2026-04 | U1: 2026-05 | V1: 2026-06 | W1: 2026-07 | X1: 2026-08 | Y1: 2026-09
A2: CMD-0001 | B2: 5781 | C2: 5709 | D2: 5571 | E2: 5464 | F2: 6165 | G2: 7353 | H2: 6290 | I2: 7637 | J2: 7449 | K2: 7151 | L2: 5395 | M2: 7858 | N2: 8049 | O2: 6934 | P2: 6954 | Q2: 5916 | R2: 8279 | S2: 8690 | T2: 9644 | U2: 8485 | V2: 10273 | W2: 10781 | X2: 7410 | Y2: 9173
A3: CMD-0002 | B3: 5977 | C3: 6013 | D3: 5580 | E3: 6052 | F3: 6082 | G3: 6873 | H3: 6489 | I3: 7741 | J3: 8202 | K3: 7772 | L3: 5867 | M3: 8282 | N3: 7532 | O3: 7627 | P3: 7207 | Q3: 6734 | R3: 8388 | S3: 9254 | T3: 9462 | U3: 9368 | V3: 10563 | W3: 10570 | X3: 7535 | Y3: 9751
A4: CMD-0003 | B4: 6159 | C4: 6040 | D4: 5590 | E4: 6371 | F4: 6442 | G4: 7255 | H4: 6800 | I4: 8211 | J4: 7705 | K4: 8146 | L4: 6048 | M4: 8916 | N4: 7892 | O4: 7047 | P4: 7801 | Q4: 6601 | R4: 9377 | S4: 9566 | T4: 9025 | U4: 9736 | V4: 11827 | W4: 11023 | X4: 7747 | Y4: 9867
A5: CMD-0004 | B5: 2646 | C5: 2564 | D5: 2454 | E5: 2753 | F5: 2467 | G5: 3218 | H5: 2964 | I5: 3384 | J5: 3341 | K5: 3428 | L5: 2473 | M5: 3877 | N5: 3772 | O5: 3178 | P5: 3270 | Q5: 2972 | R5: 3997 | S5: 4219 | T5: 4172 | U5: 4273 | V5: 4630 | W5: 5264 | X5: 3486 | Y5: 4727
A6: CMD-0005 | B6: 3159 | C6: 3575 | D6: 3274 | E6: 3768 | F6: 3827 | G6: 4645 | H6: 4018 | I6: 4638 | J6: 5100 | K6: 4071 | L6: 3311 | M6: 4662 | N6: 4705 | O6: 4174 | P6: 4431 | Q6: 3946 | R6: 5313 | S6: 6008 | T6: 5698 | U6: 5619 | V6: 6626 | W6: 6023 | X6: 4181 | Y6: 5685
A7: CMD-0006 | B7: 824 | C7: 684 | D7: 714 | E7: 130 | F7: 709 | G7: 708 | H7: 1104 | I7: 751 | J7: 471 | K7: 492 | L7: 598 | M7: 683 | N7: 559 | O7: 425 | P7: 972 | Q7: 550 | R7: 695 | S7: 530 | T7: 1064 | U7: 1037 | V7: 601 | W7: 752 | X7: 398 | Y7: 1178
A8: CMD-0007 | B8: 3781 | C8: 3598 | D8: 3430 | E8: 3180 | F8: 3846 | G8: 4807 | H8: 4591 | I8: 3985 | J8: 4821 | K8: 3684 | L8: 2791 | M8: 5261 | N8: 4182 | O8: 3720 | P8: 4384 | Q8: 4054 | R8: 3891 | S8: 4182 | T8: 5596 | U8: 5379 | V8: 5454 | W8: 7077 | X8: 3879 | Y8: 3079
A9: CMD-0008 | B9: 997 | C9: 1137 | D9: 976 | E9: 1188 | F9: 1476 | G9: 1593 | H9: 1317 | I9: 1776 | J9: 1934 | K9: 1445 | L9: 690 | M9: 1542 | N9: 974 | O9: 1648 | P9: 1605 | Q9: 1059 | R9: 903 | S9: 1174 | T9: 1281 | U9: 1937 | V9: 1116 | W9: 1766 | X9: 544 | Y9: 1830
A10: CMD-0009 | B10: 5488 | C10: 5545 | D10: 5309 | E10: 5836 | F10: 5879 | G10: 7616 | H10: 5783 | I10: 7055 | J10: 7571 | K10: 7495 | L10: 4894 | M10: 8790 | N10: 7353 | O10: 7236 | P10: 6512 | Q10: 6383 | R10: 8609 | S10: 8723 | T10: 8561 | U10: 9314 | V10: 10841 | W10: 10467 | X10: 7868 | Y10: 8918
A11: CMD-0010 | B11: 3300 | C11: 3197 | D11: 3361 | E11: 3509 | F11: 3573 | G11: 3952 | H11: 3809 | I11: 4526 | J11: 4946 | K11: 4013 | L11: 3014 | M11: 4531 | N11: 4525 | O11: 4065 | P11: 4213 | Q11: 3336 | R11: 4684 | S11: 5228 | T11: 4994 | U11: 4532 | V11: 6142 | W11: 5843 | X11: 3969 | Y11: 5882
A12: CMD-0011 | B12: 2330 | C12: 2492 | D12: 2593 | E12: 2636 | F12: 2641 | G12: 3274 | H12: 2930 | I12: 3578 | J12: 3733 | K12: 3482 | L12: 2226 | M12: 3916 | N12: 3839 | O12: 3285 | P12: 3197 | Q12: 2859 | R12: 4099 | S12: 4114 | T12: 3933 | U12: 3632 | V12: 4886 | W12: 4751 | X12: 3363 | Y12: 4658
A13: CMD-0012 | B13: 282 | C13: 323 | D13: 278 | E13: 334 | F13: 272 | G13: 302 | H13: 323 | I13: 344 | J13: 333 | K13: 335 | L13: 260 | M13: 310 | N13: 343 | O13: 282 | P13: 326 | Q13: 286 | R13: 353 | S13: 307 | T13: 379 | U13: 381 | V13: 461 | W13: 400 | X13: 274 | Y13: 384
... A117: CMD-0116 | B117: 2452 | C117: 2451 | D117: 2401 | E117: 2717 | F117: 1988 | G117: 2680 | H117: 2557 | I117: 2839 | J117: 2538 | K117: 2712 | L117: 2362 | M117: 2412 | N117: 2672 | O117: 2377 | P117: 2488 | Q117: 2502 | R117: 2849 | S117: 2339 | T117: 2906 | U117: 2999 | V117: 3672 | W117: 3007 | X117: 2301 | Y117: 2942

Sheet Stock_Snapshot
A1: sku | B1: on_hand_qty | C1: on_order_qty | D1: oldest_lot_expiry | E1: snapshot_date
A2: CMD-0001 | B2: 1932 | C2: 24121 | E2: 46295
A3: CMD-0002 | B3: 13678 | C3: 30024 | E3: 46295
A4: CMD-0003 | B4: 4175 | C4: 29319 | E4: 46295
A5: CMD-0004 | B5: 6222 | C5: 9711 | E5: 46295
A6: CMD-0005 | B6: 1198 | C6: 13897 | E6: 46295
A7: CMD-0006 | B7: 831 | C7: 3636 | E7: 46295
A8: CMD-0007 | B8: 4152 | C8: 17287 | E8: 46295
A9: CMD-0008 | B9: 2463 | C9: 5541 | E9: 46295
A10: CMD-0009 | B10: 11572 | C10: 29605 | E10: 46295
A11: CMD-0010 | B11: 6085 | C11: 17552 | E11: 46295
A12: CMD-0011 | B12: 3477 | C12: 9576 | E12: 46295
A13: CMD-0012 | B13: 281 | C13: 2458 | E13: 46295
... A41: CMD-0040 | B41: 348 | C41: 615 | E41: 46295
A42: CMD-0041 | B42: 318 | C42: 2247 | D42: 46356 | E42: 46295
A43: CMD-0042 | B43: 1227 | C43: 2135 | D43: 46356 | E43: 46295
A44: CMD-0043 | B44: 26788 | C44: 23892 | D44: 46537 | E44: 46295
A45: CMD-0044 | B45: 13454 | C45: 30220 | D45: 46386 | E45: 46295
A46: CMD-0045 | B46: 2428 | C46: 14859 | D46: 46660 | E46: 46295
A47: CMD-0046 | B47: 23409 | C47: 36774 | D47: 46629 | E47: 46295
A48: CMD-0047 | B48: 133127 | C48: 22682 | E48: 46295
A49: CMD-0048 | B49: 166418 | C49: 22533 | E49: 46295
A50: CMD-0049 | B50: 46663 | C50: 45034 | E50: 46295
A51: CMD-0050 | B51: 69862 | C51: 79109 | E51: 46295
A52: CMD-0051 | B52: 808736 | C52: 257065 | E52: 46295
A53: CMD-0052 | B53: 450917 | C53: 140136 | E53: 46295
A54: CMD-0053 | B54: 227999 | C54: 41967 | E54: 46295
A55: CMD-0054 | B55: 48656 | C55: 55485 | E55: 46295
A56: CMD-0055 | B56: 877262 | C56: 107993 | E56: 46295
A57: CMD-0056 | B57: 44286 | C57: 53006 | E57: 46295
A58: CMD-0057 | B58: 49650 | C58: 43844 | E58: 46295
A59: CMD-0058 | B59: 665799 | C59: 69455 | E59: 46295
... A108: CMD-0107 | B108: 2548 | C108: 1176 | E108: 46295
A109: CMD-0108 | B109: 86 | C109: 0 | D109: 46446 | E109: 46295
A110: CMD-0109 | B110: 8860 | C110: 0 | D110: 46842 | E110: 46295
A111: CMD-0110 | B111: 2362 | C111: 0 | D111: 46629 | E111: 46295
A112: CMD-0111 | B112: 34820 | C112: 0 | D112: 46842 | E112: 46295
A113: CMD-0112 | B113: 1702 | C113: 0 | D113: 47329 | E113: 46295
A114: CMD-0113 | B114: 1290 | C114: 0 | D114: 46964 | E114: 46295
A115: CMD-0114 | B115: 39030 | C115: 0 | D115: 46812 | E115: 46295
A116: CMD-0115 | B116: 1060 | C116: 0 | D116: 47360 | E116: 46295
A117: CMD-0116 | B117: 9691 | C117: 0 | D117: 46356 | E117: 46295

Sheet PO_Lines
A1: po_number | B1: sku | C1: supplier_id | D1: order_date | E1: promised_date | F1: received_date | G1: qty_ordered | H1: qty_received | I1: qty_rejected | J1: unit_price_eur | K1: status | L1: category | M1: std_cost_eur | N1: order_month | O1: po_value_eur | P1: price_variance_eur | Q1: received_flag | R1: lead_time_days | S1: on_time | T1: in_full | U1: otif | V1: days_late
A2: PO101228 | B2: CMD-0058 | C2: S04 | D2: 45566 | E2: 45601 | F2: 45612 | G2: 65077 | H2: 41810 | I2: 370 | J2: 0.1178 | K2: Received | L2: =INDEX(Items!$C$2:$C$117,MATCH(B2,Items!$A$2:$A$117,0)) | M2: =INDEX(Items!$E$2:$E$117,MATCH(B2,Items!$A$2:$A$117,0)) | N2: =TEXT(D2,"yyyy-mm") | O2: =G2*J2 | P2: =(J2-M2)*G2 | Q2: =IF(K2="Received",1,0) | R2: =IF(Q2=1,F2-D2,0) | S2: =IF(Q2=1,IF(F2<=E2,1,0),0) | T2: =IF(Q2=1,IF(H2>=G2,1,0),0) | U2: =S2*T2 | V2: =IF(Q2=1,MAX(0,F2-E2),0)
A3: PO101304 | B3: CMD-0064 | C3: S01 | D3: 45566 | E3: 45587 | F3: 45584 | G3: 120731 | H3: 120731 | I3: 226 | J3: 0.0318 | K3: Received | L3: =INDEX(Items!$C$2:$C$117,MATCH(B3,Items!$A$2:$A$117,0)) | M3: =INDEX(Items!$E$2:$E$117,MATCH(B3,Items!$A$2:$A$117,0)) | N3: =TEXT(D3,"yyyy-mm") | O3: =G3*J3 | P3: =(J3-M3)*G3 | Q3: =IF(K3="Received",1,0) | R3: =IF(Q3=1,F3-D3,0) | S3: =IF(Q3=1,IF(F3<=E3,1,0),0) | T3: =IF(Q3=1,IF(H3>=G3,1,0),0) | U3: =S3*T3 | V3: =IF(Q3=1,MAX(0,F3-E3),0)
A4: PO100264 | B4: CMD-0012 | C4: S03 | D4: 45566 | E4: 45699 | F4: 45696 | G4: 1966 | H4: 1966 | I4: 11 | J4: 2.59 | K4: Received | L4: =INDEX(Items!$C$2:$C$117,MATCH(B4,Items!$A$2:$A$117,0)) | M4: =INDEX(Items!$E$2:$E$117,MATCH(B4,Items!$A$2:$A$117,0)) | N4: =TEXT(D4,"yyyy-mm") | O4: =G4*J4 | P4: =(J4-M4)*G4 | Q4: =IF(K4="Received",1,0) | R4: =IF(Q4=1,F4-D4,0) | S4: =IF(Q4=1,IF(F4<=E4,1,0),0) | T4: =IF(Q4=1,IF(H4>=G4,1,0),0) | U4: =S4*T4 | V4: =IF(Q4=1,MAX(0,F4-E4),0)
A5: PO101144 | B5: CMD-0053 | C5: S04 | D5: 45566 | E5: 45601 | F5: 45599 | G5: 66680 | H5: 66680 | I5: 665 | J5: 0.0968 | K5: Received | L5: =INDEX(Items!$C$2:$C$117,MATCH(B5,Items!$A$2:$A$117,0)) | M5: =INDEX(Items!$E$2:$E$117,MATCH(B5,Items!$A$2:$A$117,0)) | N5: =TEXT(D5,"yyyy-mm") | O5: =G5*J5 | P5: =(J5-M5)*G5 | Q5: =IF(K5="Received",1,0) | R5: =IF(Q5=1,F5-D5,0) | S5: =IF(Q5=1,IF(F5<=E5,1,0),0) | T5: =IF(Q5=1,IF(H5>=G5,1,0),0) | U5: =S5*T5 | V5: =IF(Q5=1,MAX(0,F5-E5),0)
A6: PO101588 | B6: CMD-0086 | C6: S01 | D6: 45566 | E6: 45580 | F6: 45579 | G6: 3927 | H6: 3927 | I6: 5 | J6: 0.4679 | K6: Received | L6: =INDEX(Items!$C$2:$C$117,MATCH(B6,Items!$A$2:$A$117,0)) | M6: =INDEX(Items!$E$2:$E$117,MATCH(B6,Items!$A$2:$A$117,0)) | N6: =TEXT(D6,"yyyy-mm") | O6: =G6*J6 | P6: =(J6-M6)*G6 | Q6: =IF(K6="Received",1,0) | R6: =IF(Q6=1,F6-D6,0) | S6: =IF(Q6=1,IF(F6<=E6,1,0),0) | T6: =IF(Q6=1,IF(H6>=G6,1,0),0) | U6: =S6*T6 | V6: =IF(Q6=1,MAX(0,F6-E6),0)
A7: PO100982 | B7: CMD-0045 | C7: S05 | D7: 45566 | E7: 45671 | F7: 45670 | G7: 3234 | H7: 3234 | I7: 45 | J7: 8.99 | K7: Received | L7: =INDEX(Items!$C$2:$C$117,MATCH(B7,Items!$A$2:$A$117,0)) | M7: =INDEX(Items!$E$2:$E$117,MATCH(B7,Items!$A$2:$A$117,0)) | N7: =TEXT(D7,"yyyy-mm") | O7: =G7*J7 | P7: =(J7-M7)*G7 | Q7: =IF(K7="Received",1,0) | R7: =IF(Q7=1,F7-D7,0) | S7: =IF(Q7=1,IF(F7<=E7,1,0),0) | T7: =IF(Q7=1,IF(H7>=G7,1,0),0) | U7: =S7*T7 | V7: =IF(Q7=1,MAX(0,F7-E7),0)
A8: PO100934 | B8: CMD-0043 | C8: S05 | D8: 45566 | E8: 45671 | F8: 45671 | G8: 5146 | H8: 5146 | I8: 96 | J8: 3.69 | K8: Received | L8: =INDEX(Items!$C$2:$C$117,MATCH(B8,Items!$A$2:$A$117,0)) | M8: =INDEX(Items!$E$2:$E$117,MATCH(B8,Items!$A$2:$A$117,0)) | N8: =TEXT(D8,"yyyy-mm") | O8: =G8*J8 | P8: =(J8-M8)*G8 | Q8: =IF(K8="Received",1,0) | R8: =IF(Q8=1,F8-D8,0) | S8: =IF(Q8=1,IF(F8<=E8,1,0),0) | T8: =IF(Q8=1,IF(H8>=G8,1,0),0) | U8: =S8*T8 | V8: =IF(Q8=1,MAX(0,F8-E8),0)
A9: PO100818 | B9: CMD-0037 | C9: S07 | D9: 45566 | E9: 45608 | F9: 45616 | G9: 436 | H9: 436 | I9: 5 | J9: 53.62 | K9: Received | L9: =INDEX(Items!$C$2:$C$117,MATCH(B9,Items!$A$2:$A$117,0)) | M9: =INDEX(Items!$E$2:$E$117,MATCH(B9,Items!$A$2:$A$117,0)) | N9: =TEXT(D9,"yyyy-mm") | O9: =G9*J9 | P9: =(J9-M9)*G9 | Q9: =IF(K9="Received",1,0) | R9: =IF(Q9=1,F9-D9,0) | S9: =IF(Q9=1,IF(F9<=E9,1,0),0) | T9: =IF(Q9=1,IF(H9>=G9,1,0),0) | U9: =S9*T9 | V9: =IF(Q9=1,MAX(0,F9-E9),0)
A10: PO101384 | B10: CMD-0071 | C10: S01 | D10: 45566 | E10: 45587 | F10: 45585 | G10: 96584 | H10: 96584 | I10: 199 | J10: 0.0355 | K10: Received | L10: =INDEX(Items!$C$2:$C$117,MATCH(B10,Items!$A$2:$A$117,0)) | M10: =INDEX(Items!$E$2:$E$117,MATCH(B10,Items!$A$2:$A$117,0)) | N10: =TEXT(D10,"yyyy-mm") | O10: =G10*J10 | P10: =(J10-M10)*G10 | Q10: =IF(K10="Received",1,0) | R10: =IF(Q10=1,F10-D10,0) | S10: =IF(Q10=1,IF(F10<=E10,1,0),0) | T10: =IF(Q10=1,IF(H10>=G10,1,0),0) | U10: =S10*T10 | V10: =IF(Q10=1,MAX(0,F10-E10),0)
A11: PO100454 | B11: CMD-0021 | C11: S04 | D11: 45566 | E11: 45636 | F11: 45647 | G11: 1230 | H11: 1230 | I11: 16 | J11: 4.94 | K11: Received | L11: =INDEX(Items!$C$2:$C$117,MATCH(B11,Items!$A$2:$A$117,0)) | M11: =INDEX(Items!$E$2:$E$117,MATCH(B11,Items!$A$2:$A$117,0)) | N11: =TEXT(D11,"yyyy-mm") | O11: =G11*J11 | P11: =(J11-M11)*G11 | Q11: =IF(K11="Received",1,0) | R11: =IF(Q11=1,F11-D11,0) | S11: =IF(Q11=1,IF(F11<=E11,1,0),0) | T11: =IF(Q11=1,IF(H11>=G11,1,0),0) | U11: =S11*T11 | V11: =IF(Q11=1,MAX(0,F11-E11),0)
A12: PO100520 | B12: CMD-0024 | C12: S04 | D12: 45566 | E12: 45636 | F12: 45633 | G12: 4298 | H12: 2628 | I12: 30 | J12: 3.31 | K12: Received | L12: =INDEX(Items!$C$2:$C$117,MATCH(B12,Items!$A$2:$A$117,0)) | M12: =INDEX(Items!$E$2:$E$117,MATCH(B12,Items!$A$2:$A$117,0)) | N12: =TEXT(D12,"yyyy-mm") | O12: =G12*J12 | P12: =(J12-M12)*G12 | Q12: =IF(K12="Received",1,0) | R12: =IF(Q12=1,F12-D12,0) | S12: =IF(Q12=1,IF(F12<=E12,1,0),0) | T12: =IF(Q12=1,IF(H12>=G12,1,0),0) | U12: =S12*T12 | V12: =IF(Q12=1,MAX(0,F12-E12),0)
A13: PO100706 | B13: CMD-0032 | C13: S01 | D13: 45567 | E13: 45595 | F13: 45594 | G13: 1250 | H13: 1250 | I13: 0 | J13: 5.15 | K13: Received | L13: =INDEX(Items!$C$2:$C$117,MATCH(B13,Items!$A$2:$A$117,0)) | M13: =INDEX(Items!$E$2:$E$117,MATCH(B13,Items!$A$2:$A$117,0)) | N13: =TEXT(D13,"yyyy-mm") | O13: =G13*J13 | P13: =(J13-M13)*G13 | Q13: =IF(K13="Received",1,0) | R13: =IF(Q13=1,F13-D13,0) | S13: =IF(Q13=1,IF(F13<=E13,1,0),0) | T13: =IF(Q13=1,IF(H13>=G13,1,0),0) | U13: =S13*T13 | V13: =IF(Q13=1,MAX(0,F13-E13),0)
... A1662: PO100635 | B1662: CMD-0028 | C1662: S11 | D1662: 46164 | E1662: 46241 | F1662: 46240 | G1662: 3490 | H1662: 3490 | I1662: 8 | J1662: 16.3152 | K1662: Received | L1662: =INDEX(Items!$C$2:$C$117,MATCH(B1662,Items!$A$2:$A$117,0)) | M1662: =INDEX(Items!$E$2:$E$117,MATCH(B1662,Items!$A$2:$A$117,0)) | N1662: =TEXT(D1662,"yyyy-mm") | O1662: =G1662*J1662 | P1662: =(J1662-M1662)*G1662 | Q1662: =IF(K1662="Received",1,0) | R1662: =IF(Q1662=1,F1662-D1662,0) | S1662: =IF(Q1662=1,IF(F1662<=E1662,1,0),0) | T1662: =IF(Q1662=1,IF(H1662>=G1662,1,0),0) | U1662: =S1662*T1662 | V1662: =IF(Q1662=1,MAX(0,F1662-E1662),0)
A1663: PO100139 | B1663: CMD-0006 | C1663: S03 | D1663: 46164 | E1663: 46297 | G1663: 790 | H1663: 0 | I1663: 0 | J1663: 36.049 | K1663: Open | L1663: =INDEX(Items!$C$2:$C$117,MATCH(B1663,Items!$A$2:$A$117,0)) | M1663: =INDEX(Items!$E$2:$E$117,MATCH(B1663,Items!$A$2:$A$117,0)) | N1663: =TEXT(D1663,"yyyy-mm") | O1663: =G1663*J1663 | P1663: =(J1663-M1663)*G1663 | Q1663: =IF(K1663="Received",1,0) | R1663: =IF(Q1663=1,F1663-D1663,0) | S1663: =IF(Q1663=1,IF(F1663<=E1663,1,0),0) | T1663: =IF(Q1663=1,IF(H1663>=G1663,1,0),0) | U1663: =S1663*T1663 | V1663: =IF(Q1663=1,MAX(0,F1663-E1663),0)
A1664: PO100789 | B1664: CMD-0035 | C1664: S01 | D1664: 46164 | E1664: 46192 | F1664: 46191 | G1664: 646 | H1664: 646 | I1664: 2 | J1664: 9.6511 | K1664: Received | L1664: =INDEX(Items!$C$2:$C$117,MATCH(B1664,Items!$A$2:$A$117,0)) | M1664: =INDEX(Items!$E$2:$E$117,MATCH(B1664,Items!$A$2:$A$117,0)) | N1664: =TEXT(D1664,"yyyy-mm") | O1664: =G1664*J1664 | P1664: =(J1664-M1664)*G1664 | Q1664: =IF(K1664="Received",1,0) | R1664: =IF(Q1664=1,F1664-D1664,0) | S1664: =IF(Q1664=1,IF(F1664<=E1664,1,0),0) | T1664: =IF(Q1664=1,IF(H1664>=G1664,1,0),0) | U1664: =S1664*T1664 | V1664: =IF(Q1664=1,MAX(0,F1664-E1664),0)
A1665: PO101551 | B1665: CMD-0082 | C1665: S01 | D1665: 46164 | E1665: 46178 | F1665: 46175 | G1665: 6257 | H1665: 6257 | I1665: 12 | J1665: 2.3896 | K1665: Received | L1665: =INDEX(Items!$C$2:$C$117,MATCH(B1665,Items!$A$2:$A$117,0)) | M1665: =INDEX(Items!$E$2:$E$117,MATCH(B1665,Items!$A$2:$A$117,0)) | N1665: =TEXT(D1665,"yyyy-mm") | O1665: =G1665*J1665 | P1665: =(J1665-M1665)*G1665 | Q1665: =IF(K1665="Received",1,0) | R1665: =IF(Q1665=1,F1665-D1665,0) | S1665: =IF(Q1665=1,IF(F1665<=E1665,1,0),0) | T1665: =IF(Q1665=1,IF(H1665>=G1665,1,0),0) | U1665: =S1665*T1665 | V1665: =IF(Q1665=1,MAX(0,F1665-E1665),0)
A1666: PO100163 | B1666: CMD-0007 | C1666: S03 | D1666: 46164 | E1666: 46297 | F1666: 46294 | G1666: 3551 | H1666: 3551 | I1666: 25 | J1666: 22.8802 | K1666: Received | L1666: =INDEX(Items!$C$2:$C$117,MATCH(B1666,Items!$A$2:$A$117,0)) | M1666: =INDEX(Items!$E$2:$E$117,MATCH(B1666,Items!$A$2:$A$117,0)) | N1666: =TEXT(D1666,"yyyy-mm") | O1666: =G1666*J1666 | P1666: =(J1666-M1666)*G1666 | Q1666: =IF(K1666="Received",1,0) | R1666: =IF(Q1666=1,F1666-D1666,0) | S1666: =IF(Q1666=1,IF(F1666<=E1666,1,0),0) | T1666: =IF(Q1666=1,IF(H1666>=G1666,1,0),0) | U1666: =S1666*T1666 | V1666: =IF(Q1666=1,MAX(0,F1666-E1666),0)
A1667: PO100929 | B1667: CMD-0042 | C1667: S05 | D1667: 46164 | E1667: 46269 | F1667: 46281 | G1667: 685 | H1667: 685 | I1667: 11 | J1667: 9.1773 | K1667: Received | L1667: =INDEX(Items!$C$2:$C$117,MATCH(B1667,Items!$A$2:$A$117,0)) | M1667: =INDEX(Items!$E$2:$E$117,MATCH(B1667,Items!$A$2:$A$117,0)) | N1667: =TEXT(D1667,"yyyy-mm") | O1667: =G1667*J1667 | P1667: =(J1667-M1667)*G1667 | Q1667: =IF(K1667="Received",1,0) | R1667: =IF(Q1667=1,F1667-D1667,0) | S1667: =IF(Q1667=1,IF(F1667<=E1667,1,0),0) | T1667: =IF(Q1667=1,IF(H1667>=G1667,1,0),0) | U1667: =S1667*T1667 | V1667: =IF(Q1667=1,MAX(0,F1667-E1667),0)
A1668: PO100515 | B1668: CMD-0023 | C1668: S04 | D1668: 46164 | E1668: 46234 | F1668: 46233 | G1668: 3987 | H1668: 3987 | I1668: 39 | J1668: 9.064 | K1668: Received | L1668: =INDEX(Items!$C$2:$C$117,MATCH(B1668,Items!$A$2:$A$117,0)) | M1668: =INDEX(Items!$E$2:$E$117,MATCH(B1668,Items!$A$2:$A$117,0)) | N1668: =TEXT(D1668,"yyyy-mm") | O1668: =G1668*J1668 | P1668: =(J1668-M1668)*G1668 | Q1668: =IF(K1668="Received",1,0) | R1668: =IF(Q1668=1,F1668-D1668,0) | S1668: =IF(Q1668=1,IF(F1668<=E1668,1,0),0) | T1668: =IF(Q1668=1,IF(H1668>=G1668,1,0),0) | U1668: =S1668*T1668 | V1668: =IF(Q1668=1,MAX(0,F1668-E1668),0)
A1669: PO101887 | B1669: CMD-0102 | C1669: S09 | D1669: 46164 | E1669: 46185 | F1669: 46182 | G1669: 2416 | H1669: 2416 | I1669: 13 | J1669: 6.9113 | K1669: Received | L1669: =INDEX(Items!$C$2:$C$117,MATCH(B1669,Items!$A$2:$A$117,0)) | M1669: =INDEX(Items!$E$2:$E$117,MATCH(B1669,Items!$A$2:$A$117,0)) | N1669: =TEXT(D1669,"yyyy-mm") | O1669: =G1669*J1669 | P1669: =(J1669-M1669)*G1669 | Q1669: =IF(K1669="Received",1,0) | R1669: =IF(Q1669=1,F1669-D1669,0) | S1669: =IF(Q1669=1,IF(F1669<=E1669,1,0),0) | T1669: =IF(Q1669=1,IF(H1669>=G1669,1,0),0) | U1669: =S1669*T1669 | V1669: =IF(Q1669=1,MAX(0,F1669-E1669),0)
A1670: PO100067 | B1670: CMD-0003 | C1670: S11 | D1670: 46164 | E1670: 46283 | F1670: 46282 | G1670: 7529 | H1670: 7529 | I1670: 19 | J1670: 25.3582 | K1670: Received | L1670: =INDEX(Items!$C$2:$C$117,MATCH(B1670,Items!$A$2:$A$117,0)) | M1670: =INDEX(Items!$E$2:$E$117,MATCH(B1670,Items!$A$2:$A$117,0)) | N1670: =TEXT(D1670,"yyyy-mm") | O1670: =G1670*J1670 | P1670: =(J1670-M1670)*G1670 | Q1670: =IF(K1670="Received",1,0) | R1670: =IF(Q1670=1,F1670-D1670,0) | S1670: =IF(Q1670=1,IF(F1670<=E1670,1,0),0) | T1670: =IF(Q1670=1,IF(H1670>=G1670,1,0),0) | U1670: =S1670*T1670 | V1670: =IF(Q1670=1,MAX(0,F1670-E1670),0)
A1671: PO101001 | B1671: CMD-0045 | C1671: S05 | D1671: 46164 | E1671: 46269 | F1671: 46267 | G1671: 3429 | H1671: 3429 | I1671: 60 | J1671: 9.2597 | K1671: Received | L1671: =INDEX(Items!$C$2:$C$117,MATCH(B1671,Items!$A$2:$A$117,0)) | M1671: =INDEX(Items!$E$2:$E$117,MATCH(B1671,Items!$A$2:$A$117,0)) | N1671: =TEXT(D1671,"yyyy-mm") | O1671: =G1671*J1671 | P1671: =(J1671-M1671)*G1671 | Q1671: =IF(K1671="Received",1,0) | R1671: =IF(Q1671=1,F1671-D1671,0) | S1671: =IF(Q1671=1,IF(F1671<=E1671,1,0),0) | T1671: =IF(Q1671=1,IF(H1671>=G1671,1,0),0) | U1671: =S1671*T1671 | V1671: =IF(Q1671=1,MAX(0,F1671-E1671),0)
A1672: PO101757 | B1672: CMD-0095 | C1672: S08 | D1672: 46164 | E1672: 46241 | F1672: 46241 | G1672: 381 | H1672: 381 | I1672: 9 | J1672: 94.5849 | K1672: Received | L1672: =INDEX(Items!$C$2:$C$117,MATCH(B1672,Items!$A$2:$A$117,0)) | M1672: =INDEX(Items!$E$2:$E$117,MATCH(B1672,Items!$A$2:$A$117,0)) | N1672: =TEXT(D1672,"yyyy-mm") | O1672: =G1672*J1672 | P1672: =(J1672-M1672)*G1672 | Q1672: =IF(K1672="Received",1,0) | R1672: =IF(Q1672=1,F1672-D1672,0) | S1672: =IF(Q1672=1,IF(F1672<=E1672,1,0),0) | T1672: =IF(Q1672=1,IF(H1672>=G1672,1,0),0) | U1672: =S1672*T1672 | V1672: =IF(Q1672=1,MAX(0,F1672-E1672),0)
A1673: PO101295 | B1673: CMD-0062 | C1673: S01 | D1673: 46164 | E1673: 46185 | F1673: 46182 | G1673: 77767 | H1673: 77767 | I1673: 156 | J1673: 0.1173 | K1673: Received | L1673: =INDEX(Items!$C$2:$C$117,MATCH(B1673,Items!$A$2:$A$117,0)) | M1673: =INDEX(Items!$E$2:$E$117,MATCH(B1673,Items!$A$2:$A$117,0)) | N1673: =TEXT(D1673,"yyyy-mm") | O1673: =G1673*J1673 | P1673: =(J1673-M1673)*G1673 | Q1673: =IF(K1673="Received",1,0) | R1673: =IF(Q1673=1,F1673-D1673,0) | S1673: =IF(Q1673=1,IF(F1673<=E1673,1,0),0) | T1673: =IF(Q1673=1,IF(H1673>=G1673,1,0),0) | U1673: =S1673*T1673 | V1673: =IF(Q1673=1,MAX(0,F1673-E1673),0)
A1674: PO101637 | B1674: CMD-0090 | C1674: S01 | D1674: 46164 | E1674: 46178 | F1674: 46175 | G1674: 4350 | H1674: 4350 | I1674: 10 | J1674: 7.1997 | K1674: Received | L1674: =INDEX(Items!$C$2:$C$117,MATCH(B1674,Items!$A$2:$A$117,0)) | M1674: =INDEX(Items!$E$2:$E$117,MATCH(B1674,Items!$A$2:$A$117,0)) | N1674: =TEXT(D1674,"yyyy-mm") | O1674: =G1674*J1674 | P1674: =(J1674-M1674)*G1674 | Q1674: =IF(K1674="Received",1,0) | R1674: =IF(Q1674=1,F1674-D1674,0) | S1674: =IF(Q1674=1,IF(F1674<=E1674,1,0),0) | T1674: =IF(Q1674=1,IF(H1674>=G1674,1,0),0) | U1674: =S1674*T1674 | V1674: =IF(Q1674=1,MAX(0,F1674-E1674),0)
A1675: PO101263 | B1675: CMD-0059 | C1675: S01 | D1675: 46171 | E1675: 46192 | F1675: 46211 | G1675: 221664 | H1675: 221664 | I1675: 398 | J1675: 0.0289 | K1675: Received | L1675: =INDEX(Items!$C$2:$C$117,MATCH(B1675,Items!$A$2:$A$117,0)) | M1675: =INDEX(Items!$E$2:$E$117,MATCH(B1675,Items!$A$2:$A$117,0)) | N1675: =TEXT(D1675,"yyyy-mm") | O1675: =G1675*J1675 | P1675: =(J1675-M1675)*G1675 | Q1675: =IF(K1675="Received",1,0) | R1675: =IF(Q1675=1,F1675-D1675,0) | S1675: =IF(Q1675=1,IF(F1675<=E1675,1,0),0) | T1675: =IF(Q1675=1,IF(H1675>=G1675,1,0),0) | U1675: =S1675*T1675 | V1675: =IF(Q1675=1,MAX(0,F1675-E1675),0)
... A1683: PO100360 | B1683: CMD-0016 | C1683: S07 | D1683: 46187 | E1683: 46278 | F1683: 46275 | G1683: 6666 | H1683: 6666 | I1683: 54 | J1683: 31.8836 | K1683: Received | L1683: =INDEX(Items!$C$2:$C$117,MATCH(B1683,Items!$A$2:$A$117,0)) | M1683: =INDEX(Items!$E$2:$E$117,MATCH(B1683,Items!$A$2:$A$117,0)) | N1683: =TEXT(D1683,"yyyy-mm") | O1683: =G1683*J1683 | P1683: =(J1683-M1683)*G1683 | Q1683: =IF(K1683="Received",1,0) | R1683: =IF(Q1683=1,F1683-D1683,0) | S1683: =IF(Q1683=1,IF(F1683<=E1683,1,0),0) | T1683: =IF(Q1683=1,IF(H1683>=G1683,1,0),0) | U1683: =S1683*T1683 | V1683: =IF(Q1683=1,MAX(0,F1683-E1683),0)
A1684: PO100188 | B1684: CMD-0008 | C1684: S03 | D1684: 46187 | E1684: 46320 | G1684: 1288 | H1684: 0 | I1684: 0 | J1684: 27.9188 | K1684: Open | L1684: =INDEX(Items!$C$2:$C$117,MATCH(B1684,Items!$A$2:$A$117,0)) | M1684: =INDEX(Items!$E$2:$E$117,MATCH(B1684,Items!$A$2:$A$117,0)) | N1684: =TEXT(D1684,"yyyy-mm") | O1684: =G1684*J1684 | P1684: =(J1684-M1684)*G1684 | Q1684: =IF(K1684="Received",1,0) | R1684: =IF(Q1684=1,F1684-D1684,0) | S1684: =IF(Q1684=1,IF(F1684<=E1684,1,0),0) | T1684: =IF(Q1684=1,IF(H1684>=G1684,1,0),0) | U1684: =S1684*T1684 | V1684: =IF(Q1684=1,MAX(0,F1684-E1684),0)
A1685: PO100288 | B1685: CMD-0013 | C1685: S11 | D1685: 46187 | E1685: 46306 | G1685: 842 | H1685: 0 | I1685: 0 | J1685: 7.965 | K1685: Open | L1685: =INDEX(Items!$C$2:$C$117,MATCH(B1685,Items!$A$2:$A$117,0)) | M1685: =INDEX(Items!$E$2:$E$117,MATCH(B1685,Items!$A$2:$A$117,0)) | N1685: =TEXT(D1685,"yyyy-mm") | O1685: =G1685*J1685 | P1685: =(J1685-M1685)*G1685 | Q1685: =IF(K1685="Received",1,0) | R1685: =IF(Q1685=1,F1685-D1685,0) | S1685: =IF(Q1685=1,IF(F1685<=E1685,1,0),0) | T1685: =IF(Q1685=1,IF(H1685>=G1685,1,0),0) | U1685: =S1685*T1685 | V1685: =IF(Q1685=1,MAX(0,F1685-E1685),0)
A1686: PO101888 | B1686: CMD-0102 | C1686: S09 | D1686: 46187 | E1686: 46208 | F1686: 46206 | G1686: 2438 | H1686: 1706 | I1686: 4 | J1686: 6.9113 | K1686: Received | L1686: =INDEX(Items!$C$2:$C$117,MATCH(B1686,Items!$A$2:$A$117,0)) | M1686: =INDEX(Items!$E$2:$E$117,MATCH(B1686,Items!$A$2:$A$117,0)) | N1686: =TEXT(D1686,"yyyy-mm") | O1686: =G1686*J1686 | P1686: =(J1686-M1686)*G1686 | Q1686: =IF(K1686="Received",1,0) | R1686: =IF(Q1686=1,F1686-D1686,0) | S1686: =IF(Q1686=1,IF(F1686<=E1686,1,0),0) | T1686: =IF(Q1686=1,IF(H1686>=G1686,1,0),0) | U1686: =S1686*T1686 | V1686: =IF(Q1686=1,MAX(0,F1686-E1686),0)
A1687: PO101248 | B1687: CMD-0058 | C1687: S04 | D1687: 46187 | E1687: 46222 | F1687: 46222 | G1687: 57720 | H1687: 57720 | I1687: 570 | J1687: 0.1213 | K1687: Received | L1687: =INDEX(Items!$C$2:$C$117,MATCH(B1687,Items!$A$2:$A$117,0)) | M1687: =INDEX(Items!$E$2:$E$117,MATCH(B1687,Items!$A$2:$A$117,0)) | N1687: =TEXT(D1687,"yyyy-mm") | O1687: =G1687*J1687 | P1687: =(J1687-M1687)*G1687 | Q1687: =IF(K1687="Received",1,0) | R1687: =IF(Q1687=1,F1687-D1687,0) | S1687: =IF(Q1687=1,IF(F1687<=E1687,1,0),0) | T1687: =IF(Q1687=1,IF(H1687>=G1687,1,0),0) | U1687: =S1687*T1687 | V1687: =IF(Q1687=1,MAX(0,F1687-E1687),0)
A1688: PO100408 | B1688: CMD-0018 | C1688: S02 | D1688: 46187 | E1688: 46243 | F1688: 46250 | G1688: 6604 | H1688: 4073 | I1688: 16 | J1688: 39.0576 | K1688: Received | L1688: =INDEX(Items!$C$2:$C$117,MATCH(B1688,Items!$A$2:$A$117,0)) | M1688: =INDEX(Items!$E$2:$E$117,MATCH(B1688,Items!$A$2:$A$117,0)) | N1688: =TEXT(D1688,"yyyy-mm") | O1688: =G1688*J1688 | P1688: =(J1688-M1688)*G1688 | Q1688: =IF(K1688="Received",1,0) | R1688: =IF(Q1688=1,F1688-D1688,0) | S1688: =IF(Q1688=1,IF(F1688<=E1688,1,0),0) | T1688: =IF(Q1688=1,IF(H1688>=G1688,1,0),0) | U1688: =S1688*T1688 | V1688: =IF(Q1688=1,MAX(0,F1688-E1688),0)
A1689: PO101662 | B1689: CMD-0091 | C1689: S08 | D1689: 46187 | E1689: 46264 | F1689: 46264 | G1689: 1006 | H1689: 1006 | I1689: 11 | J1689: 24.514 | K1689: Received | L1689: =INDEX(Items!$C$2:$C$117,MATCH(B1689,Items!$A$2:$A$117,0)) | M1689: =INDEX(Items!$E$2:$E$117,MATCH(B1689,Items!$A$2:$A$117,0)) | N1689: =TEXT(D1689,"yyyy-mm") | O1689: =G1689*J1689 | P1689: =(J1689-M1689)*G1689 | Q1689: =IF(K1689="Received",1,0) | R1689: =IF(Q1689=1,F1689-D1689,0) | S1689: =IF(Q1689=1,IF(F1689<=E1689,1,0),0) | T1689: =IF(Q1689=1,IF(H1689>=G1689,1,0),0) | U1689: =S1689*T1689 | V1689: =IF(Q1689=1,MAX(0,F1689-E1689),0)
A1690: PO100766 | B1690: CMD-0034 | C1690: S04 | D1690: 46187 | E1690: 46229 | F1690: 46228 | G1690: 721 | H1690: 721 | I1690: 11 | J1690: 10.8665 | K1690: Received | L1690: =INDEX(Items!$C$2:$C$117,MATCH(B1690,Items!$A$2:$A$117,0)) | M1690: =INDEX(Items!$E$2:$E$117,MATCH(B1690,Items!$A$2:$A$117,0)) | N1690: =TEXT(D1690,"yyyy-mm") | O1690: =G1690*J1690 | P1690: =(J1690-M1690)*G1690 | Q1690: =IF(K1690="Received",1,0) | R1690: =IF(Q1690=1,F1690-D1690,0) | S1690: =IF(Q1690=1,IF(F1690<=E1690,1,0),0) | T1690: =IF(Q1690=1,IF(H1690>=G1690,1,0),0) | U1690: =S1690*T1690 | V1690: =IF(Q1690=1,MAX(0,F1690-E1690),0)
A1691: PO101202 | B1691: CMD-0055 | C1691: S04 | D1691: 46187 | E1691: 46222 | F1691: 46219 | G1691: 100649 | H1691: 100649 | I1691: 970 | J1691: 0.0966 | K1691: Received | L1691: =INDEX(Items!$C$2:$C$117,MATCH(B1691,Items!$A$2:$A$117,0)) | M1691: =INDEX(Items!$E$2:$E$117,MATCH(B1691,Items!$A$2:$A$117,0)) | N1691: =TEXT(D1691,"yyyy-mm") | O1691: =G1691*J1691 | P1691: =(J1691-M1691)*G1691 | Q1691: =IF(K1691="Received",1,0) | R1691: =IF(Q1691=1,F1691-D1691,0) | S1691: =IF(Q1691=1,IF(F1691<=E1691,1,0),0) | T1691: =IF(Q1691=1,IF(H1691>=G1691,1,0),0) | U1691: =S1691*T1691 | V1691: =IF(Q1691=1,MAX(0,F1691-E1691),0)
A1692: PO100838 | B1692: CMD-0037 | C1692: S07 | D1692: 46187 | E1692: 46229 | F1692: 46237 | G1692: 460 | H1692: 460 | I1692: 5 | J1692: 55.2286 | K1692: Received | L1692: =INDEX(Items!$C$2:$C$117,MATCH(B1692,Items!$A$2:$A$117,0)) | M1692: =INDEX(Items!$E$2:$E$117,MATCH(B1692,Items!$A$2:$A$117,0)) | N1692: =TEXT(D1692,"yyyy-mm") | O1692: =G1692*J1692 | P1692: =(J1692-M1692)*G1692 | Q1692: =IF(K1692="Received",1,0) | R1692: =IF(Q1692=1,F1692-D1692,0) | S1692: =IF(Q1692=1,IF(F1692<=E1692,1,0),0) | T1692: =IF(Q1692=1,IF(H1692>=G1692,1,0),0) | U1692: =S1692*T1692 | V1692: =IF(Q1692=1,MAX(0,F1692-E1692),0)
A1693: PO101328 | B1693: CMD-0065 | C1693: S10 | D1693: 46188 | E1693: 46216 | F1693: 46216 | G1693: 121157 | H1693: 121157 | I1693: 113 | J1693: 0.119 | K1693: Received | L1693: =INDEX(Items!$C$2:$C$117,MATCH(B1693,Items!$A$2:$A$117,0)) | M1693: =INDEX(Items!$E$2:$E$117,MATCH(B1693,Items!$A$2:$A$117,0)) | N1693: =TEXT(D1693,"yyyy-mm") | O1693: =G1693*J1693 | P1693: =(J1693-M1693)*G1693 | Q1693: =IF(K1693="Received",1,0) | R1693: =IF(Q1693=1,F1693-D1693,0) | S1693: =IF(Q1693=1,IF(F1693<=E1693,1,0),0) | T1693: =IF(Q1693=1,IF(H1693>=G1693,1,0),0) | U1693: =S1693*T1693 | V1693: =IF(Q1693=1,MAX(0,F1693-E1693),0)
A1694: PO101734 | B1694: CMD-0094 | C1694: S08 | D1694: 46188 | E1694: 46265 | F1694: 46267 | G1694: 399 | H1694: 399 | I1694: 7 | J1694: 76.3127 | K1694: Received | L1694: =INDEX(Items!$C$2:$C$117,MATCH(B1694,Items!$A$2:$A$117,0)) | M1694: =INDEX(Items!$E$2:$E$117,MATCH(B1694,Items!$A$2:$A$117,0)) | N1694: =TEXT(D1694,"yyyy-mm") | O1694: =G1694*J1694 | P1694: =(J1694-M1694)*G1694 | Q1694: =IF(K1694="Received",1,0) | R1694: =IF(Q1694=1,F1694-D1694,0) | S1694: =IF(Q1694=1,IF(F1694<=E1694,1,0),0) | T1694: =IF(Q1694=1,IF(H1694>=G1694,1,0),0) | U1694: =S1694*T1694 | V1694: =IF(Q1694=1,MAX(0,F1694-E1694),0)
A1695: PO100612 | B1695: CMD-0027 | C1695: S04 | D1695: 46188 | E1695: 46258 | F1695: 46258 | G1695: 7971 | H1695: 7971 | I1695: 83 | J1695: 9.1155 | K1695: Received | L1695: =INDEX(Items!$C$2:$C$117,MATCH(B1695,Items!$A$2:$A$117,0)) | M1695: =INDEX(Items!$E$2:$E$117,MATCH(B1695,Items!$A$2:$A$117,0)) | N1695: =TEXT(D1695,"yyyy-mm") | O1695: =G1695*J1695 | P1695: =(J1695-M1695)*G1695 | Q1695: =IF(K1695="Received",1,0) | R1695: =IF(Q1695=1,F1695-D1695,0) | S1695: =IF(Q1695=1,IF(F1695<=E1695,1,0),0) | T1695: =IF(Q1695=1,IF(H1695>=G1695,1,0),0) | U1695: =S1695*T1695 | V1695: =IF(Q1695=1,MAX(0,F1695-E1695),0)
A1696: PO101296 | B1696: CMD-0062 | C1696: S01 | D1696: 46188 | E1696: 46209 | F1696: 46206 | G1696: 83024 | H1696: 83024 | I1696: 179 | J1696: 0.1173 | K1696: Received | L1696: =INDEX(Items!$C$2:$C$117,MATCH(B1696,Items!$A$2:$A$117,0)) | M1696: =INDEX(Items!$E$2:$E$117,MATCH(B1696,Items!$A$2:$A$117,0)) | N1696: =TEXT(D1696,"yyyy-mm") | O1696: =G1696*J1696 | P1696: =(J1696-M1696)*G1696 | Q1696: =IF(K1696="Received",1,0) | R1696: =IF(Q1696=1,F1696-D1696,0) | S1696: =IF(Q1696=1,IF(F1696<=E1696,1,0),0) | T1696: =IF(Q1696=1,IF(H1696>=G1696,1,0),0) | U1696: =S1696*T1696 | V1696: =IF(Q1696=1,MAX(0,F1696-E1696),0)
A1697: PO100814 | B1697: CMD-0036 | C1697: S04 | D1697: 46188 | E1697: 46230 | F1697: 46229 | G1697: 511 | H1697: 511 | I1697: 7 | J1697: 12.7308 | K1697: Received | L1697: =INDEX(Items!$C$2:$C$117,MATCH(B1697,Items!$A$2:$A$117,0)) | M1697: =INDEX(Items!$E$2:$E$117,MATCH(B1697,Items!$A$2:$A$117,0)) | N1697: =TEXT(D1697,"yyyy-mm") | O1697: =G1697*J1697 | P1697: =(J1697-M1697)*G1697 | Q1697: =IF(K1697="Received",1,0) | R1697: =IF(Q1697=1,F1697-D1697,0) | S1697: =IF(Q1697=1,IF(F1697<=E1697,1,0),0) | T1697: =IF(Q1697=1,IF(H1697>=G1697,1,0),0) | U1697: =S1697*T1697 | V1697: =IF(Q1697=1,MAX(0,F1697-E1697),0)
A1698: PO100044 | B1698: CMD-0002 | C1698: S11 | D1698: 46188 | E1698: 46307 | G1698: 7793 | H1698: 0 | I1698: 0 | J1698: 8.083 | K1698: Open | L1698: =INDEX(Items!$C$2:$C$117,MATCH(B1698,Items!$A$2:$A$117,0)) | M1698: =INDEX(Items!$E$2:$E$117,MATCH(B1698,Items!$A$2:$A$117,0)) | N1698: =TEXT(D1698,"yyyy-mm") | O1698: =G1698*J1698 | P1698: =(J1698-M1698)*G1698 | Q1698: =IF(K1698="Received",1,0) | R1698: =IF(Q1698=1,F1698-D1698,0) | S1698: =IF(Q1698=1,IF(F1698<=E1698,1,0),0) | T1698: =IF(Q1698=1,IF(H1698>=G1698,1,0),0) | U1698: =S1698*T1698 | V1698: =IF(Q1698=1,MAX(0,F1698-E1698),0)
A1699: PO101072 | B1699: CMD-0048 | C1699: S10 | D1699: 46188 | E1699: 46216 | F1699: 46214 | G1699: 19650 | H1699: 19650 | I1699: 24 | J1699: 0.3328 | K1699: Received | L1699: =INDEX(Items!$C$2:$C$117,MATCH(B1699,Items!$A$2:$A$117,0)) | M1699: =INDEX(Items!$E$2:$E$117,MATCH(B1699,Items!$A$2:$A$117,0)) | N1699: =TEXT(D1699,"yyyy-mm") | O1699: =G1699*J1699 | P1699: =(J1699-M1699)*G1699 | Q1699: =IF(K1699="Received",1,0) | R1699: =IF(Q1699=1,F1699-D1699,0) | S1699: =IF(Q1699=1,IF(F1699<=E1699,1,0),0) | T1699: =IF(Q1699=1,IF(H1699>=G1699,1,0),0) | U1699: =S1699*T1699 | V1699: =IF(Q1699=1,MAX(0,F1699-E1699),0)
A1700: PO100636 | B1700: CMD-0028 | C1700: S11 | D1700: 46188 | E1700: 46265 | F1700: 46262 | G1700: 3227 | H1700: 3227 | I1700: 4 | J1700: 16.3152 | K1700: Received | L1700: =INDEX(Items!$C$2:$C$117,MATCH(B1700,Items!$A$2:$A$117,0)) | M1700: =INDEX(Items!$E$2:$E$117,MATCH(B1700,Items!$A$2:$A$117,0)) | N1700: =TEXT(D1700,"yyyy-mm") | O1700: =G1700*J1700 | P1700: =(J1700-M1700)*G1700 | Q1700: =IF(K1700="Received",1,0) | R1700: =IF(Q1700=1,F1700-D1700,0) | S1700: =IF(Q1700=1,IF(F1700<=E1700,1,0),0) | T1700: =IF(Q1700=1,IF(H1700>=G1700,1,0),0) | U1700: =S1700*T1700 | V1700: =IF(Q1700=1,MAX(0,F1700-E1700),0)
A1701: PO101758 | B1701: CMD-0095 | C1701: S08 | D1701: 46188 | E1701: 46265 | F1701: 46262 | G1701: 322 | H1701: 322 | I1701: 1 | J1701: 94.5849 | K1701: Received | L1701: =INDEX(Items!$C$2:$C$117,MATCH(B1701,Items!$A$2:$A$117,0)) | M1701: =INDEX(Items!$E$2:$E$117,MATCH(B1701,Items!$A$2:$A$117,0)) | N1701: =TEXT(D1701,"yyyy-mm") | O1701: =G1701*J1701 | P1701: =(J1701-M1701)*G1701 | Q1701: =IF(K1701="Received",1,0) | R1701: =IF(Q1701=1,F1701-D1701,0) | S1701: =IF(Q1701=1,IF(F1701<=E1701,1,0),0) | T1701: =IF(Q1701=1,IF(H1701>=G1701,1,0),0) | U1701: =S1701*T1701 | V1701: =IF(Q1701=1,MAX(0,F1701-E1701),0)
A1702: PO100684 | B1702: CMD-0030 | C1702: S11 | D1702: 46189 | E1702: 46266 | F1702: 46263 | G1702: 8141 | H1702: 8141 | I1702: 13 | J1702: 23.8857 | K1702: Received | L1702: =INDEX(Items!$C$2:$C$117,MATCH(B1702,Items!$A$2:$A$117,0)) | M1702: =INDEX(Items!$E$2:$E$117,MATCH(B1702,Items!$A$2:$A$117,0)) | N1702: =TEXT(D1702,"yyyy-mm") | O1702: =G1702*J1702 | P1702: =(J1702-M1702)*G1702 | Q1702: =IF(K1702="Received",1,0) | R1702: =IF(Q1702=1,F1702-D1702,0) | S1702: =IF(Q1702=1,IF(F1702<=E1702,1,0),0) | T1702: =IF(Q1702=1,IF(H1702>=G1702,1,0),0) | U1702: =S1702*T1702 | V1702: =IF(Q1702=1,MAX(0,F1702-E1702),0)
A1703: PO100020 | B1703: CMD-0001 | C1703: S07 | D1703: 46189 | E1703: 46280 | F1703: 46278 | G1703: 7104 | H1703: 7104 | I1703: 58 | J1703: 16.8268 | K1703: Received | L1703: =INDEX(Items!$C$2:$C$117,MATCH(B1703,Items!$A$2:$A$117,0)) | M1703: =INDEX(Items!$E$2:$E$117,MATCH(B1703,Items!$A$2:$A$117,0)) | N1703: =TEXT(D1703,"yyyy-mm") | O1703: =G1703*J1703 | P1703: =(J1703-M1703)*G1703 | Q1703: =IF(K1703="Received",1,0) | R1703: =IF(Q1703=1,F1703-D1703,0) | S1703: =IF(Q1703=1,IF(F1703<=E1703,1,0),0) | T1703: =IF(Q1703=1,IF(H1703>=G1703,1,0),0) | U1703: =S1703*T1703 | V1703: =IF(Q1703=1,MAX(0,F1703-E1703),0)
A1704: PO101524 | B1704: CMD-0080 | C1704: S06 | D1704: 46189 | E1704: 46210 | F1704: 46207 | G1704: 4900 | H1704: 4900 | I1704: 27 | J1704: 5.6959 | K1704: Received | L1704: =INDEX(Items!$C$2:$C$117,MATCH(B1704,Items!$A$2:$A$117,0)) | M1704: =INDEX(Items!$E$2:$E$117,MATCH(B1704,Items!$A$2:$A$117,0)) | N1704: =TEXT(D1704,"yyyy-mm") | O1704: =G1704*J1704 | P1704: =(J1704-M1704)*G1704 | Q1704: =IF(K1704="Received",1,0) | R1704: =IF(Q1704=1,F1704-D1704,0) | S1704: =IF(Q1704=1,IF(F1704<=E1704,1,0),0) | T1704: =IF(Q1704=1,IF(H1704>=G1704,1,0),0) | U1704: =S1704*T1704 | V1704: =IF(Q1704=1,MAX(0,F1704-E1704),0)
A1705: PO101686 | B1705: CMD-0092 | C1705: S08 | D1705: 46189 | E1705: 46266 | F1705: 46265 | G1705: 323 | H1705: 323 | I1705: 2 | J1705: 30.3541 | K1705: Received | L1705: =INDEX(Items!$C$2:$C$117,MATCH(B1705,Items!$A$2:$A$117,0)) | M1705: =INDEX(Items!$E$2:$E$117,MATCH(B1705,Items!$A$2:$A$117,0)) | N1705: =TEXT(D1705,"yyyy-mm") | O1705: =G1705*J1705 | P1705: =(J1705-M1705)*G1705 | Q1705: =IF(K1705="Received",1,0) | R1705: =IF(Q1705=1,F1705-D1705,0) | S1705: =IF(Q1705=1,IF(F1705<=E1705,1,0),0) | T1705: =IF(Q1705=1,IF(H1705>=G1705,1,0),0) | U1705: =S1705*T1705 | V1705: =IF(Q1705=1,MAX(0,F1705-E1705),0)
A1706: PO101178 | B1706: CMD-0054 | C1706: S10 | D1706: 46189 | E1706: 46217 | F1706: 46216 | G1706: 57291 | H1706: 57291 | I1706: 67 | J1706: 0.1738 | K1706: Received | L1706: =INDEX(Items!$C$2:$C$117,MATCH(B1706,Items!$A$2:$A$117,0)) | M1706: =INDEX(Items!$E$2:$E$117,MATCH(B1706,Items!$A$2:$A$117,0)) | N1706: =TEXT(D1706,"yyyy-mm") | O1706: =G1706*J1706 | P1706: =(J1706-M1706)*G1706 | Q1706: =IF(K1706="Received",1,0) | R1706: =IF(Q1706=1,F1706-D1706,0) | S1706: =IF(Q1706=1,IF(F1706<=E1706,1,0),0) | T1706: =IF(Q1706=1,IF(H1706>=G1706,1,0),0) | U1706: =S1706*T1706 | V1706: =IF(Q1706=1,MAX(0,F1706-E1706),0)
A1707: PO100660 | B1707: CMD-0029 | C1707: S11 | D1707: 46190 | E1707: 46267 | F1707: 46265 | G1707: 3645 | H1707: 3645 | I1707: 6 | J1707: 7.0761 | K1707: Received | L1707: =INDEX(Items!$C$2:$C$117,MATCH(B1707,Items!$A$2:$A$117,0)) | M1707: =INDEX(Items!$E$2:$E$117,MATCH(B1707,Items!$A$2:$A$117,0)) | N1707: =TEXT(D1707,"yyyy-mm") | O1707: =G1707*J1707 | P1707: =(J1707-M1707)*G1707 | Q1707: =IF(K1707="Received",1,0) | R1707: =IF(Q1707=1,F1707-D1707,0) | S1707: =IF(Q1707=1,IF(F1707<=E1707,1,0),0) | T1707: =IF(Q1707=1,IF(H1707>=G1707,1,0),0) | U1707: =S1707*T1707 | V1707: =IF(Q1707=1,MAX(0,F1707-E1707),0)
A1708: PO101905 | B1708: CMD-0103 | C1708: S09 | D1708: 46190 | E1708: 46211 | F1708: 46211 | G1708: 1298 | H1708: 1298 | I1708: 7 | J1708: 4.3054 | K1708: Received | L1708: =INDEX(Items!$C$2:$C$117,MATCH(B1708,Items!$A$2:$A$117,0)) | M1708: =INDEX(Items!$E$2:$E$117,MATCH(B1708,Items!$A$2:$A$117,0)) | N1708: =TEXT(D1708,"yyyy-mm") | O1708: =G1708*J1708 | P1708: =(J1708-M1708)*G1708 | Q1708: =IF(K1708="Received",1,0) | R1708: =IF(Q1708=1,F1708-D1708,0) | S1708: =IF(Q1708=1,IF(F1708<=E1708,1,0),0) | T1708: =IF(Q1708=1,IF(H1708>=G1708,1,0),0) | U1708: =S1708*T1708 | V1708: =IF(Q1708=1,MAX(0,F1708-E1708),0)
A1709: PO101476 | B1709: CMD-0078 | C1709: S06 | D1709: 46190 | E1709: 46211 | F1709: 46210 | G1709: 5047 | H1709: 5047 | I1709: 28 | J1709: 2.678 | K1709: Received | L1709: =INDEX(Items!$C$2:$C$117,MATCH(B1709,Items!$A$2:$A$117,0)) | M1709: =INDEX(Items!$E$2:$E$117,MATCH(B1709,Items!$A$2:$A$117,0)) | N1709: =TEXT(D1709,"yyyy-mm") | O1709: =G1709*J1709 | P1709: =(J1709-M1709)*G1709 | Q1709: =IF(K1709="Received",1,0) | R1709: =IF(Q1709=1,F1709-D1709,0) | S1709: =IF(Q1709=1,IF(F1709<=E1709,1,0),0) | T1709: =IF(Q1709=1,IF(H1709>=G1709,1,0),0) | U1709: =S1709*T1709 | V1709: =IF(Q1709=1,MAX(0,F1709-E1709),0)
A1710: PO100790 | B1710: CMD-0035 | C1710: S01 | D1710: 46190 | E1710: 46218 | F1710: 46215 | G1710: 609 | H1710: 609 | I1710: 0 | J1710: 9.6511 | K1710: Received | L1710: =INDEX(Items!$C$2:$C$117,MATCH(B1710,Items!$A$2:$A$117,0)) | M1710: =INDEX(Items!$E$2:$E$117,MATCH(B1710,Items!$A$2:$A$117,0)) | N1710: =TEXT(D1710,"yyyy-mm") | O1710: =G1710*J1710 | P1710: =(J1710-M1710)*G1710 | Q1710: =IF(K1710="Received",1,0) | R1710: =IF(Q1710=1,F1710-D1710,0) | S1710: =IF(Q1710=1,IF(F1710<=E1710,1,0),0) | T1710: =IF(Q1710=1,IF(H1710>=G1710,1,0),0) | U1710: =S1710*T1710 | V1710: =IF(Q1710=1,MAX(0,F1710-E1710),0)
... A1716: PO100516 | B1716: CMD-0023 | C1716: S04 | D1716: 46191 | E1716: 46261 | F1716: 46258 | G1716: 5086 | H1716: 5086 | I1716: 40 | J1716: 9.064 | K1716: Received | L1716: =INDEX(Items!$C$2:$C$117,MATCH(B1716,Items!$A$2:$A$117,0)) | M1716: =INDEX(Items!$E$2:$E$117,MATCH(B1716,Items!$A$2:$A$117,0)) | N1716: =TEXT(D1716,"yyyy-mm") | O1716: =G1716*J1716 | P1716: =(J1716-M1716)*G1716 | Q1716: =IF(K1716="Received",1,0) | R1716: =IF(Q1716=1,F1716-D1716,0) | S1716: =IF(Q1716=1,IF(F1716<=E1716,1,0),0) | T1716: =IF(Q1716=1,IF(H1716>=G1716,1,0),0) | U1716: =S1716*T1716 | V1716: =IF(Q1716=1,MAX(0,F1716-E1716),0)
A1717: PO100140 | B1717: CMD-0006 | C1717: S03 | D1717: 46191 | E1717: 46324 | G1717: 745 | H1717: 0 | I1717: 0 | J1717: 36.049 | K1717: Open | L1717: =INDEX(Items!$C$2:$C$117,MATCH(B1717,Items!$A$2:$A$117,0)) | M1717: =INDEX(Items!$E$2:$E$117,MATCH(B1717,Items!$A$2:$A$117,0)) | N1717: =TEXT(D1717,"yyyy-mm") | O1717: =G1717*J1717 | P1717: =(J1717-M1717)*G1717 | Q1717: =IF(K1717="Received",1,0) | R1717: =IF(Q1717=1,F1717-D1717,0) | S1717: =IF(Q1717=1,IF(F1717<=E1717,1,0),0) | T1717: =IF(Q1717=1,IF(H1717>=G1717,1,0),0) | U1717: =S1717*T1717 | V1717: =IF(Q1717=1,MAX(0,F1717-E1717),0)
A1718: PO101584 | B1718: CMD-0085 | C1718: S06 | D1718: 46191 | E1718: 46212 | F1718: 46209 | G1718: 899 | H1718: 899 | I1718: 6 | J1718: 10.8768 | K1718: Received | L1718: =INDEX(Items!$C$2:$C$117,MATCH(B1718,Items!$A$2:$A$117,0)) | M1718: =INDEX(Items!$E$2:$E$117,MATCH(B1718,Items!$A$2:$A$117,0)) | N1718: =TEXT(D1718,"yyyy-mm") | O1718: =G1718*J1718 | P1718: =(J1718-M1718)*G1718 | Q1718: =IF(K1718="Received",1,0) | R1718: =IF(Q1718=1,F1718-D1718,0) | S1718: =IF(Q1718=1,IF(F1718<=E1718,1,0),0) | T1718: =IF(Q1718=1,IF(H1718>=G1718,1,0),0) | U1718: =S1718*T1718 | V1718: =IF(Q1718=1,MAX(0,F1718-E1718),0)
A1719: PO101980 | B1719: CMD-0109 | C1719: S12 | D1719: 46191 | E1719: 46198 | F1719: 46203 | G1719: 6781 | H1719: 6781 | I1719: 6 | J1719: 1.751 | K1719: Received | L1719: =INDEX(Items!$C$2:$C$117,MATCH(B1719,Items!$A$2:$A$117,0)) | M1719: =INDEX(Items!$E$2:$E$117,MATCH(B1719,Items!$A$2:$A$117,0)) | N1719: =TEXT(D1719,"yyyy-mm") | O1719: =G1719*J1719 | P1719: =(J1719-M1719)*G1719 | Q1719: =IF(K1719="Received",1,0) | R1719: =IF(Q1719=1,F1719-D1719,0) | S1719: =IF(Q1719=1,IF(F1719<=E1719,1,0),0) | T1719: =IF(Q1719=1,IF(H1719>=G1719,1,0),0) | U1719: =S1719*T1719 | V1719: =IF(Q1719=1,MAX(0,F1719-E1719),0)
A1720: PO100384 | B1720: CMD-0017 | C1720: S11 | D1720: 46191 | E1720: 46268 | F1720: 46267 | G1720: 6071 | H1720: 6071 | I1720: 8 | J1720: 13.0707 | K1720: Received | L1720: =INDEX(Items!$C$2:$C$117,MATCH(B1720,Items!$A$2:$A$117,0)) | M1720: =INDEX(Items!$E$2:$E$117,MATCH(B1720,Items!$A$2:$A$117,0)) | N1720: =TEXT(D1720,"yyyy-mm") | O1720: =G1720*J1720 | P1720: =(J1720-M1720)*G1720 | Q1720: =IF(K1720="Received",1,0) | R1720: =IF(Q1720=1,F1720-D1720,0) | S1720: =IF(Q1720=1,IF(F1720<=E1720,1,0),0) | T1720: =IF(Q1720=1,IF(H1720>=G1720,1,0),0) | U1720: =S1720*T1720 | V1720: =IF(Q1720=1,MAX(0,F1720-E1720),0)
A1721: PO100742 | B1721: CMD-0033 | C1721: S07 | D1721: 46191 | E1721: 46233 | F1721: 46231 | G1721: 4444 | H1721: 4444 | I1721: 36 | J1721: 60.1108 | K1721: Received | L1721: =INDEX(Items!$C$2:$C$117,MATCH(B1721,Items!$A$2:$A$117,0)) | M1721: =INDEX(Items!$E$2:$E$117,MATCH(B1721,Items!$A$2:$A$117,0)) | N1721: =TEXT(D1721,"yyyy-mm") | O1721: =G1721*J1721 | P1721: =(J1721-M1721)*G1721 | Q1721: =IF(K1721="Received",1,0) | R1721: =IF(Q1721=1,F1721-D1721,0) | S1721: =IF(Q1721=1,IF(F1721<=E1721,1,0),0) | T1721: =IF(Q1721=1,IF(H1721>=G1721,1,0),0) | U1721: =S1721*T1721 | V1721: =IF(Q1721=1,MAX(0,F1721-E1721),0)
A1722: PO100212 | B1722: CMD-0009 | C1722: S11 | D1722: 46191 | E1722: 46310 | G1722: 7168 | H1722: 0 | I1722: 0 | J1722: 7.4222 | K1722: Open | L1722: =INDEX(Items!$C$2:$C$117,MATCH(B1722,Items!$A$2:$A$117,0)) | M1722: =INDEX(Items!$E$2:$E$117,MATCH(B1722,Items!$A$2:$A$117,0)) | N1722: =TEXT(D1722,"yyyy-mm") | O1722: =G1722*J1722 | P1722: =(J1722-M1722)*G1722 | Q1722: =IF(K1722="Received",1,0) | R1722: =IF(Q1722=1,F1722-D1722,0) | S1722: =IF(Q1722=1,IF(F1722<=E1722,1,0),0) | T1722: =IF(Q1722=1,IF(H1722>=G1722,1,0),0) | U1722: =S1722*T1722 | V1722: =IF(Q1722=1,MAX(0,F1722-E1722),0)
A1723: PO101638 | B1723: CMD-0090 | C1723: S01 | D1723: 46191 | E1723: 46205 | F1723: 46203 | G1723: 4010 | H1723: 4010 | I1723: 11 | J1723: 7.1997 | K1723: Received | L1723: =INDEX(Items!$C$2:$C$117,MATCH(B1723,Items!$A$2:$A$117,0)) | M1723: =INDEX(Items!$E$2:$E$117,MATCH(B1723,Items!$A$2:$A$117,0)) | N1723: =TEXT(D1723,"yyyy-mm") | O1723: =G1723*J1723 | P1723: =(J1723-M1723)*G1723 | Q1723: =IF(K1723="Received",1,0) | R1723: =IF(Q1723=1,F1723-D1723,0) | S1723: =IF(Q1723=1,IF(F1723<=E1723,1,0),0) | T1723: =IF(Q1723=1,IF(H1723>=G1723,1,0),0) | U1723: =S1723*T1723 | V1723: =IF(Q1723=1,MAX(0,F1723-E1723),0)
A1724: PO100886 | B1724: CMD-0039 | C1724: S07 | D1724: 46192 | E1724: 46234 | F1724: 46232 | G1724: 411 | H1724: 411 | I1724: 2 | J1724: 53.5497 | K1724: Received | L1724: =INDEX(Items!$C$2:$C$117,MATCH(B1724,Items!$A$2:$A$117,0)) | M1724: =INDEX(Items!$E$2:$E$117,MATCH(B1724,Items!$A$2:$A$117,0)) | N1724: =TEXT(D1724,"yyyy-mm") | O1724: =G1724*J1724 | P1724: =(J1724-M1724)*G1724 | Q1724: =IF(K1724="Received",1,0) | R1724: =IF(Q1724=1,F1724-D1724,0) | S1724: =IF(Q1724=1,IF(F1724<=E1724,1,0),0) | T1724: =IF(Q1724=1,IF(H1724>=G1724,1,0),0) | U1724: =S1724*T1724 | V1724: =IF(Q1724=1,MAX(0,F1724-E1724),0)
A1725: PO100954 | B1725: CMD-0043 | C1725: S05 | D1725: 46192 | E1725: 46297 | G1725: 6259 | H1725: 0 | I1725: 0 | J1725: 3.8007 | K1725: Open | L1725: =INDEX(Items!$C$2:$C$117,MATCH(B1725,Items!$A$2:$A$117,0)) | M1725: =INDEX(Items!$E$2:$E$117,MATCH(B1725,Items!$A$2:$A$117,0)) | N1725: =TEXT(D1725,"yyyy-mm") | O1725: =G1725*J1725 | P1725: =(J1725-M1725)*G1725 | Q1725: =IF(K1725="Received",1,0) | R1725: =IF(Q1725=1,F1725-D1725,0) | S1725: =IF(Q1725=1,IF(F1725<=E1725,1,0),0) | T1725: =IF(Q1725=1,IF(H1725>=G1725,1,0),0) | U1725: =S1725*T1725 | V1725: =IF(Q1725=1,MAX(0,F1725-E1725),0)
A1726: PO101002 | B1726: CMD-0045 | C1726: S05 | D1726: 46192 | E1726: 46297 | G1726: 3821 | H1726: 0 | I1726: 0 | J1726: 9.2597 | K1726: Open | L1726: =INDEX(Items!$C$2:$C$117,MATCH(B1726,Items!$A$2:$A$117,0)) | M1726: =INDEX(Items!$E$2:$E$117,MATCH(B1726,Items!$A$2:$A$117,0)) | N1726: =TEXT(D1726,"yyyy-mm") | O1726: =G1726*J1726 | P1726: =(J1726-M1726)*G1726 | Q1726: =IF(K1726="Received",1,0) | R1726: =IF(Q1726=1,F1726-D1726,0) | S1726: =IF(Q1726=1,IF(F1726<=E1726,1,0),0) | T1726: =IF(Q1726=1,IF(H1726>=G1726,1,0),0) | U1726: =S1726*T1726 | V1726: =IF(Q1726=1,MAX(0,F1726-E1726),0)
A1727: PO101840 | B1727: CMD-0100 | C1727: S09 | D1727: 46192 | E1727: 46213 | F1727: 46233 | G1727: 6896 | H1727: 6896 | I1727: 14 | J1727: 5.0882 | K1727: Received | L1727: =INDEX(Items!$C$2:$C$117,MATCH(B1727,Items!$A$2:$A$117,0)) | M1727: =INDEX(Items!$E$2:$E$117,MATCH(B1727,Items!$A$2:$A$117,0)) | N1727: =TEXT(D1727,"yyyy-mm") | O1727: =G1727*J1727 | P1727: =(J1727-M1727)*G1727 | Q1727: =IF(K1727="Received",1,0) | R1727: =IF(Q1727=1,F1727-D1727,0) | S1727: =IF(Q1727=1,IF(F1727<=E1727,1,0),0) | T1727: =IF(Q1727=1,IF(H1727>=G1727,1,0),0) | U1727: =S1727*T1727 | V1727: =IF(Q1727=1,MAX(0,F1727-E1727),0)
A1728: PO100236 | B1728: CMD-0010 | C1728: S03 | D1728: 46192 | E1728: 46325 | G1728: 4964 | H1728: 0 | I1728: 0 | J1728: 5.4634 | K1728: Open | L1728: =INDEX(Items!$C$2:$C$117,MATCH(B1728,Items!$A$2:$A$117,0)) | M1728: =INDEX(Items!$E$2:$E$117,MATCH(B1728,Items!$A$2:$A$117,0)) | N1728: =TEXT(D1728,"yyyy-mm") | O1728: =G1728*J1728 | P1728: =(J1728-M1728)*G1728 | Q1728: =IF(K1728="Received",1,0) | R1728: =IF(Q1728=1,F1728-D1728,0) | S1728: =IF(Q1728=1,IF(F1728<=E1728,1,0),0) | T1728: =IF(Q1728=1,IF(H1728>=G1728,1,0),0) | U1728: =S1728*T1728 | V1728: =IF(Q1728=1,MAX(0,F1728-E1728),0)
A1729: PO100336 | B1729: CMD-0015 | C1729: S03 | D1729: 46192 | E1729: 46325 | G1729: 4102 | H1729: 0 | I1729: 0 | J1729: 6.6788 | K1729: Open | L1729: =INDEX(Items!$C$2:$C$117,MATCH(B1729,Items!$A$2:$A$117,0)) | M1729: =INDEX(Items!$E$2:$E$117,MATCH(B1729,Items!$A$2:$A$117,0)) | N1729: =TEXT(D1729,"yyyy-mm") | O1729: =G1729*J1729 | P1729: =(J1729-M1729)*G1729 | Q1729: =IF(K1729="Received",1,0) | R1729: =IF(Q1729=1,F1729-D1729,0) | S1729: =IF(Q1729=1,IF(F1729<=E1729,1,0),0) | T1729: =IF(Q1729=1,IF(H1729>=G1729,1,0),0) | U1729: =S1729*T1729 | V1729: =IF(Q1729=1,MAX(0,F1729-E1729),0)
A1730: PO100719 | B1730: CMD-0032 | C1730: S01 | D1730: 46192 | E1730: 46220 | F1730: 46217 | G1730: 1228 | H1730: 1228 | I1730: 2 | J1730: 5.3045 | K1730: Received | L1730: =INDEX(Items!$C$2:$C$117,MATCH(B1730,Items!$A$2:$A$117,0)) | M1730: =INDEX(Items!$E$2:$E$117,MATCH(B1730,Items!$A$2:$A$117,0)) | N1730: =TEXT(D1730,"yyyy-mm") | O1730: =G1730*J1730 | P1730: =(J1730-M1730)*G1730 | Q1730: =IF(K1730="Received",1,0) | R1730: =IF(Q1730=1,F1730-D1730,0) | S1730: =IF(Q1730=1,IF(F1730<=E1730,1,0),0) | T1730: =IF(Q1730=1,IF(H1730>=G1730,1,0),0) | U1730: =S1730*T1730 | V1730: =IF(Q1730=1,MAX(0,F1730-E1730),0)
A1731: PO100164 | B1731: CMD-0007 | C1731: S03 | D1731: 46192 | E1731: 46325 | G1731: 4193 | H1731: 0 | I1731: 0 | J1731: 22.8802 | K1731: Open | L1731: =INDEX(Items!$C$2:$C$117,MATCH(B1731,Items!$A$2:$A$117,0)) | M1731: =INDEX(Items!$E$2:$E$117,MATCH(B1731,Items!$A$2:$A$117,0)) | N1731: =TEXT(D1731,"yyyy-mm") | O1731: =G1731*J1731 | P1731: =(J1731-M1731)*G1731 | Q1731: =IF(K1731="Received",1,0) | R1731: =IF(Q1731=1,F1731-D1731,0) | S1731: =IF(Q1731=1,IF(F1731<=E1731,1,0),0) | T1731: =IF(Q1731=1,IF(H1731>=G1731,1,0),0) | U1731: =S1731*T1731 | V1731: =IF(Q1731=1,MAX(0,F1731-E1731),0)
A1732: PO100540 | B1732: CMD-0024 | C1732: S04 | D1732: 46193 | E1732: 46263 | F1732: 46263 | G1732: 4444 | H1732: 4444 | I1732: 40 | J1732: 3.4093 | K1732: Received | L1732: =INDEX(Items!$C$2:$C$117,MATCH(B1732,Items!$A$2:$A$117,0)) | M1732: =INDEX(Items!$E$2:$E$117,MATCH(B1732,Items!$A$2:$A$117,0)) | N1732: =TEXT(D1732,"yyyy-mm") | O1732: =G1732*J1732 | P1732: =(J1732-M1732)*G1732 | Q1732: =IF(K1732="Received",1,0) | R1732: =IF(Q1732=1,F1732-D1732,0) | S1732: =IF(Q1732=1,IF(F1732<=E1732,1,0),0) | T1732: =IF(Q1732=1,IF(H1732>=G1732,1,0),0) | U1732: =S1732*T1732 | V1732: =IF(Q1732=1,MAX(0,F1732-E1732),0)
A1733: PO100068 | B1733: CMD-0003 | C1733: S11 | D1733: 46193 | E1733: 46312 | G1733: 7210 | H1733: 0 | I1733: 0 | J1733: 25.3582 | K1733: Open | L1733: =INDEX(Items!$C$2:$C$117,MATCH(B1733,Items!$A$2:$A$117,0)) | M1733: =INDEX(Items!$E$2:$E$117,MATCH(B1733,Items!$A$2:$A$117,0)) | N1733: =TEXT(D1733,"yyyy-mm") | O1733: =G1733*J1733 | P1733: =(J1733-M1733)*G1733 | Q1733: =IF(K1733="Received",1,0) | R1733: =IF(Q1733=1,F1733-D1733,0) | S1733: =IF(Q1733=1,IF(F1733<=E1733,1,0),0) | T1733: =IF(Q1733=1,IF(H1733>=G1733,1,0),0) | U1733: =S1733*T1733 | V1733: =IF(Q1733=1,MAX(0,F1733-E1733),0)
A1734: PO100588 | B1734: CMD-0026 | C1734: S04 | D1734: 46193 | E1734: 46263 | F1734: 46284 | G1734: 7407 | H1734: 7407 | I1734: 64 | J1734: 6.1388 | K1734: Received | L1734: =INDEX(Items!$C$2:$C$117,MATCH(B1734,Items!$A$2:$A$117,0)) | M1734: =INDEX(Items!$E$2:$E$117,MATCH(B1734,Items!$A$2:$A$117,0)) | N1734: =TEXT(D1734,"yyyy-mm") | O1734: =G1734*J1734 | P1734: =(J1734-M1734)*G1734 | Q1734: =IF(K1734="Received",1,0) | R1734: =IF(Q1734=1,F1734-D1734,0) | S1734: =IF(Q1734=1,IF(F1734<=E1734,1,0),0) | T1734: =IF(Q1734=1,IF(H1734>=G1734,1,0),0) | U1734: =S1734*T1734 | V1734: =IF(Q1734=1,MAX(0,F1734-E1734),0)
A1735: PO101026 | B1735: CMD-0046 | C1735: S05 | D1735: 46193 | E1735: 46298 | G1735: 8569 | H1735: 0 | I1735: 0 | J1735: 10.8871 | K1735: Open | L1735: =INDEX(Items!$C$2:$C$117,MATCH(B1735,Items!$A$2:$A$117,0)) | M1735: =INDEX(Items!$E$2:$E$117,MATCH(B1735,Items!$A$2:$A$117,0)) | N1735: =TEXT(D1735,"yyyy-mm") | O1735: =G1735*J1735 | P1735: =(J1735-M1735)*G1735 | Q1735: =IF(K1735="Received",1,0) | R1735: =IF(Q1735=1,F1735-D1735,0) | S1735: =IF(Q1735=1,IF(F1735<=E1735,1,0),0) | T1735: =IF(Q1735=1,IF(H1735>=G1735,1,0),0) | U1735: =S1735*T1735 | V1735: =IF(Q1735=1,MAX(0,F1735-E1735),0)
A1736: PO100260 | B1736: CMD-0011 | C1736: S07 | D1736: 46193 | E1736: 46284 | F1736: 46284 | G1736: 3817 | H1736: 3817 | I1736: 37 | J1736: 9.5344 | K1736: Received | L1736: =INDEX(Items!$C$2:$C$117,MATCH(B1736,Items!$A$2:$A$117,0)) | M1736: =INDEX(Items!$E$2:$E$117,MATCH(B1736,Items!$A$2:$A$117,0)) | N1736: =TEXT(D1736,"yyyy-mm") | O1736: =G1736*J1736 | P1736: =(J1736-M1736)*G1736 | Q1736: =IF(K1736="Received",1,0) | R1736: =IF(Q1736=1,F1736-D1736,0) | S1736: =IF(Q1736=1,IF(F1736<=E1736,1,0),0) | T1736: =IF(Q1736=1,IF(H1736>=G1736,1,0),0) | U1736: =S1736*T1736 | V1736: =IF(Q1736=1,MAX(0,F1736-E1736),0)
A1737: PO101416 | B1737: CMD-0074 | C1737: S10 | D1737: 46193 | E1737: 46221 | F1737: 46221 | G1737: 47647 | H1737: 47647 | I1737: 49 | J1737: 0.3601 | K1737: Received | L1737: =INDEX(Items!$C$2:$C$117,MATCH(B1737,Items!$A$2:$A$117,0)) | M1737: =INDEX(Items!$E$2:$E$117,MATCH(B1737,Items!$A$2:$A$117,0)) | N1737: =TEXT(D1737,"yyyy-mm") | O1737: =G1737*J1737 | P1737: =(J1737-M1737)*G1737 | Q1737: =IF(K1737="Received",1,0) | R1737: =IF(Q1737=1,F1737-D1737,0) | S1737: =IF(Q1737=1,IF(F1737<=E1737,1,0),0) | T1737: =IF(Q1737=1,IF(H1737>=G1737,1,0),0) | U1737: =S1737*T1737 | V1737: =IF(Q1737=1,MAX(0,F1737-E1737),0)
A1738: PO101552 | B1738: CMD-0082 | C1738: S01 | D1738: 46193 | E1738: 46207 | F1738: 46207 | G1738: 10170 | H1738: 10170 | I1738: 24 | J1738: 2.3896 | K1738: Received | L1738: =INDEX(Items!$C$2:$C$117,MATCH(B1738,Items!$A$2:$A$117,0)) | M1738: =INDEX(Items!$E$2:$E$117,MATCH(B1738,Items!$A$2:$A$117,0)) | N1738: =TEXT(D1738,"yyyy-mm") | O1738: =G1738*J1738 | P1738: =(J1738-M1738)*G1738 | Q1738: =IF(K1738="Received",1,0) | R1738: =IF(Q1738=1,F1738-D1738,0) | S1738: =IF(Q1738=1,IF(F1738<=E1738,1,0),0) | T1738: =IF(Q1738=1,IF(H1738>=G1738,1,0),0) | U1738: =S1738*T1738 | V1738: =IF(Q1738=1,MAX(0,F1738-E1738),0)
A1739: PO100092 | B1739: CMD-0004 | C1739: S07 | D1739: 46193 | E1739: 46284 | F1739: 46281 | G1739: 3901 | H1739: 3901 | I1739: 30 | J1739: 4.779 | K1739: Received | L1739: =INDEX(Items!$C$2:$C$117,MATCH(B1739,Items!$A$2:$A$117,0)) | M1739: =INDEX(Items!$E$2:$E$117,MATCH(B1739,Items!$A$2:$A$117,0)) | N1739: =TEXT(D1739,"yyyy-mm") | O1739: =G1739*J1739 | P1739: =(J1739-M1739)*G1739 | Q1739: =IF(K1739="Received",1,0) | R1739: =IF(Q1739=1,F1739-D1739,0) | S1739: =IF(Q1739=1,IF(F1739<=E1739,1,0),0) | T1739: =IF(Q1739=1,IF(H1739>=G1739,1,0),0) | U1739: =S1739*T1739 | V1739: =IF(Q1739=1,MAX(0,F1739-E1739),0)
A1740: PO100978 | B1740: CMD-0044 | C1740: S05 | D1740: 46194 | E1740: 46299 | G1740: 8479 | H1740: 0 | I1740: 0 | J1740: 11.9171 | K1740: Open | L1740: =INDEX(Items!$C$2:$C$117,MATCH(B1740,Items!$A$2:$A$117,0)) | M1740: =INDEX(Items!$E$2:$E$117,MATCH(B1740,Items!$A$2:$A$117,0)) | N1740: =TEXT(D1740,"yyyy-mm") | O1740: =G1740*J1740 | P1740: =(J1740-M1740)*G1740 | Q1740: =IF(K1740="Received",1,0) | R1740: =IF(Q1740=1,F1740-D1740,0) | S1740: =IF(Q1740=1,IF(F1740<=E1740,1,0),0) | T1740: =IF(Q1740=1,IF(H1740>=G1740,1,0),0) | U1740: =S1740*T1740 | V1740: =IF(Q1740=1,MAX(0,F1740-E1740),0)
A1741: PO100312 | B1741: CMD-0014 | C1741: S03 | D1741: 46194 | E1741: 46327 | G1741: 4934 | H1741: 0 | I1741: 0 | J1741: 14.8916 | K1741: Open | L1741: =INDEX(Items!$C$2:$C$117,MATCH(B1741,Items!$A$2:$A$117,0)) | M1741: =INDEX(Items!$E$2:$E$117,MATCH(B1741,Items!$A$2:$A$117,0)) | N1741: =TEXT(D1741,"yyyy-mm") | O1741: =G1741*J1741 | P1741: =(J1741-M1741)*G1741 | Q1741: =IF(K1741="Received",1,0) | R1741: =IF(Q1741=1,F1741-D1741,0) | S1741: =IF(Q1741=1,IF(F1741<=E1741,1,0),0) | T1741: =IF(Q1741=1,IF(H1741>=G1741,1,0),0) | U1741: =S1741*T1741 | V1741: =IF(Q1741=1,MAX(0,F1741-E1741),0)
A1742: PO100116 | B1742: CMD-0005 | C1742: S07 | D1742: 46194 | E1742: 46285 | F1742: 46285 | G1742: 4634 | H1742: 4634 | I1742: 32 | J1742: 6.6434 | K1742: Received | L1742: =INDEX(Items!$C$2:$C$117,MATCH(B1742,Items!$A$2:$A$117,0)) | M1742: =INDEX(Items!$E$2:$E$117,MATCH(B1742,Items!$A$2:$A$117,0)) | N1742: =TEXT(D1742,"yyyy-mm") | O1742: =G1742*J1742 | P1742: =(J1742-M1742)*G1742 | Q1742: =IF(K1742="Received",1,0) | R1742: =IF(Q1742=1,F1742-D1742,0) | S1742: =IF(Q1742=1,IF(F1742<=E1742,1,0),0) | T1742: =IF(Q1742=1,IF(H1742>=G1742,1,0),0) | U1742: =S1742*T1742 | V1742: =IF(Q1742=1,MAX(0,F1742-E1742),0)
A1743: PO101102 | B1743: CMD-0050 | C1743: S10 | D1743: 46194 | E1743: 46222 | F1743: 46231 | G1743: 91857 | H1743: 91857 | I1743: 85 | J1743: 0.0772 | K1743: Received | L1743: =INDEX(Items!$C$2:$C$117,MATCH(B1743,Items!$A$2:$A$117,0)) | M1743: =INDEX(Items!$E$2:$E$117,MATCH(B1743,Items!$A$2:$A$117,0)) | N1743: =TEXT(D1743,"yyyy-mm") | O1743: =G1743*J1743 | P1743: =(J1743-M1743)*G1743 | Q1743: =IF(K1743="Received",1,0) | R1743: =IF(Q1743=1,F1743-D1743,0) | S1743: =IF(Q1743=1,IF(F1743<=E1743,1,0),0) | T1743: =IF(Q1743=1,IF(H1743>=G1743,1,0),0) | U1743: =S1743*T1743 | V1743: =IF(Q1743=1,MAX(0,F1743-E1743),0)
A1744: PO101140 | B1744: CMD-0052 | C1744: S01 | D1744: 46194 | E1744: 46215 | F1744: 46214 | G1744: 126954 | H1744: 126954 | I1744: 261 | J1744: 0.2076 | K1744: Received | L1744: =INDEX(Items!$C$2:$C$117,MATCH(B1744,Items!$A$2:$A$117,0)) | M1744: =INDEX(Items!$E$2:$E$117,MATCH(B1744,Items!$A$2:$A$117,0)) | N1744: =TEXT(D1744,"yyyy-mm") | O1744: =G1744*J1744 | P1744: =(J1744-M1744)*G1744 | Q1744: =IF(K1744="Received",1,0) | R1744: =IF(Q1744=1,F1744-D1744,0) | S1744: =IF(Q1744=1,IF(F1744<=E1744,1,0),0) | T1744: =IF(Q1744=1,IF(H1744>=G1744,1,0),0) | U1744: =S1744*T1744 | V1744: =IF(Q1744=1,MAX(0,F1744-E1744),0)
A1745: PO101452 | B1745: CMD-0077 | C1745: S01 | D1745: 46194 | E1745: 46208 | F1745: 46207 | G1745: 4540 | H1745: 4540 | I1745: 6 | J1745: 9.0125 | K1745: Received | L1745: =INDEX(Items!$C$2:$C$117,MATCH(B1745,Items!$A$2:$A$117,0)) | M1745: =INDEX(Items!$E$2:$E$117,MATCH(B1745,Items!$A$2:$A$117,0)) | N1745: =TEXT(D1745,"yyyy-mm") | O1745: =G1745*J1745 | P1745: =(J1745-M1745)*G1745 | Q1745: =IF(K1745="Received",1,0) | R1745: =IF(Q1745=1,F1745-D1745,0) | S1745: =IF(Q1745=1,IF(F1745<=E1745,1,0),0) | T1745: =IF(Q1745=1,IF(H1745>=G1745,1,0),0) | U1745: =S1745*T1745 | V1745: =IF(Q1745=1,MAX(0,F1745-E1745),0)
A1746: PO101710 | B1746: CMD-0093 | C1746: S08 | D1746: 46194 | E1746: 46271 | F1746: 46271 | G1746: 717 | H1746: 717 | I1746: 11 | J1746: 61.1923 | K1746: Received | L1746: =INDEX(Items!$C$2:$C$117,MATCH(B1746,Items!$A$2:$A$117,0)) | M1746: =INDEX(Items!$E$2:$E$117,MATCH(B1746,Items!$A$2:$A$117,0)) | N1746: =TEXT(D1746,"yyyy-mm") | O1746: =G1746*J1746 | P1746: =(J1746-M1746)*G1746 | Q1746: =IF(K1746="Received",1,0) | R1746: =IF(Q1746=1,F1746-D1746,0) | S1746: =IF(Q1746=1,IF(F1746<=E1746,1,0),0) | T1746: =IF(Q1746=1,IF(H1746>=G1746,1,0),0) | U1746: =S1746*T1746 | V1746: =IF(Q1746=1,MAX(0,F1746-E1746),0)
A1747: PO101952 | B1747: CMD-0107 | C1747: S09 | D1747: 46195 | E1747: 46216 | F1747: 46215 | G1747: 1165 | H1747: 1165 | I1747: 6 | J1747: 7.1585 | K1747: Received | L1747: =INDEX(Items!$C$2:$C$117,MATCH(B1747,Items!$A$2:$A$117,0)) | M1747: =INDEX(Items!$E$2:$E$117,MATCH(B1747,Items!$A$2:$A$117,0)) | N1747: =TEXT(D1747,"yyyy-mm") | O1747: =G1747*J1747 | P1747: =(J1747-M1747)*G1747 | Q1747: =IF(K1747="Received",1,0) | R1747: =IF(Q1747=1,F1747-D1747,0) | S1747: =IF(Q1747=1,IF(F1747<=E1747,1,0),0) | T1747: =IF(Q1747=1,IF(H1747>=G1747,1,0),0) | U1747: =S1747*T1747 | V1747: =IF(Q1747=1,MAX(0,F1747-E1747),0)
A1748: PO100564 | B1748: CMD-0025 | C1748: S02 | D1748: 46195 | E1748: 46251 | F1748: 46250 | G1748: 1017 | H1748: 1017 | I1748: 4 | J1748: 10.8356 | K1748: Received | L1748: =INDEX(Items!$C$2:$C$117,MATCH(B1748,Items!$A$2:$A$117,0)) | M1748: =INDEX(Items!$E$2:$E$117,MATCH(B1748,Items!$A$2:$A$117,0)) | N1748: =TEXT(D1748,"yyyy-mm") | O1748: =G1748*J1748 | P1748: =(J1748-M1748)*G1748 | Q1748: =IF(K1748="Received",1,0) | R1748: =IF(Q1748=1,F1748-D1748,0) | S1748: =IF(Q1748=1,IF(F1748<=E1748,1,0),0) | T1748: =IF(Q1748=1,IF(H1748>=G1748,1,0),0) | U1748: =S1748*T1748 | V1748: =IF(Q1748=1,MAX(0,F1748-E1748),0)
A1749: PO101782 | B1749: CMD-0096 | C1749: S09 | D1749: 46195 | E1749: 46216 | F1749: 46215 | G1749: 874 | H1749: 874 | I1749: 2 | J1749: 6.6126 | K1749: Received | L1749: =INDEX(Items!$C$2:$C$117,MATCH(B1749,Items!$A$2:$A$117,0)) | M1749: =INDEX(Items!$E$2:$E$117,MATCH(B1749,Items!$A$2:$A$117,0)) | N1749: =TEXT(D1749,"yyyy-mm") | O1749: =G1749*J1749 | P1749: =(J1749-M1749)*G1749 | Q1749: =IF(K1749="Received",1,0) | R1749: =IF(Q1749=1,F1749-D1749,0) | S1749: =IF(Q1749=1,IF(F1749<=E1749,1,0),0) | T1749: =IF(Q1749=1,IF(H1749>=G1749,1,0),0) | U1749: =S1749*T1749 | V1749: =IF(Q1749=1,MAX(0,F1749-E1749),0)
A1750: PO101864 | B1750: CMD-0101 | C1750: S09 | D1750: 46195 | E1750: 46216 | F1750: 46215 | G1750: 4459 | H1750: 4459 | I1750: 16 | J1750: 3.811 | K1750: Received | L1750: =INDEX(Items!$C$2:$C$117,MATCH(B1750,Items!$A$2:$A$117,0)) | M1750: =INDEX(Items!$E$2:$E$117,MATCH(B1750,Items!$A$2:$A$117,0)) | N1750: =TEXT(D1750,"yyyy-mm") | O1750: =G1750*J1750 | P1750: =(J1750-M1750)*G1750 | Q1750: =IF(K1750="Received",1,0) | R1750: =IF(Q1750=1,F1750-D1750,0) | S1750: =IF(Q1750=1,IF(F1750<=E1750,1,0),0) | T1750: =IF(Q1750=1,IF(H1750>=G1750,1,0),0) | U1750: =S1750*T1750 | V1750: =IF(Q1750=1,MAX(0,F1750-E1750),0)
A1751: PO101801 | B1751: CMD-0097 | C1751: S09 | D1751: 46196 | E1751: 46217 | F1751: 46216 | G1751: 571 | H1751: 571 | I1751: 4 | J1751: 9.5481 | K1751: Received | L1751: =INDEX(Items!$C$2:$C$117,MATCH(B1751,Items!$A$2:$A$117,0)) | M1751: =INDEX(Items!$E$2:$E$117,MATCH(B1751,Items!$A$2:$A$117,0)) | N1751: =TEXT(D1751,"yyyy-mm") | O1751: =G1751*J1751 | P1751: =(J1751-M1751)*G1751 | Q1751: =IF(K1751="Received",1,0) | R1751: =IF(Q1751=1,F1751-D1751,0) | S1751: =IF(Q1751=1,IF(F1751<=E1751,1,0),0) | T1751: =IF(Q1751=1,IF(H1751>=G1751,1,0),0) | U1751: =S1751*T1751 | V1751: =IF(Q1751=1,MAX(0,F1751-E1751),0)
A1752: PO101615 | B1752: CMD-0089 | C1752: S01 | D1752: 46197 | E1752: 46211 | F1752: 46211 | G1752: 580 | H1752: 580 | I1752: 3 | J1752: 9.7747 | K1752: Received | L1752: =INDEX(Items!$C$2:$C$117,MATCH(B1752,Items!$A$2:$A$117,0)) | M1752: =INDEX(Items!$E$2:$E$117,MATCH(B1752,Items!$A$2:$A$117,0)) | N1752: =TEXT(D1752,"yyyy-mm") | O1752: =G1752*J1752 | P1752: =(J1752-M1752)*G1752 | Q1752: =IF(K1752="Received",1,0) | R1752: =IF(Q1752=1,F1752-D1752,0) | S1752: =IF(Q1752=1,IF(F1752<=E1752,1,0),0) | T1752: =IF(Q1752=1,IF(H1752>=G1752,1,0),0) | U1752: =S1752*T1752 | V1752: =IF(Q1752=1,MAX(0,F1752-E1752),0)
A1753: PO100703 | B1753: CMD-0031 | C1753: S01 | D1753: 46197 | E1753: 46225 | F1753: 46222 | G1753: 533 | H1753: 533 | I1753: 1 | J1753: 9.9807 | K1753: Received | L1753: =INDEX(Items!$C$2:$C$117,MATCH(B1753,Items!$A$2:$A$117,0)) | M1753: =INDEX(Items!$E$2:$E$117,MATCH(B1753,Items!$A$2:$A$117,0)) | N1753: =TEXT(D1753,"yyyy-mm") | O1753: =G1753*J1753 | P1753: =(J1753-M1753)*G1753 | Q1753: =IF(K1753="Received",1,0) | R1753: =IF(Q1753=1,F1753-D1753,0) | S1753: =IF(Q1753=1,IF(F1753<=E1753,1,0),0) | T1753: =IF(Q1753=1,IF(H1753>=G1753,1,0),0) | U1753: =S1753*T1753 | V1753: =IF(Q1753=1,MAX(0,F1753-E1753),0)
... A1758: PO101812 | B1758: CMD-0098 | C1758: S09 | D1758: 46205 | E1758: 46226 | F1758: 46223 | G1758: 781 | H1758: 781 | I1758: 2 | J1758: 7.416 | K1758: Received | L1758: =INDEX(Items!$C$2:$C$117,MATCH(B1758,Items!$A$2:$A$117,0)) | M1758: =INDEX(Items!$E$2:$E$117,MATCH(B1758,Items!$A$2:$A$117,0)) | N1758: =TEXT(D1758,"yyyy-mm") | O1758: =G1758*J1758 | P1758: =(J1758-M1758)*G1758 | Q1758: =IF(K1758="Received",1,0) | R1758: =IF(Q1758=1,F1758-D1758,0) | S1758: =IF(Q1758=1,IF(F1758<=E1758,1,0),0) | T1758: =IF(Q1758=1,IF(H1758>=G1758,1,0),0) | U1758: =S1758*T1758 | V1758: =IF(Q1758=1,MAX(0,F1758-E1758),0)
A1759: PO100908 | B1759: CMD-0041 | C1759: S05 | D1759: 46207 | E1759: 46312 | G1759: 1137 | H1759: 0 | I1759: 0 | J1759: 5.7989 | K1759: Open | L1759: =INDEX(Items!$C$2:$C$117,MATCH(B1759,Items!$A$2:$A$117,0)) | M1759: =INDEX(Items!$E$2:$E$117,MATCH(B1759,Items!$A$2:$A$117,0)) | N1759: =TEXT(D1759,"yyyy-mm") | O1759: =G1759*J1759 | P1759: =(J1759-M1759)*G1759 | Q1759: =IF(K1759="Received",1,0) | R1759: =IF(Q1759=1,F1759-D1759,0) | S1759: =IF(Q1759=1,IF(F1759<=E1759,1,0),0) | T1759: =IF(Q1759=1,IF(H1759>=G1759,1,0),0) | U1759: =S1759*T1759 | V1759: =IF(Q1759=1,MAX(0,F1759-E1759),0)
A1760: PO101359 | B1760: CMD-0068 | C1760: S01 | D1760: 46210 | E1760: 46231 | F1760: 46231 | G1760: 38226 | H1760: 38226 | I1760: 77 | J1760: 0.1609 | K1760: Received | L1760: =INDEX(Items!$C$2:$C$117,MATCH(B1760,Items!$A$2:$A$117,0)) | M1760: =INDEX(Items!$E$2:$E$117,MATCH(B1760,Items!$A$2:$A$117,0)) | N1760: =TEXT(D1760,"yyyy-mm") | O1760: =G1760*J1760 | P1760: =(J1760-M1760)*G1760 | Q1760: =IF(K1760="Received",1,0) | R1760: =IF(Q1760=1,F1760-D1760,0) | S1760: =IF(Q1760=1,IF(F1760<=E1760,1,0),0) | T1760: =IF(Q1760=1,IF(H1760>=G1760,1,0),0) | U1760: =S1760*T1760 | V1760: =IF(Q1760=1,MAX(0,F1760-E1760),0)
A1761: PO102014 | B1761: CMD-0114 | C1761: S12 | D1761: 46217 | E1761: 46224 | F1761: 46224 | G1761: 15210 | H1761: 15210 | I1761: 13 | J1761: 0.3534 | K1761: Received | L1761: =INDEX(Items!$C$2:$C$117,MATCH(B1761,Items!$A$2:$A$117,0)) | M1761: =INDEX(Items!$E$2:$E$117,MATCH(B1761,Items!$A$2:$A$117,0)) | N1761: =TEXT(D1761,"yyyy-mm") | O1761: =G1761*J1761 | P1761: =(J1761-M1761)*G1761 | Q1761: =IF(K1761="Received",1,0) | R1761: =IF(Q1761=1,F1761-D1761,0) | S1761: =IF(Q1761=1,IF(F1761<=E1761,1,0),0) | T1761: =IF(Q1761=1,IF(H1761>=G1761,1,0),0) | U1761: =S1761*T1761 | V1761: =IF(Q1761=1,MAX(0,F1761-E1761),0)
A1762: PO101639 | B1762: CMD-0090 | C1762: S01 | D1762: 46218 | E1762: 46232 | F1762: 46229 | G1762: 4687 | H1762: 4687 | I1762: 12 | J1762: 7.1997 | K1762: Received | L1762: =INDEX(Items!$C$2:$C$117,MATCH(B1762,Items!$A$2:$A$117,0)) | M1762: =INDEX(Items!$E$2:$E$117,MATCH(B1762,Items!$A$2:$A$117,0)) | N1762: =TEXT(D1762,"yyyy-mm") | O1762: =G1762*J1762 | P1762: =(J1762-M1762)*G1762 | Q1762: =IF(K1762="Received",1,0) | R1762: =IF(Q1762=1,F1762-D1762,0) | S1762: =IF(Q1762=1,IF(F1762<=E1762,1,0),0) | T1762: =IF(Q1762=1,IF(H1762>=G1762,1,0),0) | U1762: =S1762*T1762 | V1762: =IF(Q1762=1,MAX(0,F1762-E1762),0)
A1763: PO100517 | B1763: CMD-0023 | C1763: S04 | D1763: 46218 | E1763: 46288 | F1763: 46287 | G1763: 3796 | H1763: 3796 | I1763: 34 | J1763: 9.064 | K1763: Received | L1763: =INDEX(Items!$C$2:$C$117,MATCH(B1763,Items!$A$2:$A$117,0)) | M1763: =INDEX(Items!$E$2:$E$117,MATCH(B1763,Items!$A$2:$A$117,0)) | N1763: =TEXT(D1763,"yyyy-mm") | O1763: =G1763*J1763 | P1763: =(J1763-M1763)*G1763 | Q1763: =IF(K1763="Received",1,0) | R1763: =IF(Q1763=1,F1763-D1763,0) | S1763: =IF(Q1763=1,IF(F1763<=E1763,1,0),0) | T1763: =IF(Q1763=1,IF(H1763>=G1763,1,0),0) | U1763: =S1763*T1763 | V1763: =IF(Q1763=1,MAX(0,F1763-E1763),0)
A1764: PO100189 | B1764: CMD-0008 | C1764: S03 | D1764: 46218 | E1764: 46351 | G1764: 1551 | H1764: 0 | I1764: 0 | J1764: 27.9188 | K1764: Open | L1764: =INDEX(Items!$C$2:$C$117,MATCH(B1764,Items!$A$2:$A$117,0)) | M1764: =INDEX(Items!$E$2:$E$117,MATCH(B1764,Items!$A$2:$A$117,0)) | N1764: =TEXT(D1764,"yyyy-mm") | O1764: =G1764*J1764 | P1764: =(J1764-M1764)*G1764 | Q1764: =IF(K1764="Received",1,0) | R1764: =IF(Q1764=1,F1764-D1764,0) | S1764: =IF(Q1764=1,IF(F1764<=E1764,1,0),0) | T1764: =IF(Q1764=1,IF(H1764>=G1764,1,0),0) | U1764: =S1764*T1764 | V1764: =IF(Q1764=1,MAX(0,F1764-E1764),0)
...
